Workbook

Sheet M1
A1: ALKAMO — M1
A2: N° | B2: THÈME | C2: MOTS
A3: 1 | B3: VÊTEMENT | C3: =COUNTA(M1_mots!A3:A5000) -> 858
A4: 2 | B4: CHASSE ET PECHE | C4: =COUNTA(M1_mots!B3:B5000) -> 905
A5: 3 | B5: LANGUE | C5: =COUNTA(M1_mots!C3:C5000) -> 559
A6: 4 | B6: MAMMIFÈRE | C6: =COUNTA(M1_mots!D3:D5000) -> 600
A7: 5 | B7: TRANSPORT | C7: =COUNTA(M1_mots!E3:E5000) -> 803
A8: 6 | B8: ÉCONOMIE | C8: =COUNTA(M1_mots!F3:F5000) -> 666
A9: 7 | B9: SPORT | C9: =COUNTA(M1_mots!G3:G5000) -> 678
A10: 8 | B10: RELIGION | C10: =COUNTA(M1_mots!H3:H5000) -> 691
A11: 9 | B11: ÉCOLE | C11: =COUNTA(M1_mots!I3:I5000) -> 468
A12: 10 | B12: OUTIL ET MÉTIER | C12: =COUNTA(M1_mots!J3:J5000) -> 837
A13: 11 | B13: POLITIQUE | C13: =COUNTA(M1_mots!K3:K5000) -> 562
A14: 12 | B14: MUSIQUE | C14: =COUNTA(M1_mots!L3:L5000) -> 722
A15: 13 | B15: MINÉRAL | C15: =COUNTA(M1_mots!M3:M5000) -> 723
A16: 14 | B16: MESURE ET INSTRUMENT | C16: =COUNTA(M1_mots!N3:N5000) -> 810
A17: 15 | B17: ARTISANAT | C17: =COUNTA(M1_mots!O3:O5000) -> 679
A18: 16 | B18: FRUIT | C18: =COUNTA(M1_mots!P3:P5000) -> 603
A19: 17 | B19: ARBRE | C19: =COUNTA(M1_mots!Q3:Q5000) -> 502
A20: 18 | B20: MÉDECINE | C20: =COUNTA(M1_mots!R3:R5000) -> 809
A21: 19 | B21: BÂTIMENT | C21: =COUNTA(M1_mots!S3:S5000) -> 936
A22: 20 | B22: PHYSIQUE | C22: =COUNTA(M1_mots!T3:T5000) -> 671
A23: TOTAL | C23: =SUM(C3:C22) -> 14082

Sheet M1_mots
A1: VÊTEMENT | B1: CHASSE ET PECHE | C1: LANGUE | D1: MAMMIFÈRE | E1: TRANSPORT | F1: ÉCONOMIE | G1: SPORT | H1: RELIGION | I1: ÉCOLE | J1: OUTIL ET MÉTIER | K1: POLITIQUE | L1: MUSIQUE | M1: MINÉRAL | N1: MESURE ET INSTRUMENT | O1: ARTISANAT | P1: FRUIT | Q1: ARBRE | R1: MÉDECINE | S1: BÂTIMENT | T1: PHYSIQUE
A2: =COUNTA(A3:A5000) -> 858 | B2: =COUNTA(B3:B5000) -> 905 | C2: =COUNTA(C3:C5000) -> 559 | D2: =COUNTA(D3:D5000) -> 600 | E2: =COUNTA(E3:E5000) -> 803 | F2: =COUNTA(F3:F5000) -> 666 | G2: =COUNTA(G3:G5000) -> 678 | H2: =COUNTA(H3:H5000) -> 691 | ... T2: =COUNTA(T3:T5000) -> 671
A3: ABACA | B3: BLEU | C3: ABAU | D3: ABOYER | E3: ABONNEMENT | F3: ACCUMULER | G3: ACCELERER | H3: ABBAYE | I3: ABSENCE | J3: ACCESSOIRE | K3: ABDICATION | L3: ABOIEMENT | M3: ABRI | N3: ABATTEMENT | O3: ABRASH | P3: ABALONE | Q3: ABATTAGE | R3: ABCES | S3: ABATTOIR | T3: ABDOMEN
A4: ABAYA | B4: ABAIT | C4: ACCENT | D4: ACCOUPLER | E4: ACCELERER | F4: ACHAT | G4: ACROBATIE | H4: ABBE | I4: ACADEMIE | J4: ACCORDEUR | K4: ABDIQUER | L4: ACCORD | M4: ABRUPT | N4: ABORDABLE | O4: ABREGE | P4: ABANDON | Q4: ABATTRE | R4: ABDOMEN | S4: ABBATIAL | T4: ACOUSTIQUE
A5: ACCROC | B5: ABATTIS | C5: ACCENTUER | D5: ADDAX | E5: ACCIDENT | F5: ACQUISE | G5: ACROSPORT | H5: ABBESSE | I5: ACADEMIQUE | J5: ACIER | K5: ABSENT | L5: ACCORDEON | M5: ACAJOU | N5: ABSTINENCE | O5: ACHAT | P5: ABEILLES | Q5: ABEILLE | R5: ABOLIR | S5: ABBAYE | T5: ACTIF
A6: ACETATE | B6: ABATTRE | C6: ACRONYME | D6: AGILE | E6: ACCON | F6: ACQUIT | G6: ACTIF | H6: ABJURER | I6: ADEPTE | J6: ACTEUR | K6: ABSOLU | L6: ACCORDER | M6: ACERBE | N6: ACCALMIE | O6: ACRYLIQUE | P6: ABONDANCE | Q6: ABRICOT | R6: ABSORPTION | S6: ABOUTIR | T6: ACTION
A7: AGLET | B7: ABATURE | C7: ACTE | D7: AGNEAU | E7: ACCOSTER | F7: ACTIF | G7: ACTION | H7: ABLUTION | I7: ADMISSION | J7: ACTIF | K7: ABUS | L7: ACCORDEUR | M7: ACETAMIDE | N7: ACCORDAGE | O7: AFFINAGE | P7: ABONDANTE | Q7: ABRICOTIER | R7: ACADEMIE | T7: ACTIVITE
A8: AGNELIN | B8: ABECHER | C8: ADJECTIF | D8: AGOUTI | E8: ACHEMINER | F8: ACTION | G8: ACTIVITE | H8: ABSIDE | I8: ADRESSE | J8: ACTION | K8: ABUSER | L8: ACOUPHENE | M8: ACIDE | N8: ACETABULE | O8: AGATE | P8: ABRICOT | Q8: ABSINTHE | R8: ACCOUCHEUR | S8: ABRI | T8: ADROIT
A9: AGRAFE | B9: ABLIER | C9: ADVERBE | D9: AGRESTE | E9: ACTIONNER | F9: AFFAIRE | G9: ADVERSAIRE | H9: ABSOLUTION | I9: AGENDA | J9: ACTIVITE | K9: ACCESSION | L9: ACOUSTIQUE | M9: ACIER | N9: ACOUSTIQUE | O9: AGE | P9: ABRICOTIER | Q9: ACACIA | R9: ACCUEIL | S9: ABRIBUS | T9: AFFINITE
A10: AIGUILLE | B10: ABOIEMENT | C10: AFAR | D10: AILE | E10: ADVECTION | F10: AGENCE | G10: AEROBIC | H10: ABSOUDRE | I10: AGENT | J10: ACTUAIRE | K10: ACCORD | L10: ADAGI | M10: ACTINIUM | N10: AFFADIR | O10: AGENCE | P10: ACCAPARER | Q10: ACAJOU | R10: ACCUEILLIR | S10: ABRITER | T10: AGILE
A11: AJOURE | B11: ABOIS | C11: AFFIXE | D11: AISSELLE | E11: AERIEN | F11: AGENT | G11: AGILITE | H11: ABSOUTE | I11: AGREGAT | J11: ADAPTE | K11: ACRATIE | L11: AEROBIC | M11: ACTINOTE | N11: AFFAIBLIR | O11: AGENCEMENT | P11: ACCRA | Q11: ACCROCHER | R11: ACNE | S11: ABSIDE | T11: AGILITE
A12: AJUSTE | B12: ABORDER | C12: AINOU | D12: ALBINOS | E12: AERODYNE | F12: AGIO | G12: AGRIPPER | H12: ABSTENIR | I12: AGREGATIF | J12: AGENCE | K12: ACTION | L12: AFFETTO | M12: ADAMITE | N12: AGENCEMENT | O12: AGRAIRE | P12: ACHARNE | Q12: ADMIRER | R12: ACOUSIE | S12: ACADEMIE | T12: AIR
A13: AJUSTER | B13: ABOYEUR | C13: AKKADIEN | D13: ALLAITER | E13: AEROLITHE | F13: AGIOTAGE | G13: AIKIDO | H13: ABSTINENCE | I13: AGREGATION | J13: AGENT | K13: ACTIVER | L13: AFFUT | M13: ADULAIRE | N13: AIDE | O13: AIGUILLE | P13: ACHETEUR | Q13: AFFOUAGE | R13: ACUPUNCTUR | S13: ACCUEIL | T13: AIRE
A14: ALAISE | B14: ACASTE | C14: ALBANAIS | D14: ALLONGE | E14: AERONEF | F14: AGNEL | G14: AILIER | H14: ACEDIE | I14: AGREGE | J14: AGRONOME | K14: ACTIVISME | L14: AGADA | M14: AEROLITHE | N14: AIGUILLEE | O14: AJOURS | P14: ACIDE | Q14: AGRESTE | R14: ADMINISTRE | S14: ACHEVEMENT | T14: ALBEDO
A15: ALESE | B15: ACCIDENT | C15: ALEMANIQUE | D15: ALOUATE | E15: AEROPLANE | F15: AGREGAT | G15: ALPINISME | H15: ACHOURA | I15: ALPHABET | J15: AIGUILLE | K15: ACTIVISTE | L15: AGITEE | M15: AETITE | N15: AJUSTOIR | O15: ALANDIER | P15: ACIDITE | Q15: AGRICOLE | R15: ADOUCIR | S15: ACIERIE | T15: ALIMENTS
A16: ALPAGA | B16: ACCOUER | C16: ALGIQUE | D16: ALPAGA | E16: AEROPORT | F16: AGRICOLE | G16: AMATEUR | H16: ACOLYTE | I16: ALTERNANCE | J16: ANIMATEUR | K16: ACTUALITE | L16: AGOGO | M16: AGATE | N16: ALCOOMETRE | O16: ALCHIMIE | P16: ACQUET | Q16: AIE | R16: AFFECT | S16: ADOPTION | T16: ALLANT
A17: AMADIS | B17: ACCUL | C17: ALGOL | D17: AMNIOTE | E17: AEROSTAT | F17: AIDE | G17: AMICAL | H17: ADEPTE | I17: ANALYSE | J17: ANIMATION | K17: ADEPTE | L17: AIGU | M17: AIGLE | N17: ALENTIR | O17: ALFA | P17: ACTIONNAIR | Q17: AIRE | R17: AFFECTER | S17: AEROGARE | T17: ALLEGRE
A18: AMIANTE | B18: ACCUSATION | C18: ALGONQUIN | D18: ANDOUILLER | E18: AEROTRAIN | F18: AISANCE | G18: AMORTI | H18: ADHAN | I18: ANALYSER | J18: ANTIQUAIRE | K18: ADHERENT | L18: AILE | M18: AIGRE | N18: ALLEGER | O18: ALLIAGE | P18: AFFURER | Q18: AIRELLE | R18: AFFECTION | T18: ALLIAGE
A19: AMPLE | B19: ACHIGAN | C19: ALINEA | D19: ANE | E19: AIGUILLE | F19: ALENA | G19: AMUSEMENT | H19: ADHESION | I19: ANCIENNE | J19: APICULTEUR | K19: ADHESION | L19: AIR | M19: AIMANT | N19: ALTIMETRE | O19: ALOI | P19: AGNEAU | Q19: AJONC | R19: AGIR | S19: AEROPORT | T19: ALLOTROPIE
A20: ANGLAISE | B20: ACQUER | C20: ALLEMAND | D20: ANGLE | E20: AIR | F20: ALLOCATION | G20: ANNEAUX | H20: ADONAI | I20: ANNALES | J20: APPAREIL | K20: ADJONCTION | L20: ALARME | M20: AIRAIN | N20: ALTO | O20: ALUMINE | P20: AGRICULTEU | Q20: ALGEBRE | R20: AGREGE | S20: AFFINERIE | T20: AME
A21: ANGORA | B21: ADONNER | C21: ALLOPHONE | D21: ANGORA | E21: ALACRITE | F21: ALOI | G21: ANTIDOPAGE | H21: ADORATION | I21: ANNEE | J21: APPARITEUR | K21: ADMISSION | L21: ALBUM | M21: ALBATRE | N21: AMADOUER | O21: AMBRE | P21: AGRICULTUR | Q21: ALISIER | R21: AIDE | S21: AGENCER | T21: AMITIES
A22: ANORAK | B22: AERIEN | C22: ALPHABET | D22: ANIMAL | E22: ALLEGE | F22: ALTERATION | G22: APNEE | H22: ADORER | I22: ANNUAIRE | J22: APPRENTI | K22: ADOPTER | L22: ALLEGRO | M22: ALBITE | N22: AMBRE | O22: AMIDON | P22: AGRUME | Q22: AMANDIER | R22: AIDER | S22: AGORA | T22: AMORPHE
A23: ANTIMITE | B23: AFFUT | C23: ALSACIEN | D23: ANOA | E23: ALLEGRESSE | F23: AMENDE | G23: APNEISTE | H23: ADULATION | I23: APPLIQUER | J23: APTE | K23: ADOPTION | L23: ALTERATION | M23: ALBUGINE | N23: AME | O23: AMPHORE | P23: AIL | Q23: AMARANTE | R23: AIGUILLE | S23: AGRANDIR | T23: AMPERE
A24: APEX | B24: AFFUTER | C24: AMBIGUITE | D24: ANTENNE | E24: ALLURE | F24: AMENDER | G24: APPROPRIE | H24: AFFECTION | I24: APPRENANT | J24: APTITUDE | K24: ADOSSEUR | L24: ALTISTE | M24: ALBUGO | N24: AMORTIR | O24: ANNULAIRE | P24: ALIMENT | Q24: AMI | R24: AIR | S24: AGRICOLE | T24: ANALOGIE
A25: APPARAT | B25: AGRAINAGE | C25: AMHARIQUE | D25: ANTILOPE | E25: ALPINE | F25: AMORTIR | G25: AQUAGYM | H25: AGAPE | I25: APPRENDRE | J25: ARBITRE | K25: ADRESSE | L25: ALTO | M25: ALCALIN | N25: AMPERE | O25: ANTIMOINE | P25: ALKEKENGE | Q25: ANA | R25: AJUSTER | S25: ALCAZAR | T25: ANALYSE
A26: APPRET | B26: AGRENER | C26: ANATOMIE | D26: APPAT | E26: AMBULANCE | F26: AMPLEUR | G26: AQUAPLANE | H26: AGNOSTIQUE | I26: APPRENTI | J26: ARCHER | K26: ADROIT | L26: AMATI | M26: ALFENIDE | N26: AMPHORE | O26: APPLIQUER | P26: AMASSER | Q26: ARBORISTE | R26: ALCALOIDE | S26: ALE | T26: ANDROGYNE
A27: ARAMIDE | B27: AGRES | C27: ANAUDIE | D27: ARBORICOLE | E27: AMENAGE | F27: ANALYSE | G27: ARBALETE | H27: AMBON | I27: ARCHIVES | J27: ARCHET | K27: AFFAIRE | L27: AMBIANCE | M27: ALGUE | N27: AMPLEUR | O27: APPRENTI | P27: AMBITION | Q27: ARBOUSIER | R27: ALIENE | S27: ALLEE | T27: ANGLE
A28: ARCHAL | B28: AGRIFFER | C28: ANDINE | D28: ARETE | E28: AMPHIBIE | F28: ANALYSTE | G28: ARBITRAL | H28: AME | I28: ARGUMENTER | J28: ARCHITECTE | K28: AFFILIE | L28: AMPLE | M28: ALKALI | N28: ANA | O28: APPRET | P28: AMER | Q28: ARBRE | R28: ALIENISTE | S28: ALUNERIE | T28: ANIMAL
A29: ARMELINE | B29: AGUET | C29: ANDOKE | D29: ARRACHE | E29: ANE | F29: ANNALITE | G29: ARBITRE | H29: AMEN | I29: ART | J29: ARCHIVISTE | K29: AFFINITE | L29: AMPLI | M29: ALLOPHANE | N29: ANCRE | O29: ARCATURE | P29: AMINE | Q29: ARBUSTE | R29: ALLAITER | S29: AMBASSADE | T29: ANIMALES
A30: ARMET | B30: AGUICHER | C30: ANGLAIS | D30: ARRONDI | E30: ANGEVIN | F30: ANNUEL | G30: ARCHER | H30: AMIDA | I30: ARTICLE | J30: ARMURIER | K30: AGENCE | L30: AMPLIFIER | M30: ALMANDIN | N30: ANGLE | O30: ARCHE | P30: ANACARDIER | Q30: ARDENNE | R30: ALLERGIE | S30: AMBITIEUX | T30: ANIMER
A31: ARMOIRE | B31: AIGLEFIN | C31: ANGLOPHONE | D31: ATELE | E31: ANNEXE | F31: ANNUITE | G31: ARCHERIE | H31: AMISH | I31: ARTISTE | J31: ARRIMEUR | K31: AGILITE | L31: ANDALOUX | M31: ALMELEC | N31: ANGSTROM | O31: ARGENT | P31: ANANAS | Q31: ARGAN | R31: ALLOPATHE | S31: AMBITION | T31: ANNULAIRE
A32: ARMURE | B32: AIM | C32: ANTONYME | D32: ATTACHE | E32: ARBORER | F32: APPOINT | G32: ARENE | H32: AMOUR | I32: ASSIDU | J32: ARROSEUR | K32: AGITATION | L32: ANDANTE | M32: ALPAX | N32: ANNEE | O32: ARGENTURE | P32: API | Q32: ARGANIER | R32: ALLOPATHIE | S32: AMBULANCE
A33: ASTRAKAN | B33: AIN | C33: APEX | D33: AUROCHS | E33: ARCHE | F33: APPORT | G33: ARRIERE | H33: ANAGOGIE | I33: ASSIDUITE | J33: ART | K33: AGITER | L33: APPEAU | M33: ALPINISME | N33: ANNUEL | O33: ARGILE | P33: ARACHIDE | Q33: ARMURE | R33: ALVEOLE | S33: AMENAGER | T33: APPARENCE
A34: ATELIER | B34: ALAI | C34: APHASIE | D34: AVAHI | E34: ARMATEUR | F34: APPORTEUR | G34: ARTISTE | H34: ANATHEME | I34: ATELIER | J34: ARTISAN | K34: AGORA | L34: ARCHET | M34: ALTERITE | N34: APAISER | O34: ARGUE | P34: ARBOUSIER | Q34: ASPIC | R34: ALZHEIMER | S34: AMENDER | T34: APPDIGEST
A35: ATOUR | B35: ALAN | C35: APHONE | D35: AVANT | E35: ARPEGE | F35: ARGENT | G35: ATEMI | H35: ANCETRE | I35: ATLAS | J35: ARTISANAL | K35: AGRARIEN | L35: ARCON | M35: ALUMINE | N35: APERCU | O35: ARMURE | P35: ARBRE | Q35: AUBEPINE | R35: AMADOUER | S35: AMIENOISE | T35: APPOINT
A36: BABOUCHE | B36: ALEVIN | C36: APHONIE | D36: BABIROUSSA | E36: ARRET | F36: ARGENTIER | G36: ATHLETE | H36: ANGE | I36: ATTENTION | J36: ARTISANAT | K36: AGREGATION | L36: ARGOL | M36: ALUMINITE | N36: APPAREIL | O36: ARMURIER | P36: ARBUSTE | Q36: AULNE | R36: AMBULANCE | S36: AMIRAUTE | T36: APTE
A37: BACHE | B37: ALGUE | C37: APHTE | D37: BABOUIN | E37: ARROSEUSE | F37: ARPAILLEUR | G37: ATHLETIQUE | H37: ANGELOT | I37: AUTEUR | J37: ARTISTE | K37: AGREMENT | L37: ARIA | M37: ALUMINIUM | N37: APPEAU | O37: ART | P37: ARGENT | Q37: AUNE | R37: AMBULANCIE | S37: AMPHIBIE | T37: APTITUDE
A38: BALLERINE | B38: ALOSE | C38: APOSTROPHE | D38: BAI | E38: ARTERE | F38: ARRERAGES | G38: ATHLETISME | H38: ANGLICAN | I38: AUTORITE | J38: ASSIDU | K38: ALIENATION | L38: ARIETTE | M38: ALUN | N38: APTITUDE | O38: ARTIFICE | P38: ARILLE | Q38: AUTOMNE | S38: ANCIEN
A39: BALLET | B39: ALOSIER | C39: ARABE | D39: BAIJI | E39: ASCENSEUR | F39: ARRIERE | G39: ATTAQUANT | H39: ANIMISME | I39: AVIS | J39: ASSIDUITE | K39: ALLIAGE | L39: ARPEGE | M39: ALUNITE | N39: ARBITRAGE | O39: ARTISAN | P39: ARISTOCRAT | Q39: AVELINE | R39: AMELIORER | S39: ANIMALERIE | T39: ARISTOTE
A40: BANANE | B40: AMARRE | C40: ARGOT | D40: BALEINE | E40: ASTRONEF | F40: ARRIMAGE | G40: ATTELAGE | H40: ANIMISTE | I40: BAC | J40: ASSISTANT | K40: ALLIANCE | L40: ARRANGEUR | M40: AMBRE | N40: ARCHET | O40: ARTISANAL | P40: AROMATIQUE | Q40: AVOCAT | R40: AMINE | S40: ANNEXE | T40: ASPECT
A41: BANDANA | B41: AMARRER | C41: ARGOTIER | D41: BARBE | E41: ATTELAGE | F41: ASSAINIR | G41: AUTOMOBILE | H41: ANNATE | I41: BACHOT | J41: ASSURANCE | K41: ALLIE | L41: ART | M41: AMER | N41: ARDEUR | O41: ARTISANAT | P41: AROME | Q41: AZALEE | R41: AMPHETAMIN | S41: APPUYER | T41: ASTHENIE
A42: BANDEAU | B42: AMBLEUR | C42: ARGUMENTER | D42: BARBU | E42: ATTERRIR | F42: ASSIETTE | G42: AVIATION | H42: APOCALYPSE | I42: BAGAGE | J42: ASSUREUR | K42: AMBASSADE | L42: ARTICULER | M42: AMERES | N42: ARE | O42: ARTISTE | P42: ARRACHAGE | Q42: BADIANE | R42: AMPOULE | S42: AQUARIUM
A43: BANNETTE | B43: AMER | C43: ARMENIEN | D43: BARDOT | E43: AUTO | F43: ASSIGNAT | G43: AVIRON | H43: APOSTAT | I43: BAHUT | J43: ATELIER | K43: AMENDEMENT | L43: ARTISTE | M43: AMIANTE | N43: AREOMETRE | O43: ARTISTIQUE | P43: ARRIERESAI | Q43: BALAI | R43: ANALGESIQU | S43: AQUEDUC | T43: ATHLETE
A44: BAPTISTE | B44: AMIRAUTE | C44: ARTICLE | D44: BARIBAL | E44: AUTOBUS | F44: ASSOCIE | G44: BALLE | H44: APOSTATE | I44: BANC | J44: ATTIRAIL | K44: AMENDER | L44: ASSOURDIR | M44: AMPELITE | N44: ARPENT | O44: ASPIRER | P44: ASSAISONNE | Q44: BALSA | R44: ANALYSE | S44: ARCADE | T44: ATOME
A45: BAREGE | B45: AMORCAGE | C45: ARTICULER | D45: BARRIR | E45: AUTOCAR | F45: ASSURANCE | G45: BALLON | H45: APOTRE | I45: BEP | J45: AUDIT | K45: AMICALE | L45: ATONAL | M45: AMPHIBOLE | N45: ARPENTEUR | O45: ASSIETTE | P45: ASTRINGENT | Q45: BAMBOU | R45: ANATOMIE | S45: ARCHE | T45: ATOMIQUE
A46: BARRE | B46: AMORCE | C46: ASPERITE | D46: BAUDET | E46: AUTOGIRE | F46: ATELIER | G46: BANC | H46: ARCHE | I46: BILAN | J46: AUDITEUR | K46: AMNISTIE | L46: AUBADE | M46: ANDESINE | N46: ARRETER | O46: ATELIER | P46: ATOUT | Q46: BANANIER | R46: ANATOMIQUE | S46: ARCHITECTE | T46: ATOMISME
A47: BARRETTE | B47: AMORCER | C47: ASTRUC | D47: BEIGE | E47: AUTOMOBILE | F47: AUMONE | G47: BANDEROLE | H47: ARCHEVÊQUE | I47: BILINGUE | J47: AUTEUR | K47: ANALOGIE | L47: AUDITEUR | M47: ANDESITE | N47: ARTICLE | O47: ATTELLE | P47: AUBAINE | Q47: BAOBAB | R47: ANEMIE
A48: BAS | B48: AMURE | C48: ASTURIEN | D48: BEIRA | E48: AUTOMOTEUR | F48: AUREUS | G48: BAQUET | H48: ARDEUR | I48: BIZUT | J48: AUTOMATE | K48: ANALYSTE | L48: AUDITIF | M48: ANGLESITE | N48: ASPE | O48: AVANTBRAS | P48: AUBERGINE | Q48: BAR | R48: ANESTHESIE | S48: ARDOISE | T48: AUTORITE
A49: BASANE | B49: ANCHOIS | C49: ATTRIBUT | D49: BELER | E49: AUTONEIGE | F49: AUSTERITE | G49: BARRE | H49: ASCESE | I49: BIZUTER | J49: AVIATEUR | K49: ANARCHIE | L49: AUDITION | M49: ANGUILLE | N49: ASSAGIR | O49: AVIVOIR | Q49: BARRE | R49: ANESTHESIQ | S49: ARDOISERIE | T49: BACON
A50: BASIN | B50: ANGON | C50: AUXILIAIRE | D50: BELETTE | E50: AUTORAIL | F50: AVARE | G50: BASEBALL | H50: ASCETISME | I50: BOITE | J50: AVIATRICE | K50: ANARCHISME | L50: AULIQUE | M50: ANGULAIRE | N50: ASSOUPLIR | O50: AZULEJO | P50: AUTOMNE | Q50: BASSES | R50: ANIS | S50: ARENE | T50: BALEZE
A51: BASKET | B51: ANGUILLE | C51: AUYE | D51: BELIER | E51: AUTOROUTE | F51: AVARICE | G51: BASKET | H51: ASPIRATION | I51: BOURSE | J51: AVIRON | K51: ANOCRATIE | L51: AURA | M51: ANHYDRITE | N51: ASSOURDIR | O51: BADINE | P51: AVANTAGE | Q51: BAUME | R51: ANNEXE | S51: ARMATURE | T51: BARAQUE
A52: BASQUE | B52: ANIMAL | C52: AWA | D52: BELUGA | E52: AVANCER | F52: AVERS | G52: BASKETBALL | H52: ATHEE | I52: BOURSIER | J52: AVOCAT | K52: APARTHEID | L52: BAFFLE | M52: ANSE | N52: ASSURANCE | O52: BAGUETTE | P52: AVELINE | Q52: BEC | R52: ANSE | S52: ARMURERIE | T52: BARYCENTRE
A53: BASSINET | B53: ANIMAUX | C53: AWADHI | D53: BESTIAL | E53: AVENUE | F53: AVOIR | G53: BATON | H53: ATHEISME | I53: BRAILLE | J53: BACLER | K53: APOLITIQUE | L53: BAGLAMA | M53: ANTIMOINE | N53: ATOME | O53: BALAI | P53: AVOCATIER | Q53: BERGERE | R53: ANTALGIE | S53: ARRANGER | T53: BARYON
A54: BATAVIA | B54: ANTILOPE | C54: AYMARA | D54: BETE | E54: AVION | F54: BADWILL | G54: BATTANT | H54: ATMA | I54: BREVET | J54: BAGAGE | K54: ARBITRAIRE | L54: BALADEUR | M54: APATITE | N54: ATTELEE | O54: BALEINE | P54: AVOINE | Q54: BETE | R54: ANTIBIOTIQ | S54: ARSENAL | T54: BAVARD
A55: BATIK | B55: ANUER | C55: AZERI | D55: BEUGLER | E55: AVIONNETTE | F55: BAIL | G55: BATTE | H55: ATTENTE | I55: BRIMADE | J55: BAGAGISTE | K55: ARENE | L55: BALAFON | M55: APLITE | N55: ATTENDRIR | O55: BAMBOU | P55: BADIANE | Q55: BETEL | R55: ANTICANCER | S55: ART | T55: BEAU
A56: BATISTE | B56: APLET | C56: AZTEQUE | D56: BICHE | E56: AVISO | F56: BAISSE | G56: BATTRE | H56: AUMONE | I56: BROCHURE | J56: BAGNE | K56: ARMISTICE | L56: BALALAIKA | M56: APOTRE | N56: ATTENTION | O56: BANDAGE | P56: BAIE | Q56: BICHE | R56: ANTICOAGUL | S56: ARTICULER | T56: BICEPS
A57: BAVETTE | B57: APNEE | C57: BABIL | D57: BIPEDE | E57: AXEL | F57: BALANCE | G57: BIATHLON | H57: AUTEL | I57: BROSSE | J57: BAIGNEUR | K57: ARTIFICE | L57: BALAN | M57: APRE | N57: ATTENUER | O57: BARBOTINE | P57: BAIL | Q57: BIGARREAU | R57: ANTICORPS | S57: ARTIMON
A58: BAVOIR | B58: APPAT | C58: BALBUTIER | D58: BISON | E58: BAGAGE | F58: BALANCIER | G58: BICROSS | H58: AVATAR | I58: BUCHEUR | J58: BALADIN | K58: ASSEMBLEE | L58: BALLADE | M58: ARAGONITE | N58: ATTIEDIR | O58: BATIK | P58: BAISSER | Q58: BIOENERGET | R58: ANTIDEPRES | S58: ARTISTE | T58: BIOLOGIE
A59: BEGUIN | B59: APPATER | C59: BAMBARA | D59: BLAIR | E59: BAGNOLE | F59: BANCAIRE | G59: BILLARD | H59: AVE | I59: BUREAU | J59: BALAI | K59: ASTUCE | L59: BALLET | M59: ARDOISE | N59: AUDIMETRE | O59: BATON | P59: BANANE | Q59: BIOMASSE | R59: ANTIDOTE | S59: ASILE | T59: BIOLOGIQUE
A60: BEIGE | B60: APPEAU | C60: BANTOU | D60: BLAIREAU | E60: BALADEUSE | F60: BANCO | G60: BIRDIE | H60: AVIS | I60: BUVARD | J60: BALAYEUR | K60: ATTENTAT | L60: BANDE | M60: ARENITE | N60: AUDIOMETRE | O60: BEAU | P60: BANANIER | Q60: BIOME | R60: ANTIGENE | S60: ASSEMBLAGE
A61: BERET | B61: AQUARIUM | C61: BARAGOUIN | D61: BLANC | E61: BALANCELLE | F61: BANQUE | G61: BLOC | H61: BAHAI | I61: CABINET | J61: BANQUE | K61: ATTRACTION | L61: BANJO | M61: ARGENT | N61: AUGEE | O61: BEAUTE | P61: BASILIC | Q61: BLEU | R61: ANTIHISTAM | S61: ASSEMBLER | T61: BITUME
A62: BERMUDA | B62: AQUATIQUE | C62: BARAKI | D62: BLOND | E62: BALANDRE | F62: BANQUIER | G62: BOBSLEIGH | H62: BAPTEME | I62: CAHIER | J62: BANQUIER | K62: AUSTERITE | L62: BAR | M62: ARGILE | N62: AULNE | O62: BESACE | P62: BATTEUSE | Q62: BLEUET | R62: ANTIPSYCHO | S62: ASSEOIR | T62: BOHR
A63: BERTHE | B63: AQUE | C63: BARGU | D63: BOEUF | E63: BALEINIER | F63: BARATTAGE | G63: BOCCIA | H63: BAPTISER | I63: CALAME | J63: BARBIER | K63: AUTARCIE | L63: BARBAT | M63: ARGILEUSE | N63: AUNE | O63: BETTERAVE | P63: BEIGNET | Q63: BOA | R63: ANTISEPTIQ | S63: ATELIER | T63: BOSON
A64: BESACE | B64: ARAIGNEE | C64: BASIC | D64: BOIS | E64: BALISEUR | F64: BAREME | G64: BOIS | H64: BAPTISTE | I64: CALCUL | J64: BARMAN | K64: AUTOCRATIE | L64: BARRE | M64: ARGYROSE | N64: AUNEE | O64: BEURRE | P64: BENEFICIER | Q64: BOIRE | R64: ANTIVIRAL | S64: ATHANEE | T64: BOUCHE
A65: BIBI | B65: ARBALETE | C65: BASQUE | D65: BOITE | E65: BALLADE | F65: BARON | G65: BORNE | H65: BASILIEN | I65: CALCULER | J65: BARRE | K65: AUTONOME | L65: BARYTON | M65: ARIDE | N65: AUSTERITE | O65: BIERE | P65: BENIE | Q65: BOISE | R65: ANXIETE | S65: ATHENEE | T65: BRAS
A66: BICORNE | B66: ARC | C66: BAVARD | D66: BONDIR | E66: BALLON | F66: BAREMES | G66: BOTTE | H66: BASILIQUE | I66: CALEPIN | J66: BARREUR | K66: AUTORITE | L66: BASSE | M66: ARKOSE | N66: AVAL | O66: BIJOU | P66: BERGAMOTE | Q66: BOISEMENT | R66: AORTE | S66: ATRIUM | T66: BRILLER
A67: BIGOUDEN | B67: ARCHE | C67: BAVARDAGE | D67: BONGO | E67: BANLIEUE | F67: BESOINS | G67: BOTTER | H67: BEATIFIE | I67: CAMARADE | J67: BATELIER | K67: AUTORITES | L67: BASSET | M67: ARSENIC | N67: AVERTIR | O67: BIJOUTERIE | P67: BETAIL | Q67: BOISMORT | R67: APHASIE | S67: ATTIQUE | T67: BRUIT
A68: BIJOU | B68: ARCHER | C68: BAVARDE | D68: BONOBE | E68: BANNE | F68: BENEFICE | G68: BOULE | H68: BEATIFIER | I68: CAMPUS | J68: BATIMENT | K68: AVANTAGE | L68: BASSIN | M68: ARSENITE | N68: BADIN | O68: BIJOUTIER | P68: BETTERAVE | Q68: BOISSON | R68: APOTHICAIR | S68: AUBERGE | T68: BRUTAL
A69: BIKINI | B69: ARCTIQUE | C69: BAVARDER | D69: BONTO | E69: BAQUET | F69: BENEFIQUE | G69: BOULISME | H69: BEATITUDE | I69: CANCRE | J69: BATIR | K69: AVENEMENT | L69: BASSINET | M69: ASBESTE | N69: BAGUIER | O69: BISCUIT | P69: BEURRE | Q69: BON | R69: APPELER | S69: AUBETTE | T69: BUSTE
A70: BLANC | B70: ARDILLON | C70: BEC | D70: BORD | E70: BARBOTE | F70: BESANT | G70: BOWLING | H70: BENIR | I70: CANTINE | J70: BATISSEUR | K70: AVERTI | L70: BASSON | M70: ASPHALTE | N70: BAISSER | O70: BOIS | P70: BIEN | Q70: BONSAI | R70: APPENDICE | S70: AUDACIEUX | T70: CADAVRE
A71: BLAZER | B71: ARGENT | C71: BEGAYER | D71: BOSSE | E71: BARCASSE | F71: BESOIN | G71: BOXE | H71: BENIT | I71: CAP | J71: BATTEUR | K71: AVISE | L71: BAT | M71: ASSISE | N71: BALANCE | O71: BOISERIE | P71: BIENFAIT | Q71: BOSQUET | R71: APPRETER | S71: AUDIENCE | T71: CALME
A72: BLEU | B72: ARMATEUR | C72: BEGUE | D72: BOUC | E72: BARD | F72: BIEN | G72: BOXER | H72: BENITIER | I72: CAPACITE | J72: BEDANE | K72: AXIOCRATIE | L72: BATA | M72: ASTERIE | N72: BALISE | O72: BOISSON | P72: BIGARADE | Q72: BOSSE | R72: APPROCHE | S72: AUMONERIE | T72: CAPABLE
A73: BLOUSE | B73: ARME | C73: BENGALI | D73: BOUCHE | E73: BARGE | F73: BIENS | G73: BOYCOTT | H73: BIBLE | I73: CAPES | J73: BENEVOLE | K73: BANDE | L73: BATELET | M73: ASTEROIDE | N73: BALLOT | O73: BOLAIRE | P73: BIOSSON | Q73: BOUCHON | R73: AROMATHERA | S73: AUTEL | T73: CAPACITE
A74: BLOUSER | B74: ARMEE | C74: BERBERE | D74: BOULEDOGUE | E74: BARQUE | F74: BIFFAGE | G74: BRASSE | H74: BIBLIQUE | I74: CAPESIEN | J74: BERGER | K74: BARRE | L74: BATON | M74: ATACAMITE | N74: BAN | O74: BOTEH | P74: BLANC | Q74: BOULE | R74: ARRANGER | T74: CAPTEUR
A75: BLOUSON | B75: ARMEMENT | C75: BETOL | D75: BOUQUETIN | E75: BARQUETTE | F75: BIFFETON | G75: BRIDGE | H75: BIGOTERIE | I75: CARNET | J75: BESOGNE | K75: BENEFICE | L75: BATTERIE | M75: ATOME | N75: BANDA | O75: BOTTE | P75: BLE | Q75: BOULEAU | R75: ARTERE | S75: AUTOGARE | T75: CARACTERE
A76: BOB | B76: ARMER | C76: BIELORUSSE | D76: BOURRE | E76: BARRIERE | F76: BIGAILLE | G76: BRONCA | H76: BINAGE | I76: CARTABLE | J76: BIBLIOTHEC | K76: BICAMERAL | L76: BEATBOX | M76: AUGE | N76: BANDE | O76: BOTTIER | P76: BLET | Q76: BOUQUET | R76: ASCITE | S76: AVANCE | T76: CARAPACE
A77: BOBINE | B77: AROME | C77: BIHARI | D77: BOUT | E77: BARROT | F77: BIJOUX | G77: BUDO | H77: BLASPHEME | I77: CARTON | J77: BIFACE | K77: BIOCRATIE | L77: BECARRE | M77: AUGITE | N77: BARIL | O77: BOUGEOIR | P77: BLEUET | Q77: BOURBONS | R77: ASEPSIE | S77: AVANCEMENT | T77: CAUSALITE
A78: BODY | B78: ARQUEBUSE | C78: BILINGUE | D78: BOUTOIR | E78: BASCULE | F78: BILAN | G78: BUNKER | H78: BONZE | I78: CASIER | J78: BIJOUTIER | K78: BLOC | L78: BEDON | M78: AUTEL | N78: BARILLET | O78: BOUGERIE | P78: BOISSON | Q78: BOURGEON | R78: ASILE | S78: AVANTPROJE | T78: CELERITE
A79: BOGOLAN | B79: ARRIMAGE | C79: BIRMAN | D79: BOVIDE | E79: BASTERNE | F79: BILLET | G79: BUT | H79: BOUDDHISME | I79: CENACLE | J79: BINETTE | K79: BLOCADIE | L79: BELE | M79: AUTUNITE | N79: BAROMETRE | O79: BOUGIE | P79: BONBON | Q79: BOUTON | R79: ASPIRINE | S79: AVARIE | T79: CELLULE
A80: BOLERO | B80: ARRIMER | C80: BIWAT | D80: BOVIN | E80: BAT | F80: BILLON | G80: BUTEUR | H80: BOUDDHISTE | I80: CENSEUR | J80: BIOGRAPHE | K80: BLOCARD | L80: BELIERE | M80: AVALER | N80: BARRE | O80: BOULEAU | P80: BONI | Q80: BOUTURE | R80: ASSAINIR | S80: AVORTE | T80: CELSIUS
A81: BOLIVAR | B81: ARRIMEUR | C81: BOIS | D81: BRACONNAGE | E81: BATAI | F81: BUTINS | G81: CABRER | H81: BREVIAIRE | I81: CENSURE | J81: BIOLOGISTE | K81: BOUGISME | L81: BEMOL | M81: AZURITE | N81: BARREL | O81: BOUTEILLE | P81: BORIE | Q81: BRANCHAGE | R81: ASSAISONNE | S81: BAGNE | T81: CERVEAU
A82: BOMBE | B82: ARTEMIS | C82: BONAN | D82: BRAIRE | E82: BATEAU | F82: BLANC | G82: CADET | H82: BURQA | I82: CENTRE | J82: BISEAU | K82: BOYCOTT | L82: BENDIR | M82: BALANE | N82: BARRETTE | O82: BOUTIQUE | P82: BOTANIQUE | Q82: BRANCHE | R82: ASSIDUITE | S82: BAIN | T82: CHAIR
A83: BOMBER | B83: ARTISANALE | C83: BOUCHE | D83: BRANCHE | E83: BATELET | F83: BLASON | G83: CADOR | H83: CADI | I83: CERCLE | J83: BLOUSE | K83: BRIGUE | L83: BERCEUSE | M83: BALISE | N83: BARRIQUE | O83: BRACELET | P83: BOURGEON | Q83: BRANCHES | R83: ASSISTANCE | S83: BALCON | T83: CHAIRE
A84: BONNET | B84: ASTICOT | C84: BRETON | D84: BRAS | E84: BATELLE | F84: BUDGETER | G84: CADRER | H84: CAGOTERIE | I84: CERTIFICAT | J84: BOITE | K84: BUDGET | L84: BERIMBAU | M84: BALME | N84: BARROT | O84: BRAS | P84: BRAISER | Q84: BRANCHETTE | R84: ASSISTER | S84: BANQUE | T84: CHALEUR
A85: BOOT | B85: ATALANTE | C85: BUCAL | D85: BREBIS | E85: BENNE | F85: BLOCUS | G85: CAGE | H85: CALICE | I85: CERTIFIE | J85: BOITIER | K85: BUDGETAIRE | L85: BIDON | M85: BAMBOU | N85: BARYE | O85: BRASAGE | P85: BUDGET | Q85: BRANCHU | R85: ASSURANCE | S85: BAR | T85: CHAMP
A86: BORDER | B86: ATLANTIQUE | C86: BULGARE | D86: BROSSE | E86: BERLINE | F86: BONHEUR | G86: CALER | H86: CALIFAT | I86: CHAIRE | J86: BONNE | K86: BUREAU | L86: BIGOPHONE | M86: BANC | N86: BARYTON | O86: BRASSAGE | P86: BUTIN | Q86: BRAS | R86: ASSURE | S86: BARAQUE | T86: CHARGE
... A99: BOURRER | B99: AVUER | C99: CHARABIA | D99: CANINE | E99: BINARD | F99: CADRE | G99: CATCH | H99: CATENE | I99: CLUB | J99: BRASSEUR | K99: CENSURE | L99: BONGO | M99: BETON | N99: BIDON | O99: BUREAU | P99: CARAMBOLE | Q99: BUISSON | R99: AVULSION | S99: BATIMENT | T99: CINETIQUE
A100: BOURSE | B100: BAC | C100: CHAT | D100: CAPRIN | E100: BIPLACE | F100: CAGNOTTE | G100: CATEGORIE | H100: CATHARISME | I100: COLLE | J100: BRICOLAGE | L100: BONGOS | M100: BIENNAL | N100: BLOQUER | O100: BURIN | P100: CARCEVULE | Q100: BULLE | R100: BACHELIER | S100: BATIR | T100: CLARTE
A101: BOUTIQUE | B101: BACHOT | C101: CHINOIS | D101: CAPYBARA | E101: BIPLAN | F101: CAISSE | G101: CENDREE | H101: CATHEDRALE | I101: COLLEGE | J101: BROCHE | K101: CENTRE | L101: BOULA | M101: BIJOU | N101: BOISSEAU | O101: CABAS | P101: CARITATIF | Q101: CACAO | R101: BACILLE | S101: BATISSE | T101: COEUR
A102: BOUTON | B102: BADAIL | C102: CHUCHOTER | D102: CARACAL | E102: BIREACTEUR | F102: CAISSIER | G102: CENTRAL | H102: CATHOLIQUE | I102: COLONIE | J102: BROCHEUR | K102: CENTRISME | L102: BOUM | M102: BILLE | N102: BRENT | O102: CABOCHE | P102: CAROUBE | Q102: CADUC | R102: BACTERIE | S102: BATISSEUR | T102: COHESION
A103: BOUTONNER | B103: BAIE | C103: CIMBRE | D103: CARAPACE | E103: BIREME | F103: CALCUL | G103: CENTRE | H103: CELEBRER | I103: COMMERCE | J103: BRODEUR | K103: CENTRISTE | L103: BOUZOUKI | M103: BILLON | N103: BRIDER | O103: CACAO | P103: CARPELLE | Q103: CAFE | R103: BAIN | S103: BATTERIE | T103: COLLOIDE
A104: BOXER | B104: BAIGNADE | C104: CINGALAIS | D104: CARESSE | E104: BISQUINE | F104: CAPITAL | G104: CENTRER | H104: CELESTE | I104: COMPAS | J104: BROSSE | K104: CERCLE | L104: BOYAU | M104: BIOTITE | N104: BRISER | O104: CALCIN | P104: CARYOPSE | Q104: CAJOU | R104: BANDER | S104: BAZAR | T104: COLORER
A105: BRAGUE | B105: BAILLE | C105: CITATION | D105: CARIBOU | E105: BLINDE | F105: CARTEL | G105: CERCEAU | H105: CELESTIN | I105: COMPETENCE | J105: BROSSIER | K105: CHAINE | L105: BRANLE | M105: BISANNUEL | N105: BURETTE | O105: CANETTE | P105: CASSIS | Q105: CALEBASSE | R105: BARBITURIQ | S105: BERCAIL | T105: COMBUSTIBL
A106: BRAGUETTE | B106: BALANCE | C106: CLAPPEMENT | D106: CARLIN | E106: BLONDIN | F106: CASH | G106: CEREBRAL | H106: CELLE | I106: COMPRENDRE | J106: BROYEUR | K106: CHAMBRE | L106: BREAKCORE | M106: BISCUIT | N106: BYTE | O106: CANEVAS | P106: CASUEL | Q106: CALME | R106: BASSIN | S106: BERGERIE | T106: COMPERE
A107: BRAIE | B107: BALANCER | C107: CLIC | D107: CARNASSIER | E107: BOEING | F107: CAURIS | G107: CESTE | H107: CENACLE | I107: COMPTER | J107: BRULEUR | K107: CHANCELIER | L107: BRIOSO | M107: BISMUTH | N107: CABLE | O107: CANNE | P107: CEDRAT | Q107: CAMELIA | R107: BATTRE | S107: BESOIN | T107: COMPLEXION
A108: BRASSARD | B108: BALEINE | C108: CODE | D108: CARNIVORE | E108: BOGGIE | F108: CAUTION | G108: CHALLENGE | H108: CENE | I108: CONCOURS | J108: BUCHERON | K108: CHAOS | L108: BRUANT | M108: BITUME | N108: CABOT | O108: CANNETTE | P108: CEP | Q108: CAMELLIA | R108: BAUME | S108: BETON | T108: CONCEPT
A109: BRELUCHE | B109: BALEINIER | C109: COMMUN | D109: CASTOR | E109: BOGUET | F109: CAVALERIE | G109: CHALLENGER | H109: CERTITUDE | I109: CONFERENCE | J109: BUCHEUR | K109: CHEFFERIE | L109: BRUIT | M109: BLENDE | N109: CABRE | O109: CARCAISE | P109: CEREALE | Q109: CANADA | R109: BELLADONE | S109: BETONARME | T109: CONCEPTUEL
A110: BRETELLE | B110: BALEINIERE | C110: COMPLEMENT | D110: CAUDALE | E110: BOLIDE | F110: CENS | G110: CHAMPION | H110: CHABBAT | I110: CONGE | J110: BURALISTE | K110: CHOIX | L110: BRUITISTE | M110: BLOC | N110: CACHER | O110: CARNET | P110: CEREALIERE | Q110: CANNELLE | R110: BERCER | S110: BEURRERIE | T110: CONCRET
A111: BRETON | B111: BALLAST | C111: CONCEPT | D111: CAVALIER | E111: BOOSTER | F111: CENTIME | G111: CHARGER | H111: CHAHADA | I111: CONJUGUER | J111: BUREAU | K111: CITE | L111: BRUYANT | M111: BOHRIUM | N111: CADENCER | O111: CARREAU | P111: CERISE | Q111: CANOT | R111: BESOIN | S111: BICOQUE
A112: BRIDE | B112: BALVANE | C112: CONFER | D112: CAVITE | E112: BOUGER | F112: CENTRALE | G112: CHASSE | H112: CHAIRE | I112: CONNAITRE | J112: BURIN | K112: CITOYEN | L112: BUCCIN | M112: BOIS | N112: CADRAN | O112: CARRELAGE | P112: CERISIER | Q112: CARIBOU | R112: BICHONNER | S112: BIJOUTERIE | T112: CONDITION
...

Sheet M2
A1: ALKAMO — M2
A2: N° | B2: THÈME | C2: MOTS
A3: 1 | B3: MARINE | C3: =COUNTA(M2_mots!A3:A5000) -> 701
A4: 2 | B4: CHIMIE | C4: =COUNTA(M2_mots!B3:B5000) -> 804
A5: 3 | B5: COUTURE | C5: =COUNTA(M2_mots!C3:C5000) -> 826
A6: 4 | B6: GRAMMAIRE | C6: =COUNTA(M2_mots!D3:D5000) -> 598
A7: 5 | B7: FLEUR | C7: =COUNTA(M2_mots!E3:E5000) -> 603
A8: 6 | B8: INDUSTRIE | C8: =COUNTA(M2_mots!F3:F5000) -> 659
A9: 7 | B9: MÉTIER | C9: =COUNTA(M2_mots!G3:G5000) -> 1214
A10: 8 | B10: ANIMAL | C10: =COUNTA(M2_mots!H3:H5000) -> 549
A11: 9 | B11: CUISINE | C11: =COUNTA(M2_mots!I3:I5000) -> 720
A12: 10 | B12: INSTITUTION | C12: =COUNTA(M2_mots!J3:J5000) -> 756
A13: 11 | B13: OUTIL | C13: =COUNTA(M2_mots!K3:K5000) -> 779
A14: 12 | B14: PÉDAGOGIE | C14: =COUNTA(M2_mots!L3:L5000) -> 783
A15: 13 | B15: JEU | C15: =COUNTA(M2_mots!M3:M5000) -> 739
A16: 14 | B16: ART ET MUSIQUE | C16: =COUNTA(M2_mots!N3:N5000) -> 855
A17: 15 | B17: ASTRONOMIE | C17: =COUNTA(M2_mots!O3:O5000) -> 601
A18: 16 | B18: ALIMENT | C18: =COUNTA(M2_mots!P3:P5000) -> 743
A19: 17 | B19: BOTANIQUE | C19: =COUNTA(M2_mots!Q3:Q5000) -> 996
A20: 18 | B20: ÉNERGIE | C20: =COUNTA(M2_mots!R3:R5000) -> 754
A21: 19 | B21: PUISSANCE | C21: =COUNTA(M2_mots!S3:S5000) -> 612
A22: 20 | B22: ANATOMIE | C22: =COUNTA(M2_mots!T3:T5000) -> 882
A23: TOTAL | C23: =SUM(C3:C22) -> 15174

Sheet M2_mots
A1: MARINE | B1: CHIMIE | C1: COUTURE | D1: GRAMMAIRE | E1: FLEUR | F1: INDUSTRIE | G1: MÉTIER | H1: ANIMAL | I1: CUISINE | J1: INSTITUTION | K1: OUTIL | L1: PÉDAGOGIE | M1: JEU | N1: ART ET MUSIQUE | O1: ASTRONOMIE | P1: ALIMENT | Q1: BOTANIQUE | R1: ÉNERGIE | S1: PUISSANCE | T1: ANATOMIE
A2: =COUNTA(A3:A5000) -> 701 | B2: =COUNTA(B3:B5000) -> 804 | C2: =COUNTA(C3:C5000) -> 826 | D2: =COUNTA(D3:D5000) -> 598 | E2: =COUNTA(E3:E5000) -> 603 | F2: =COUNTA(F3:F5000) -> 659 | G2: =COUNTA(G3:G5000) -> 1214 | H2: =COUNTA(H3:H5000) -> 549 | ... T2: =COUNTA(T3:T5000) -> 882
A3: ABER | B3: ACCUM | C3: ABEILLE | D3: ABECEDAIR | E3: ABEILLE | F3: ABATTOIR | G3: ABATTEUR | H3: ABATTAGE | I3: ABAISSE | J3: ABOLITION | K3: ACCOMPAGNE | L3: ABECEDAIR | M3: ACADEMIE | N3: ABSTRAIT | O3: ABSIDE | P3: ABECQUER | Q3: ABELIA | R3: ABATTAGE | S3: ABATTRE | T3: ABCES
A4: ABORD | B4: ACETAMIDE | C4: ABLATION | D4: ABLATIF | E4: ABRUTIR | F4: ABRASION | G4: ABOYEUR | H4: ABATTOIR | I4: ABAISSER | J4: ACADEMIE | K4: ACCORD | L4: ABREGE | M4: ACCESSOIRE | N4: ACADEMISME | O4: ACCOMPLIR | P4: ABONDANCE | Q4: ABELIE | R4: ABSORPTION | T4: ABDOMEN
A5: ABORDAGE | B5: ACETATE | C5: ACADEMIE | D5: ABREVIATIO | E5: ABSINTHE | F5: ACHAT | G5: ACCONIER | H5: ABEILLE | I5: ABAT | J5: ACADEMIQUE | K5: ACCORDEUR | L5: ACADEMIE | M5: ACCORD | N5: ACCORD | O5: ACCRETION | P5: ABONDANTE | Q5: ABOUTA | R5: ACCELERATE | S5: ACCESSION | T5: ABDOMINAL
A6: ABORDER | B6: ACETONE | C6: ACCESSOIRE | D6: ABSTRAIT | E6: ACACIA | F6: ACIDE | G6: ACHETEUR | H6: ABRUPT | I6: ABATTIS | J6: ACCOMMODER | K6: ACCORDOIR | L6: ACCOMPAGNE | M6: ACQUISITIO | N6: ACCORDAGE | O6: ACRAB | P6: ABRITER | Q6: ABSCISSION | S6: ACCULER | T6: ABDUCTEUR
A7: ABRI | B7: ACETYLENE | C7: ACCLAME | D7: ACADEMIE | E7: ACANTHE | F7: ACIER | G7: ACIERISTE | H7: AGIR | I7: ABERDEEN | J7: ACCORD | K7: ACIER | L7: ACCUEIL | M7: ACTEUR | N7: ACCORDEON | O7: ACTEUR | P7: ABSORBER | Q7: ACANTHE | R7: ACCUMULATE | S7: ACHEMINER | T7: ACADEMIE
A8: ABYSSAL | B8: ACIDE | C8: ACCOUCHEME | D8: ACCENT | E8: ACANTHES | F8: ACIERIE | G8: ACONIER | H8: AGRESSIF | I8: ABRICOT | J8: ACCUEIL | K8: ACTE | L8: ACQUERIR | M8: ACTION | N8: ACCORDEUR | O8: ACTIVITE | P8: ABSTINENCE | Q8: ACARIEN | R8: ACHAT | S8: ACIER | T8: ACANTHE
A9: ACCALMIE | B9: ACIER | C9: ACCROC | D9: ACCEPTION | E9: ACHILLEE | F9: ACRYLIQUE | G9: ACQUERIR | H9: AGRESSIVIT | I9: ACCRA | J9: ACHEMINER | K9: AFFUTER | L9: ACQUIS | M9: ACTIONNAIR | N9: ACCROCHE | O9: AERODYNE | P9: ACIDE | Q9: ACCLIMATAT | R9: ACHETER | S9: ACQUERIR | T9: ACETABULE
A10: ACCOSTAGE | B10: ACRYLIQUE | C10: ACCROCHE | D10: ACCORD | E10: ACTEE | F10: ACTIF | G10: ACROBATE | H10: AGRESTE | I10: ACCUEIL | J10: ACTE | K10: AIGUILLE | L10: ACQUISITIO | M10: ADAPTATEUR | N10: ACHROME | O10: AEROLITE | P10: ACIDITE | Q10: ACIDE | R10: ACRETE | S10: ACTE | T10: ACINI
A11: ACCOSTER | B11: ACTINIUM | C11: ACETATE | D11: ACCUSATIF | E11: AGAPANTHE | F11: ACTIVITE | G11: ACTEUR | H11: AIGLE | I11: ACERBE | J11: ACTES | K11: AIR | L11: ACTIVE | M11: ADAPTATIVE | N11: ACORDE | O11: AGIR | P11: ACTIF | Q11: ACOELOMATE | R11: ACTINIDE | S11: ACTION | T11: ADAPTATIF
A12: ACTUAIRE | B12: ACTINOTE | C12: ACRYLIQUE | D12: ACRONYME | E12: AGASTACHE | F12: ADAPTATION | G12: AEDE | H12: AIGRETTE | I12: ACHARD | J12: ACTION | K12: AISSETTE | L12: ACTIVITE | M12: ADDICTIF | N12: ACTE | O12: AGO | P12: ACTUALISER | Q12: ACTINIDIE | R12: ACTION | S12: ACUITE | T12: ADAPTEE
A13: AERIEN | B13: ACTIVATION | C13: ADMIRATION | D13: ACTANT | E13: AGAVE | F13: ADDITIF | G13: AERONAUTE | H13: AIR | I13: ACRA | J13: ACTUAIRE | K13: ALENE | L13: ADEPTE | M13: ADOPTER | N13: ACTEUR | O13: AIR | P13: ADDITIF | Q13: ADAPTATION | R13: ACTIONNEUR | S13: ADMINISTRE | T13: ADDUCTEUR
A14: AERONEF | B14: ADAMANTIN | C14: AGRAFE | D14: ACTE | E14: AGE | F14: ADJUVANT | G14: AEROSTIER | H14: ALBATROS | I14: AFFAME | J14: ADAPTEE | K14: ALESOIR | L14: ADMISSION | M14: ADVERSAIRE | N14: ACTIVITES | O14: AKARNAR | P14: AFFAME | Q14: ADAXIALE | R14: ACTIVITE | S14: ADVERSAIRE | T14: ADNEE
A15: AFFINER | B15: ADAMITE | C15: AGRAFURE | D15: ACTIF | E15: AGRIMOINE | F15: ADROIT | G15: AFFICHEUR | H15: ALIMENTAIR | I15: AGAPE | J15: ADHESION | K15: ALIDADE | L15: ADOLESCENT | M15: ADVERSE | N15: ACTRICE | O15: ALBEDO | P15: AFFOURAGER | Q15: ADRAGANT | R15: ADDITION | S15: AFFAIBLISS | T15: ADRENALINE
A16: AFFRETER | B16: ADULAIRE | C16: AIGUILLE | D16: ADJECTIF | E16: AINES | F16: AFFAIRE | G16: AFFILEUR | H16: ALLIGATOR | I16: AGNEAU | J16: ADJOINT | K16: ALTO | L16: ADOPTER | M16: AERIEN | N16: ACTUALITE | O16: ALBENE | P16: AGAPE | Q16: AGRICULTUR | R16: ADYNAMIE | S16: AGENT | T16: AILE
A17: AFFRETEUR | B17: AEGYRINE | C17: AIGUILLEE | D17: ADJECTIVAL | E17: AIR | F17: AFFINAGE | G17: AFFILOIR | H17: ALPAGA | I17: AIGRE | J17: ADMINISTRA | K17: AMPEREMETR | L17: ADULTE | M17: AFFICHAGE | N17: ADAGIO | O17: ALCOR | P17: AGAR | Q17: AGRION | R17: AGENCE | S17: AGILITE | T17: AINE
A18: AIRE | B18: AEROSOL | C18: AISANCE | D18: ADJONCTION | E18: AISSELLE | F18: AGENCEMENT | G18: AFFINEUR | H18: ALTRUISTE | I18: AIL | J18: ADMINISTRE | K18: ANALYSE | L18: AFFICHE | M18: ALEATOIRE | N18: ADMIRATEU | O18: ALGOL | P18: AGNEAU | Q18: AGRONOMIE | R18: AGILITE | S18: AGIR | T18: AISSELLE
... A22: ALLURE | B22: AIMANT | C22: AJOURER | D22: ADVERBE | E22: ALOE | F22: AIGUISER | G22: AFFUTEUR | H22: ANIMAL | I22: ALIGOT | J22: AGENCEMENT | K22: ANGLE | L22: AGREGE | M22: AMATEUR | N22: AEROBIC | O22: ALPHA | P22: AGRICULTUR | Q22: AILE | R22: ALIMENT | S22: AIDE | T22: AMPHITHEAT
A23: ALOSE | B23: AIR | C23: AJUSTE | D23: ADVERBIAL | E23: AMANDIER | F23: AIR | G23: AGENCIER | H23: ANIMALERIE | I23: ALIMENT | J23: AGENCER | K23: APPAREIL | L23: AGREMENT | M23: AMBIANCE | N23: AEROGRAPHE | O23: ALTAZIMUTH | P23: AGROALIMEN | Q23: AKENE | S23: AIRAIN | T23: AMYGDALE
A24: AMARINER | B24: AIRAIN | C24: AJUSTER | D24: AFFINITE | E24: AMARANTE | F24: ALARME | G24: AGENT | H24: ANIMALITE | I24: ALIMENTAIR | J24: AGENT | K24: APPAREILLA | L24: ALBUM | M24: AMICAL | N24: AFFICHE | O24: ALTIMETRE | P24: AIDE | Q24: ALATERNE | R24: ALIMENTER | S24: ALLIANCE | T24: AMYLASE
A25: AMARRAGE | B25: ALABANDINE | C25: ALLURE | D25: AFFIXE | E25: AMARYLLIS | F25: ALCOOL | G25: AGIOTEUR | H25: ANTHROPOPH | I25: ALIMENTER | J25: AGREE | K25: APPLICATIO | L25: ALLAITEMEN | M25: AMPHITHEAT | N25: AGON | O25: ALTITUDE | P25: AIL | Q25: ALBINOS | R25: ALLANT | S25: ALLIANCES | T25: ANAGLYPHE
A26: AMARRE | B26: ALABANDITE | C26: ALPAGA | D26: AGRAMMATIC | E26: AMITIE | F26: ALESAGE | G26: AGREEUR | H26: ANTILOPE | I26: ALLEGE | J26: AGRICOLE | K26: ARATOIRE | L26: ALPHABETIS | M26: AMUSANT | N26: AIKIDO | O26: ALUNIR | P26: ALCOOL | Q26: ALBIZZIA | R26: ALLEGRESSE | S26: ALLIE | T26: ANAL
A27: AMARRES | B27: ALBATRE | C27: AMBULATOIR | D27: AGRAMMATIS | E27: AMMI | F27: ALESOIR | G27: AIDE | H27: APPETIT | I27: ALMANACH | J27: AJUSTER | K27: ARME | L27: AMI | M27: AMUSEMENT | N27: AIR | O27: ALYCONE | P27: ALGUE | Q27: ALBUMINE | R27: ALLUMAGE | S27: ALLURE | T27: ANALYSE
A28: AME | B28: ALBITE | C28: AMIDONNER | D28: AGREGATION | E28: AMSONIE | F28: ALFA | G28: AIDEAU | H28: APPRIVOIS | I28: ALOYAU | J28: ALIGNER | K28: ARRACHECLO | L28: AMIE | M28: AMUSER | N28: AISANCE | O28: AMAS | P28: ALGUES | Q28: ALEURITE | R28: ALTERNATEU | S28: AMBITION | T28: ANATOMIE
A29: AMER | B29: ALBUGINE | C29: AMPUTATION | D29: AKKADIEN | E29: ANCOLIE | F29: ALIMENT | G29: AIGUISEUR | H29: APTITUDE | I29: AMANDE | J29: ALINEA | K29: ASSORTIME | L29: AMITIE | M29: ANALYSER | N29: ALBUM | O29: AMATEUR | P29: ALIMENT | Q29: ALGOIDE | R29: AME | S29: AME | T29: ANATOMIQUE
A30: AMIRAL | B30: ALBUGO | C30: ANATOMIE | D30: ALLATIF | E30: ANDROCEE | F30: ALIMENTER | G30: AIGUISOIR | H30: AQUATIQUE | I30: AMIDON | J30: ALLIANCE | K30: ASTRE | L30: AMPHI | M30: ANIMATEUR | N30: ALCHIMIE | O30: ANALEMME | P30: ALIMENTAIR | Q30: ALGUE | R30: AMORTISSEM | S30: AMNISTIE | T30: ANATOMISER
A31: AMONT | B31: ALCALI | C31: ANATOMISTE | D31: ALLOMORPHE | E31: ANEMONE | F31: ALLIAGE | G31: AISSEAU | H31: ARAIGNEE | I31: AMUSE | J31: ALLOCATION | K31: ASTROLABE | L31: ANALPHABET | M31: ANIMER | N31: ALLEGORIE | O31: ANGLE | Q31: ALIBOUFIER | R31: AMPACITE | S31: AMPLEUR | T31: ANATOMISTE
A32: ANCHOIS | B32: ALCALIN | C32: ANESTHESIE | D32: ALPHABET | E32: ANTHERE | F32: ALLUMETTE | G32: AJUSTEUR | H32: ARCHETYPE | I32: ANCHOIS | J32: AMBASSADE | K32: ATELIER | L32: ANALYSE | N32: ALLEGRO | O32: ANNEAU | P32: ALIMENTER | Q32: ALIMENT | R32: AMPERAGE | S32: AMPLIFICAT | T32: ANGIOGRAPH
A33: ANCRAGE | B33: ALCALINITE | C33: ANGORA | D33: ALTERNANCE | E33: ANTHURIUM | F33: ALUMINIUM | G33: ALCADE | H33: ARTHROPODE | I33: ANDOUILLET | J33: AMENAGEMEN | K33: ATTIRAIL | L33: ANGE | M33: ANTICIPER | N33: ALTO | O33: ANNEE | P33: ALLAITEMEN | Q33: ALIMENTS | R33: AMPERE | S33: AMPLIFIER | T33: ANIMAL
A34: ANCRE | B34: ALCANE | C34: APIECEUR | D34: AMBIGUITE | E34: ARBRE | F34: ALUNERIE | G34: ALCOOLIER | H34: ASSOUVIR | I34: ANETH | J34: ANALYSE | K34: ATTISOIR | L34: ANIMATEUR | M34: APPROCHE | N34: AMATEUR | O34: ANTARES | P34: ALLAITER | Q34: ALLEE | R34: ANIMATION | S34: AMPLITUDE | T34: ANNEAU
A35: ANGLE | B35: ALCANES | C35: APLAT | D35: AMIM | E35: ARBRISSEAU | F35: AMBRE | G35: ALESEUR | H35: AUTOMATIQU | I35: ANIS | J35: ANARCHIE | K35: BAGAGE | L35: ANIMER | M35: ARBITRAGE | N35: AMBITION | O35: ANTENNE | P35: ALLERGIE | Q35: ALLIER | R35: ANION | S35: AMPOULE | T35: ANNEXE
A36: ANNEXE | B36: ALCENE | C36: APPARENCE | D36: AMORPHE | E36: ARBUSTE | F36: AMIDON | G36: ALESOIR | H36: AUTOUR | I36: APERITIF | J36: ANARCHISME | K36: BALANCE | L36: ANNONCER | M36: ARBITRE | N36: ANDANTE | O36: APEX | P36: AMANDE | Q36: ALOE | R36: ANODE | S36: ANARCHIE | T36: ANNULAIRE
A37: ANSE | B37: ALCHIMIE | C37: APPLIQUE | D37: ANAGRAMME | E37: AREOLE | F37: AMORCE | G37: ALFATIER | H37: AUTRUCHE | I37: APPRENTI | J37: ANATOMIQUE | K37: BALANCIER | L37: APPRENANT | M37: ARBITRER | N37: ANIMATEUR | O37: APHELIE | P37: AMBROISIE | Q37: ALOES | R37: APATHIE | S37: ANEANTIR | T37: ANSE
A38: ANTENNE | B38: ALCHIMISTE | C38: APPRET | D38: ANALOGIE | E38: ARGANIER | F38: AMORTIR | G38: ALIENISTE | H38: AYE | I38: ARGENT | J38: ANIMER | K38: BALAYETTE | L38: APPRENDRE | M38: ARCADE | N38: ANTILABE | O38: APHELION | P38: AMER | Q38: ALOUCHIER | R38: APATHIQUE | S38: ANGE | T38: ANTERIEUR
A39: APPAT | B39: ALCOOL | C39: ARMATURE | D39: ANALYSE | E39: ARGENTE | F39: AMPHORE | G39: ALISIER | H39: BABOUIN | I39: ARMOIRE | J39: APPRETER | K39: BANJO | L39: APPRENTI | M39: ARENE | N39: ANTIQUE | O39: APOASTRE | P39: AMIDON | Q39: ALPAGA | R39: APLOMB | S39: ANNEXION | T39: ANTHELIX
A40: AQUATIQUE | B40: ALDEHYDE | C40: ARRET | D40: ANALYSEUR | E40: ARMOISE | F40: AMPOULE | G40: ALPINISTE | H40: BALEINE | I40: AROMATE | J40: ARBITRAIRE | K40: BARBE | L40: APPRENTIE | M40: ARGENT | N40: ANTIQUITE | O40: APOGEE | P40: AMITIE | Q40: ALPIN | R40: APPROVISIO | S40: ANODE | T40: ANTHROPOLO
A41: ARCHIPEL | B41: ALDEHYDES | C41: ARRONDI | D41: ANALYSTE | E41: ARNICA | F41: ANALYSE | G41: ALTISTE | H41: BALOURD | I41: AROMATIQUE | K41: BAROMETRE | L41: APPROCHE | M41: ARMEE | N41: APARTE | O41: APOLLO | P41: AMORCER | Q41: ALPINE | R41: APRETE | S41: APOGEE | T41: ANTHROPOME
A42: ARCTIQUE | B42: ALGEBRE | C42: ARTISANAL | D42: ANAPHORE | E42: AROME | F42: APTE | G42: AMATEUR | H42: BANDICOOT | I42: AROME | K42: BAROQUE | L42: APPROPRIA | M42: ASSEMBLER | N42: AQUARELLE | O42: APOLUNE | P42: AMPLIFICAT | Q42: ALTEA | R42: APTE | S42: ARBITRAGE | T42: ANTHROPOTO
A43: ARISER | B43: ALIZARINE | C43: ARTISANAT | D43: ANASTROPHE | E43: ARROSER | F43: ARGENT | G43: ANALYSTE | H43: BARBARE | I43: ART | J43: ARCHIVE | K43: BARRE | L43: APTITUDE | M43: ASTUCE | N43: ARABESQUE | O43: APPARENTE | P43: ANIMAL | Q43: AMARANTE | R43: APTITUDE | S43: ARDEUR | T43: ANTICORPS
A44: ARMADA | B44: ALLIAGE | C44: ARTISTIQUE | D44: ANGLICISME | E44: ARTICHAUT | F44: ARGILE | G44: ANIER | H44: BARBARIE | I44: ASSIETTE | J44: ARMATURE | K44: BARYTON | L44: ARDOISE | M44: ATHLETE | N44: ARCHET | O44: APSIDE | P44: ANIMALE | Q44: AMARINE | R44: ARDENT | S44: ARGENT | T44: ANTRE
A45: ARMATEUR | B45: ALLOPHANE | C45: ASSEMBLAGE | D45: ANNOTATION | E45: ARUM | F45: ARME | G45: ANIMALIER | H45: BELETTE | I45: ASSIETTES | J45: ARMEE | K45: BATTERIE | L45: ART | M45: ATHLETISME | N45: ARIA | O45: ARAIGNEE | P45: ANOREXIE | Q45: AMBOINE | R45: ARDEUR | S45: ARISTOCRAT | T45: ANUS
A46: ARMEE | B46: ALMANDIN | C46: ASSEMBLE | D46: ANOMAL | E46: ASPHODELE | F46: ARMEMENT | G46: ANIMATEUR | H46: BELIER | I46: ASTE | J46: ARRANGER | K46: BAUDRIER | L46: ARTICLE | M46: ATOUT | N46: ARPEGE | O46: ARCHE | P46: APERITIF | Q46: AMBRE | R46: ARGON | S46: ARME | T46: AORTE
A47: ARMEMENT | B47: ALMANDINE | C47: ASSEMBLER | D47: ANTECEDENT | E47: ASTER | F47: ART | G47: ANNALISTE | H47: BELUGA | I47: ATTENDRIR | J47: ARRETE | K47: BECHE | L47: ASCENDANCE | M47: ATTRAPE | N47: ART | O47: ARIEL | P47: APPETIT | Q47: AMBRETTE | R47: ARME | S47: ARMEE | T47: APONEVROSE
A48: ARMER | B48: ALMELEC | C48: ASSISE | D48: ANTIPHRASE | E48: ASTILBE | F48: ARTICULER | G48: ANSPECT | H48: BEOTIEN | I48: AUBERGINE | J48: ARRETS | K48: BEDANE | L48: ASSIDU | M48: ATTRAPER | O48: ARTISTE | P48: APPORT | Q48: AMORPHE | R48: ARMEE | S48: ARSENAL | T48: APOPHYSE
A49: ARRAISONNE | B49: ALPAX | C49: ASSISTANT | D49: ANTITHESE | E49: AUBEPINE | F49: ARTIFICE | G49: AOUTERON | H49: BERNACLE | I49: AVOINE | J49: ARTICULER | K49: BEQUILLE | L49: ASSIDUITE | M49: AVENTURE | N49: ARTIFICE | O49: ASPECT | P49: APPORTER | Q49: ANACARDE | R49: ARRACHER | S49: ASPIRATEUR | T49: APPAREIL
A50: ARRIMAGE | B50: ALUMINE | C50: ASSORTI | D50: ANTONYME | E50: AUCUBA | F50: ARTIFICIEU | G50: APIECEUR | H50: BESOIN | I50: AXOA | J50: ASILE | K50: BESOIN | L50: ATELIER | M50: AVIATION | N50: ARTISAN | O50: ASSOLIR | P50: APPROVISIO | Q50: ANATOMIE | R50: ASTATIQUE | S50: ASTREINDRE | T50: APPENDICE
A51: ARSENAL | B51: ALUMINITE | C51: ATELIER | D51: AORISTE | E51: AUREOLE | F51: ARTISAN | G51: APPAREIL | H51: BESOINS | I51: AXONGE | J51: ASSEMBLAGE | K51: BIFACE | L51: ATELIERS | M51: AVIRON | N51: ARTISANAT | O51: ASTERISME | P51: APPUI | Q51: ANEMOMO | R51: ASTRE | S51: ATOME | T51: ARCADE
A52: ARTILLERIE | B52: ALUMINIUM | C52: ATTACHE | D52: APHASIE | E52: AUTEURE | F52: ARTISANAL | G52: APTITUDE | H52: BESTIAIRE | I52: BACON | J52: ASSEMBLEE | K52: BINETTE | L52: ATTACHEMEN | M52: AXE | N52: ARTISTE | O52: ASTEROIDE | P52: AQUATIQUE | R52: ATOME | S52: ATTRACTION
A53: ARTIMON | B53: ALUN | C53: ATTACHER | D53: APHORISME | E53: AZALEE | F53: ARTISANAT | G53: ARCON | H53: BESTIAL | I53: BAGUETTE | J53: ASSEMBLER | K53: BISAIGUE | L53: ATTITUDE | M53: BABIOLE | N53: ARTISTERIE | O53: ASTRAL | P53: AQUEDUC | Q53: ANGUSTURE | R53: ATOMIQUE | S53: AUGMENTER | T53: AREOLE
B54: ALUNITE | C54: BALAFRE | D54: APOCOPE | E54: BAIES | F54: ASSEMBLAGE | G54: ARGENTIER | H54: BESTIOLE | I54: BAHUT | J54: ASSOCIATIO | K54: BISEAU | L54: AUBE | M54: BABYFOOT | N54: ARTISTIQUE | O54: ASTRE | P54: ARACHIDE | Q54: ANIL | R54: ATONIE | S54: AUTOCRATE | T54: ARN
A55: ATTERRIR | B55: AMALGAME | C55: BALAYETTE | D55: APOSTROPHE | E55: BAPTISIA | F55: ASSEMBLEE | G55: ARGOT | H55: BETAIL | I55: BAKLAWA | J55: ASSOCIE | K55: BOIS | L55: AURORE | M55: BACCARA | N55: ARTMODERNE | O55: ASTROLABE | P55: ARGENT | Q55: ANIME | R55: ATTOVOLT | S55: AUTOCRATIE | T55: ARRANGEMEN
A56: ATTERRISSA | B56: AMAZONITE | C56: BALEINAGE | D56: APPARTENAN | E56: BEAUTE | F56: ASSEMBLER | G56: ARMAILLI | H56: BETE | I56: BALANCE | J56: ATELIER | K56: BOUCLIER | L56: AUTEUR | M56: BACKGAMMON | O56: ASTROLOGIE | P56: ARMER | Q56: ANISETTE | S56: AUTONOMIE | T56: ARTERE
A57: AUBE | B57: AMBRE | C57: BANDE | D57: APPELABLE | E57: BEGONIA | F57: ASTUCIEUX | G57: ARMATEUR | H57: BICHE | I57: BANANE | J57: ATOME | K57: BOURROIR | L57: AUTISTE | M57: BADINAGE | N57: ASSYRIEN | O57: ASTRONAUTE | P57: AROME | Q57: ANNONE | R57: AUDACE | S57: AUTORITAIR | T57: ARTERIOLE
A58: AULNE | B58: AMERICIUM | C58: BAROQUE | D58: APPORT | E58: BELLEDENUI | F58: ATELIER | G58: ARME | H58: BIODIVERSI | I58: BANQUET | J58: ATTACHE | K58: BOUTIQUE | L58: AUTODIDACT | M58: BADMINTON | N58: ATELIER | O58: ASTRONEF | P58: ATTACHER | Q58: ANNUELLE | R58: AUGMENTER | S58: AUTORITE | T58: ARTHRODIE
A59: AURIQUE | B59: AMETHYSTE | C59: BASQUE | D59: APPOSITION | E59: BERCE | F59: AUBAINE | G59: ARPENT | H59: BIPEDE | I59: BARATTE | J59: ATTRIBUTIO | K59: BROCHOIR | L59: AUTONOMIE | M59: BAL | N59: ATTRACTION | O59: ASTRONOME | P59: ATTISER | Q59: ANONA | R59: AUTONOME | S59: AVANCER | T59: ARTHROPODE
A60: AVAL | B60: AMIANTE | C60: BASTE | D60: APPRENDRE | E60: BERGENIA | F60: AUDACE | G60: ARPETE | H60: BISON | I60: BARBECUE | J60: AUDIT | K60: BURIN | L60: AUTRICE | M60: BALANCOIRE | N60: AUDITEUR | O60: ASTRONOMIE | P60: AUBERGINE | Q60: ANOURE | R60: AUTORITE | S60: AVANTAGE | T60: ARTHROSE
A61: AVANT | B61: AMIDE | C61: BATI | D61: APPRENTISS | E61: BETOINE | F61: AUTOMATE | G61: ARRETISTE | H61: BLAIREAU | I61: BARDE | J61: AUDITEUR | K61: CALIBRAGE | L61: AUXILIAIRE | M61: BALLE | N61: AUDITION | O61: ASTUCIEUX | P61: AVALER | Q61: ANTHERE | R61: AVARE | S61: AVENEMENT
A62: AVARIE | B62: AMINE | C62: BATIE | D62: APPROCHE | E62: BLANCHE | F62: AUTOMATION | G62: ART | H62: BOEUF | I62: BASE | J62: AUTONOME | K62: CAOUTCHOUC | L62: AVERTIR | M62: BALLON | N62: AUTEUR | O62: ATENUATION | P62: AVIVER | Q62: ANTHOLOGIE | R62: BAISSER | S62: AVOIR | T62: ARTICULER
A63: AVIONIQUE | B63: AMMONIAC | C63: BATIK | D63: APRES | E63: BLE | F63: AUTOMOBILE | G63: ARTILLEUR | H63: BONOBO | I63: BASILIC | J63: AUTORITE | K63: CAPTEUR | L63: AVISER | M63: BANDE | N63: BAL | O63: ATLAS | P63: AVOCADO | Q63: ANTIPODE | R63: BANQUER | S63: AVOIRBARRE | T63: ARYTENOIDE
A64: AVIRON | B64: AMORPHE | C64: BATIR | D64: ARABE | E64: BLEU | F64: AVANCE | G64: ARTISAN | H64: BOSSE | I64: BASSINE | J64: AVIATION | K64: CARTOGRAPH | L64: BABOUIN | M64: BANQUE | N64: BALADEUR | O64: ATMOSPHERE | P64: AVOINE | Q64: APOPTOSE | R64: BANQUEROUT | S64: BATERIE | T64: ASPERITE
A65: AVISO | B65: AMPELITE | C65: BEAUTE | D65: ARABISATIO | E65: BLEUET | F65: AXLE | G65: ARTISTE | H65: BOTANIQUE | I65: BATEUR | J65: AVIS | K65: CENDRIER | L65: BAC | M65: BARRE | N65: BALAFON | O65: ATOME | P65: AVOIR | Q65: AQUATIQUE | R65: BARRAGE | S65: BATON | T65: ASSEMBLAGE
A66: AZIMUT | B66: AMPHOTERE | C66: BECQUET | D66: ARGOT | E66: BLOND | F66: BALOURDISE | G66: ASPIC | H66: BOUQUETIN | I66: BATTERIE | J66: AVOCAT | K66: CERF | L66: BACCALAUR | M66: BASCULE | N66: BALCON | O66: ATTENDRE | P66: BACADE | Q66: ARABICA | R66: BATTERIE | S66: BATTRE | T66: ASTRONOMIE
A67: AZUR | B67: ANALYTE | C67: BEQUET | D67: ART | E67: BOTANIQUE | F67: BANCAIRE | G67: ASSE | H67: BOVIN | I67: BECHAMEL | J67: BANCAIRE | K67: CHALUMEAU | L67: BALBUTIEM | M67: BASKET | N67: BALLERIN | O67: ATTRACTION | P67: BACON | Q67: ARAC | R67: BESOIN | S67: BEAUCOUP | T67: ATOME
A68: BABORD | B68: ANALYTIQUE | C68: BERTHE | D68: ARTICLE | E68: BOTANISTE | F68: BANQUE | G68: ASSEAU | H68: BRACONNAGE | I68: BECTER | J68: BANQUE | K68: CHANDELIER | L68: BAPTEME | M68: BASQUE | N68: BALLERINE | O68: AURORE | P68: BACTERIE | Q68: ARALIA | R68: BIOENERGET | S68: BEAUTE | T68: ATRABILE
A69: BAC | B69: ANATOMIE | C69: BIAIS | D69: ASPECT | E69: BOUCAGE | F69: BATELLERIE | G69: ASSETTE | H69: BRUSQUE | I69: BEDAINE | J69: BARREAU | K69: CHANT | L69: BARBOTEUS | M69: BASTE | N69: BALLET | O69: AUSTRAL | P69: BANANE | Q69: ARBORETUM | R69: BIOENERGIE | S69: BICEPS | T69: ATRIUM
A70: BAIE | B70: ANDESINE | C70: BICHE | D70: ASSAVOIR | E70: BOUQUET | F70: BATIMENT | G70: ASSISTANT | H70: BRUT | I70: BEIGNET | J70: BATI | K70: CHASSE | L70: BEBE | M70: BATAILLE | N70: BANDE | O70: AUTEL | P70: BAOZI | Q70: ARBRISSEAU | R70: BIOGAZ | S70: BLOC | T70: ATTACHE
A71: BAIGNADE | B71: ANDESITE | C71: BIJOU | D71: ASSERTIF | E71: BOURGEON | F71: BATIR | G71: ASSURANCE | H71: BRUTAL | I71: BELUGA | J71: BATIR | K71: CHASSOIR | L71: BERCE | M71: BATIR | N71: BANDEDESSI | O71: AVENTURE | P71: BASE | Q71: ARBUSTRE | R71: BIOMASSE | S71: BLOCUS | T71: ATTIQUE
A72: BAIGNER | B72: ANHYDRIDE | C72: BIJOUX | D72: ASSONANCE | E72: BOURRACHE | F72: BETTERAVE | G72: ASTIC | H72: BRUTE | I72: BENEFICE | J72: BEY | K72: CHEVALET | L72: BERCER | M72: BATON | N72: BAROQUE | O72: AVION | P72: BASSECOUR | Q72: ARCANE | R72: BIPLITE | S72: BOBINE | T72: AUGE
A73: BAILLE | B73: ANHYDRITE | C73: BINDER | D73: ATTRIBUT | E73: BOUTON | F73: BEURRE | G73: ATOMISTE | H73: BUFFLE | I73: BENTO | J73: BIENFAISAN | K73: CISAILLE | L73: BIENSEANC | M73: BATTE | N73: BASSE | O73: AXE | P73: BEC | Q73: AREC | R73: BITUME | S73: BOMBE | T73: AUREOLE
... A83: BANC | B83: ARGENTAN | C83: BORDE | D83: BICASUEL | E83: BUDDLEIA | F83: BONNETERIE | G83: AUTRICE | H83: CAIMAN | I83: BOISSON | J83: BULLETIN | K83: COMMUNICAT | L83: BREVET | M83: BILLE | N83: BEAUXARTS | O83: BESTIA | P83: BIBERON | Q83: AROMATIQUE | R83: BRENT | S83: CAPACITE | T83: BENIN
A84: BANDE | B84: ARGENTINE | C84: BORDER | D84: BILINGUE | E84: BUGLE | F84: BOULANGER | G84: AVALEUR | H84: CANARD | I84: BOL | J84: BUREAU | K84: COMPAS | L84: BROUETTE | M84: BILLET | N84: BECARRE | O84: BIANCA | P84: BIERE | Q84: ARTHROPODE | R84: BRULAGE | T84: BERTILLONN
A85: BANNIERE | B85: ARGENTITE | C85: BOTTIER | E85: BULBE | F85: BOULEAU | G85: AVOCAT | H85: CANIDE | I85: BONI | J85: BUREAUCRAT | K85: COMPOSTEUR | L85: BULLETIN | M85: BINGO | N85: BEMOL | O85: BINAIRE | P85: BILE | Q85: ARTOCARPE | R85: BRULEUR | S85: CAPOT | T85: BICEPS
A86: BANQUE | B86: ARGENTON | C86: BOUFFANT | D86: CACOGRAPHE | E86: BUTINER | F86: BRASSAGE | G86: BADINE | H86: CANNIBALIS | I86: BORDELAISE | J86: BUSINESS | K86: CONCENTRAT | L86: CADRE | M86: BIODIVERSI | N86: BEQUET | O86: BIOLOGIE | P86: BIO | Q86: ASEXUEE | R86: BRUT | S86: CAPTER | T86: BILE
A87: BANQUER | B87: ARGILE | C87: BOUFFE | D87: CADENCE | E87: CACTUS | F87: BRASSERIE | G87: BAILE | H87: CAPTIVITE | I87: BOUCAN | J87: CABINET | K87: CONCERT | L87: CAHIER | M87: BIT | N87: BERCEUSE | O87: BLAZAR | P87: BISCUIT | Q87: ASPHODELE | R87: BUTANE | S87: CAPTIVER | T87: BIOCHIMIE
A88: BARGE | B88: ARGON | C88: BOURRAGE | D88: CAHIER | E88: CADEAU | F88: BRASSICOLE | G88: BAILLI | H88: CAPUCIN | I88: BOUFFE | J88: CADRE | K88: CONCERTO | L88: CALCUL | M88: BLIND | N88: BESTIAIRE | O88: BLEUE | P88: BITUMER | Q88: ASSAMELA | R88: CABLE | S88: CAPTIVITE | T88: BIOLOGIE
A89: BARQUE | B89: ARGYROSE | C89: BOURRE | D89: CALEMBOUR | E89: CAFEIER | F89: BREVET | G89: BALEINIER | H89: CAPYBARA | I89: BOUILLI | J89: CAFE | K89: CONCRET | L89: CALENDRIER | M89: BLUFF | N89: BIEN | O89: BLUFF | P89: BLANCHIR | Q89: ATACA | R89: CALORIE | S89: CARREE | T89: BIOLOGIEMO
A90: BARRAGE | B90: AROMATIQUE | C90: BOURREE | D90: CALQUE | E90: CALICE | F90: BREVETER | G90: BALISEUR | H90: CARACAL | I90: BOUILLIE | J90: CAISSE | K90: CONNAISSAN | L90: CAMARADE | M90: BLUFFER | N90: BIGUINE | O90: BOITE | P90: BLATTE | Q90: ATOCA | R90: CALORIFIQU | S90: CASTE | T90: BIOLOGIQUE
A91: BARRE | B91: ARSENIC | C91: BOUTIQUE | D91: CAS | E91: CALLUNE | F91: BRICOLEUR | G91: BANQUIER | H91: CARCASSE | I91: BOUILLIR | J91: CALOT | K91: CONNAITRE | L91: CAMPUS | M91: BOG | N91: BIJOU | O91: BOLIDE | P91: BLE | Q91: ATOCATIER | R91: CALORIQUE | S91: CATECHISE | T91: BIOPSIE
A92: BARREUR | B92: ARSENIQUE | C92: BOUTIS | D92: CASUEL | E92: CAMASSIA | F92: BRILLANT | G92: BANQUISTE | H92: CARIBOU | I92: BOUILLOIRE | J92: CAMPUS | K92: CORDE | L92: CANCRE | M92: BOMBARDEME | N92: BISCUIT | O92: BOREAL | P92: BOEUF | Q92: ATTIER | R92: CANALISER | S92: CATHODE | T92: BOSSE
A93: BARREUSE | B93: ARSENITE | C93: BOUTON | D93: CATAPHORE | E93: CAMELIA | F93: BROYEUR | G93: BARREAU | H93: CARNASSIER | I93: BOUILLON | J93: CANCEROLOG | K93: CORNET | L93: CANDIDAT | M93: BOMBARDIER | N93: BISTRE | O93: BOREALE | P93: BOISSON | Q93: AUBIER | R93: CAPACITE | S93: CENTRALE | T93: BOSSELURE
A94: BARROT | B94: ASBESTE | C94: BOUTONNAGE | D94: CATEGORIE | E94: CAMELLIA | F94: BRUIT | G94: BASCULEUR | H94: CARNIVORE | I94: BOULANGER | J94: CANDIDAT | K94: CORNETTE | L94: CANON | M94: BOMBE | N94: BIWA | O94: BOUCLE | P94: BOOSTER | Q94: AUCUBA | R94: CAPTATION | S94: CHALEUR | T94: BOUCHE
A95: BASE | B95: ASPHALTE | C95: BOUTONNER | D95: CAUSE | E95: CAMOMILLE | F95: BUTANE | G95: BASE | H95: CASTOR | I95: BOUREK | J95: CANTON | K95: CORPS | L95: CANTINE | M95: BON | N95: BLUES | O95: BRANCHES | P95: BOUCANER | Q95: AUGERON | R95: CAPTEUR | S95: CHANTIER | T95: BOURSA
A96: BATAILLE | B96: ASTATE | C96: BOUTONS | D96: CCOD | E96: CAMPANULE | F96: CABLAGE | G96: BASSIN | H96: CENTAURE | I96: BOUTEILLE | K96: COUCHOIR | L96: CARNET | M96: BONNETEAU | N96: BOILEAU | O96: BRAS | P96: BOUCHE | Q96: AUNAI | R96: CARACTERE | S96: CHAR | T96: BOUTON
A97: BATEAU | B97: ASTERIE | C97: BRANCHE | D97: CCOI | E97: CAPITULE | F97: CACAO | G97: BASSISTE | H97: CERF | I97: BOY | J97: CAPITOLE | K97: COUPERET | L97: CATECHESE | M97: BONUS | N97: BOIS | O97: BRENNER | P97: BOUCHEE | Q97: AUTONYME | R97: CARBONE | S97: CHARGEUR | T97: BRACHIAL
A98: BATELIER | B98: ASTRONOMIE | C98: BRECHE | D98: CEDILLE | E98: CAPRE | F98: CADENCE | G98: BASTE | H98: CHAIR | I98: BRAISAGE | J98: CARACTERE | K98: COURBE | L98: CATECHISER | M98: BOSS | N98: BOLERO | O98: BRILLANCE | P98: BOUCHER | Q98: AUXINE | R98: CARBURANT | S98: CHARMER | T98: BRANCHE
A99: BATELLERIE | B99: ATOME | C99: BRELOQUE | D99: CESURE | E99: CAPSULE | F99: CAFE | G99: BATELEUR | H99: CHAMEAU | I99: BRAISE | J99: CARACTERIS | K99: COUTEAU | L99: CATECHISM | M99: BOSTON | N99: BOSSA | O99: BRUME | P99: BOUCHERIE | Q99: AVIAIRE | R99: CARBURE | S99: CHAUDIERE | T99: BRECHE
A100: BATIMENT | B100: ATOMIQUE | C100: BRETELLE | D100: CETTE | E100: CAPUCINE | F100: CALIBRE | G100: BATONNIER | H100: CHAMPETRE | I100: BRAISER | J100: CARCERALE | K100: CRAYON | L100: CATHOLIQUE | M100: BOULE | N100: BOULEUR | O100: BULBE | P100: BOUCHES | Q100: AVODIRE | R100: CARBUROL | S100: CHAUFFAGE | T100: BROCHE
A101: BATTANT | B101: AUGITE | C101: BRICOLAGE | D101: CHAINE | E101: CARDAMINE | F101: CAMIONNAGE | G101: BATTE | H101: CHASSE | I101: BRICK | J101: CARDINAL | K101: CROCHET | L101: CEGEP | M101: BOURLE | N101: BOUM | O101: BUT | P101: BOUDIN | Q101: AWALE | R101: CASQUER | S101: CHEF | T101: BRONCHE
A102: BEAUFORT | B102: AUSTENITE | C102: BRIDE | D102: CHAMP | E102: CARDINAL | F102: CANAL | G102: BAYLE | H102: CHASSEACOU | I102: BRIDER | J102: CARTEL | K102: CROISSANT | L102: CENSEUR | M102: BOUT | N102: BOURRES | O102: CABOTIN | P102: BOUFFE | Q102: AZOBE | R102: CATHODE | S102: CHEVAL | T102: BRONCHIQUE
A103: BEAUPRE | B103: AUTUNITE | C103: BROCART | D103: CHARADE | E103: CARLINE | F103: CAOUTCHOUC | G103: BECHE | H103: CHASSER | I103: BRIK | J103: CASINO | K103: CUEILLOIR | L103: CENTRE | M103: BOWLING | N103: BREAKCORE | O103: CADRAN | P103: BOUFFER | Q103: AZOTE | R103: CATION | S103: CHEVALVAPE | T103: BUCCALE
A104: BEQUILLE | B104: AVENTURINE | C104: BROCHAGE | D104: CHOSE | E104: CARMIN | F104: CAPABLE | G104: BECHEUR | H104: CHASSEUR | I104: BRIOCHE | J104: CATHOLICIS | K104: CUIVRE | L104: CERCEAU | M104: BOXE | N104: BRIO | O104: CALCUL | P104: BOUGON | Q104: BACCHANTE | R104: CENTIVOLT | T104: BULBE
A105: BER | B105: AZOTE | C105: BROCHE | D105: CLASSE | E105: CARPELLE | F105: CAPACITE | G105: BECHOIR | H105: CHAT | I105: BROCHE | J105: CATHOLIQUE | K105: CUTTER | L105: CEREBRAL | M105: BOY | N105: BRONZE | O105: CALDERA | P105: BOUILLIE | Q105: BACTERIE | R105: CENTIWATT | S105: CIRCUIT | T105: BUSTE
A106: BERGE | B106: AZURITE | C106: BROCHURE | D106: CLAUSE | E106: CATALPA | F106: CAPITAL | G106: BEDEAU | H106: CHAUVE | I106: BROCHETTE | J106: CAUCUS | K106: CYMBALE | L106: CEREBRALE | M106: BRECHE | N106: BRUIT | O106: CALENDRIER | P106: BOUILLON | Q106: BADAMIER | R106: CENTRALE | S106: CITOYEN | T106: CADAVRE
A107: BIEF | B107: BALANCE | C107: BRODE | D107: CLAUSULE | E107: CENTAUREE | F107: CAPTEUR | G107: BEDEISTE | H107: CHEVAL | I107: BRULE | J107: CENTRALISA | K107: DAVIER | L107: CERTIFICAT | M107: BREDOUILLE | N107: BRUITISTE | O107: CAMERA | P107: BOULIMIE | Q107: BAGASSE | R107: CENTRIFUGE | S107: CLASSEOUVR | T107: CALICE
A108: BITTE | B108: BARYTE | C108: BRODER | D108: COD | E108: CERISIER | F108: CARBURANT | G108: BERCEAU | H108: CHEVRE | I108: BRULOIR | K108: DEBITAGE | L108: CERVEAU | M108: BRELAN | N108: BUDO | O108: CANCER | P108: BOUSTIFAIL | Q108: BAGUIER | R108: CENTROIDE | S108: COALITION | T108: CALOTTE
A109: BLOCUS | B109: BARYTINE | C109: BRODERIE | D109: COGNITION | E109: CHALEUR | F109: CARBURE | G109: BESSON | H109: CHEVREUIL | I109: BRUNIR | J109: CENTRE | K109: DECAPEUR | L109: CERVELET | M109: BRIDGE | N109: BUNRAKU | O109: CANICULE | P109: BRAISE | Q109: BAIE | R109: CHALEUR | S109: COCA | T109: CALVAIRE
A110: BORD | B110: BARYUM | C110: BRODEUR | D110: COHERENCE | E110: CHAMPIGNON | F110: CARTEL | G110: BIDENT | H110: CHIEN | I110: BUANDERIE | J110: CERCLE | K110: DECOUPOIR | L110: CHAIRE | M110: BUT | N110: BUSTE | O110: CAPSULE | P110: BRANCHIE | Q110: BALANITE | R110: CHAMP | S110: COERCITIF | T110: CAMBA
A111: BORDE | B111: BASALTE | C111: BUCHE | D111: COI | E111: CHARME | F111: CARTON | G111: BIDULE | H111: CHIMPANZE | I111: BUDGETAIR | J111: CEREMONIE | K111: DENSITOMET | L111: CHANT | M111: BUTEUR | N111: BUTO | O111: CAPTEUR | P111: BREUVAGE | Q111: BALATA | R111: CHARBON | S111: COEUR | T111: CANAL
A112: BORDEE | B112: BASANITE | C112: BUSC | D112: COMMITATIF | E112: CHARNU | F112: CARTONNAGE | G112: BIENETRE | H112: CHOQUANT | I112: BUFFET | J112: CHAMBRE | K112: DENTICULE | L112: CHERCHER | M112: CACHE | N112: BYZANTIN | O112: CARDANER | P112: BRICOLER | Q112: BALSAMIER | R112: CHARGE | S112: COLLINE | T112: CANE
...

Sheet M3
A1: ALKAMO — M3
A2: N° | B2: THÈME | C2: MOTS
A3: 1 | B3: JEU ET SPORT | C3: =COUNTA(M3_mots!A3:A5000) -> 1180
A4: 2 | B4: TEMPS ET MÉTÉO | C4: =COUNTA(M3_mots!B3:B5000) -> 564
A5: 3 | B5: INFORMATIQUE | C5: =COUNTA(M3_mots!C3:C5000) -> 1167
A6: 4 | B6: MATHÉMATIQUES | C6: =COUNTA(M3_mots!D3:D5000) -> 940
A7: 5 | B7: AGRICULTURE | C7: =COUNTA(M3_mots!E3:E5000) -> 787
A8: 6 | B8: ART | C8: =COUNTA(M3_mots!F3:F5000) -> 971
A9: 7 | B9: NAVIGATION | C9: =COUNTA(M3_mots!G3:G5000) -> 1093
A10: 8 | B10: FAUNE ET FLORE | C10: =COUNTA(M3_mots!H3:H5000) -> 951
A11: 9 | B11: GUERRE | C11: =COUNTA(M3_mots!I3:I5000) -> 735
A12: 10 | B12: ADMINISTRATION | C12: =COUNTA(M3_mots!J3:J5000) -> 1081
A13: 11 | B13: FAMILLE | C13: =COUNTA(M3_mots!K3:K5000) -> 448
A14: 12 | B14: PHYSIQUE ET CHIMIE | C14: =COUNTA(M3_mots!L3:L5000) -> 1456
A15: 13 | B15: PAYS ET CAPITALES | C15: =COUNTA(M3_mots!M3:M5000) -> 819
A16: 14 | B16: MÉDECINE ET ANATOMIE | C16: =COUNTA(M3_mots!N3:N5000) -> 1575
A17: 15 | B17: COMMERCE | C17: =COUNTA(M3_mots!O3:O5000) -> 1019
A18: 16 | B18: DROIT ET JUSTICE | C18: =COUNTA(M3_mots!P3:P5000) -> 703
A19: 17 | B19: LITTÉRATURE | C19: =COUNTA(M3_mots!Q3:Q5000) -> 649
A20: 18 | B20: TOURISME | C20: =COUNTA(M3_mots!R3:R5000) -> 471
A21: 19 | B21: URBANISME | C21: =COUNTA(M3_mots!S3:S5000) -> 628
A22: 20 | B22: MER ET OCÉAN | C22: =COUNTA(M3_mots!T3:T5000) -> 1152
A23: TOTAL | C23: =SUM(C3:C22) -> 18389

Sheet M3_mots
A1: JEU ET SPORT | B1: TEMPS ET MÉTÉO | C1: INFORMATIQUE | D1: MATHÉMATIQUES | E1: AGRICULTURE | F1: ART | G1: NAVIGATION | H1: FAUNE ET FLORE | I1: GUERRE | J1: ADMINISTRATION | K1: FAMILLE | L1: PHYSIQUE ET CHIMIE | M1: PAYS ET CAPITALES | N1: MÉDECINE ET ANATOMIE | O1: COMMERCE | P1: DROIT ET JUSTICE | Q1: LITTÉRATURE | R1: TOURISME | S1: URBANISME | T1: MER ET OCÉAN
A2: =COUNTA(A3:A5000) -> 1180 | B2: =COUNTA(B3:B5000) -> 564 | C2: =COUNTA(C3:C5000) -> 1167 | D2: =COUNTA(D3:D5000) -> 940 | E2: =COUNTA(E3:E5000) -> 787 | F2: =COUNTA(F3:F5000) -> 971 | G2: =COUNTA(G3:G5000) -> 1093 | H2: =COUNTA(H3:H5000) -> 951 | ... T2: =COUNTA(T3:T5000) -> 1152
A3: ACADEMIE | B3: ABAS | C3: ABSTRAIT | D3: ABAQUE | E3: ABATTOIR | F3: ABSTRAIT | G3: ABATEE | H3: ABATTAGE | I3: ABRI | J3: ABATTEMENT | K3: ACCUEIL | L3: ABDOMEN | M3: ABDIQUER | N3: ABCES | O3: ABATAGE | P3: ABROGATION | Q3: ABSTRACTIO | R3: ABRI | S3: ABRI | T3: ABATEE
A4: ACCESSOIRE | B4: ABAT | C4: ACADEMIE | D4: ABELIEN | E4: ABLAIS | F4: ACADEMISME | G4: ABER | H4: ABATTOIR | I4: ACADEMIE | J4: ABOLITION | K4: ADOLESCENC | L4: ACCUM | M4: ABIDJAN | N4: ABDOMEN | O4: ACCORD | P4: ABSOLUTION | Q4: ABSTRAIT | R4: ACCUEIL | S4: ABRIBUS | T4: ABER
A5: ACCORD | B5: ABONDANCE | C5: ACCES | D5: ABSCISSE | E5: ABOITEAU | F5: ACCORD | G5: ABORD | H5: ABBAYE | I5: ACCORD | J5: ABROGER | K5: ADOLESCENT | L5: ACETAMIDE | M5: ACCORD | N5: ABDOMINAL | O5: ACCORDER | P5: ABUS | Q5: ACADEMICIE | R5: ACCUEILS | S5: ABSIDE | T5: ABORD
A6: ACQUISITIO | B6: ABONDANTE | C6: ACCUEIL | D6: ABSOLUE | E6: ABRICOT | F6: ACCORDAGE | G6: ABORDAGE | H6: ABEILLE | I6: ACHARNE | J6: ABSOLU | K6: ADOPTER | L6: ACETATE | M6: ACCRA | N6: ABDUCTEUR | O6: ACCUMULER | P6: ABUSUS | Q6: ACADEMISME | R6: AEROPORT | S6: ACCROISSEM | T6: ABORDAGE
A7: ACROBATIE | B7: ABRI | C7: ACTIVATION | E7: ABUSER | F7: ACCORDEON | G7: ABORDER | H7: ABRUPT | I7: ACHARNEMEN | J7: ABUS | K7: ADOPTIF | L7: ACETONE | M7: ACCREDITE | N7: ABOLIR | O7: ACHAT | P7: ACCEDIT | Q7: ACCENT | R7: AFFLUENT | S7: ACCROTERE | T7: ABORDER
A8: ACROSPORT | B8: ABRITER | C8: ACTIVER | D8: ABSTRAITE | E8: ACARIOSE | F8: ACCORDEUR | G8: ABRI | H8: ACACIA | I8: ACHEEN | J8: ABUSIF | K8: ADOPTION | L8: ACETYLENE | M8: ACCUEILLIR | N8: ABSORPTION | O8: ACHETER | P8: ACCENSE | Q8: ACCESSOIRE | R8: AFFLUT | S8: ACIER | T8: ABRI
A9: ACTEUR | B9: ABSOLU | C9: ACTUALISER | D9: ABSURDE | E9: ACMEE | F9: ACCROCHE | G9: ABYSSAL | H9: ACAJOU | I9: ACIER | J9: ACADEMIE | K9: ADOPTIVE | L9: ACIDE | M9: ACHGABAT | N9: ACADEMIE | O9: ACHETEUR | P9: ACCORD | Q9: ACROSTICHE | R9: AFFLUX | S9: ACROPOLE | T9: ABYSSAL
A10: ACTIF | B10: ACCALMIE | C10: ADAPTATEUR | D10: ACUTANGLE | E10: ACREAGE | F10: ACHROME | G10: ACCALMIE | H10: ACANTHE | I10: ACTION | J10: ACADEMIQUE | K10: ADULTE | L10: ACIER | M10: ADDIS | N10: ACANTHE | O10: ACOMPTE | P10: ACCUSATION | Q10: ACTE | R10: AGENCE | S10: AEROPORT | T10: ACCALMIE
A11: ACTION | C11: ADRESSE | D11: ADDITION | E11: ACTIVITE | F11: ACORDE | G11: ACCONAGE | H11: ADAPTATION | I11: ACTIVISTE | J11: ACCIDENT | K11: AFFECTION | L11: ACOUSTIQUE | M11: ADRESSE | N11: ACCOUCHEUR | O11: ACQUET | P11: ACCUSE | Q11: ACTEURS | R11: AGREABLE | S11: AGENCEMENT | T11: ACCONAGE
A12: ACTIONNAIR | B12: ACCLIMATAT | C12: ADWARE | D12: ADHERENT | E12: ADONNER | F12: ACTE | G12: ACCORE | H12: AGIR | I12: ADVERSAIRE | J12: ACCOMMODER | K12: AFFIN | L12: ACRYLIQUE | M12: ADROIT | N12: ACCUEIL | O12: ACQUISE | P12: ACCUSER | Q12: ACTION | R12: AGREMENT | S12: AGGLOMERAT | T12: ACCORE
A13: ACTIVITE | B13: ACCORDER | C13: AFFECTER | D13: ADJACENT | E13: ADOS | F13: ACTEUR | G13: ACCOSTAGE | H13: AGNEAU | I13: AERIEN | J13: ACCORD | K13: AFFINITE | L13: ACTIF | M13: AFFAIRES | N13: ACCUEILLIR | O13: ACQUIT | P13: ACQUERIR | Q13: ACTUALISME | R13: AIR | S13: AGGLOMERE | T13: ACCOSTAGE
A14: ADAPTATEUR | B14: AGE | C14: AFFECTUEUX | D14: ADJOINT | E14: AERER | F14: ACTIVITES | G14: ACCOSTER | H14: AGRESSIF | I14: AERODROME | J14: ACCUEIL | K14: AGE | L14: ACTINIUM | M14: AFFIRME | N14: ACETABULE | O14: ACTIF | P14: ACQUET | Q14: ACTUALITE | R14: ALBUM | S14: AGORA | T14: ACCOSTER
A15: ADAPTATIVE | B15: AGILITE | C15: AFFICHAGE | D15: AFFECTER | E15: AFFINER | F15: ACTRICE | G15: ACONIER | H15: AGRESSIVIT | I15: AERONEF | J15: ACCUSE | K15: AIEUL | L15: ACTINOTE | M15: AFRIQUE | N15: ACINI | O15: ACTION | P15: ACQUIT | Q15: ADAPTATIO | R15: ALLER | S15: AGRANDISSE | T15: ACONIER
A16: ADDICTIF | B16: AGITATION | C16: AFFICHE | D16: AFFINE | E16: AGATIS | F16: ACTUALITE | G16: ACTUAIRE | H16: AGRESTE | I16: AFFAIRE | J16: ACHEMINER | K16: AIEULE | L16: ACTION | M16: AGENTDIPL | N16: ACNE | O16: ACTIVITE | P16: ACQUITTE | Q16: ADMIRATEU | R16: ALPIN | S16: AIR | T16: ACTUAIRE
A17: ADOPTER | B17: AIR | C17: AFFICHEUR | D17: AFFIXE | E17: AGNEAU | F17: ADAGIO | G17: AERIEN | H17: AIGLE | I17: AFFRONTEME | J17: ACOMPTE | K17: AIMANTE | L17: ACTIVATION | M17: AGRICOLE | N17: ACOUSIE | O17: AERIEN | P17: ACTE | Q17: AFFECTE | R17: ALPINISME | S17: ALEM | T17: AERIEN
A18: ADVERSAIRE | B18: ALERTE | C18: AFFILIE | D18: AGREGATION | E18: AGRAIRE | F18: ADMIRATEU | G18: AEROBUS | H18: AIGRETTE | I18: AFFRONTER | J18: ACQUET | K18: AIMER | L18: ACTIVITE | M18: ALBANIE | N18: ACUPUNCTUR | O18: AFFAIRE | P18: ACTIF | Q18: AFFECTIF | R18: AMBULANT | S18: ALFIZ | T18: AEROBUS
A19: ADVERSE | B19: ALIZE | C19: AFFILIER | D19: AIGU | E19: AGRI | F19: ADMIRATION | G19: AERODYNE | H19: AILE | I19: AFFUT | J19: ACQUIT | K19: AINE | L19: ADAMANTIN | M19: ALGER | N19: ADAPTATIF | O19: AFFLUX | P19: ACTION | Q19: AFFECTUEU | R19: AMI | S19: ALLEE | T19: AERODYNE
A20: AERIEN | B20: ALMANACH | C20: AGENT | D20: AIRE | E20: AGRIAL | F20: ADMIRER | G20: AERONAVAL | H20: AIR | I20: AGHA | J20: ACRONYME | K20: AINOU | L20: ADAMITE | M20: ALGERIE | N20: ADAPTEE | O20: AGENCE | P20: ACTIONNER | Q20: AFFICHE | R20: AMIE | S20: AMENAGER | T20: AERONAVAL
A21: AEROBIC | B21: ALTITUDE | C21: AGILE | D21: AJOUT | E21: AGRICOLE | F21: ADRESSE | G21: AERONEF | H21: AIRELLE | I21: AGRESSIF | J21: ACTE | K21: AISEE | L21: ADROIT | M21: ALLEGEANC | N21: ADDUCTEUR | O21: AGENT | P21: ADJUGER | Q21: AIMANT | R21: AMIS | S21: AMEUBLEME | T21: AERONEF
A22: AFFICHAGE | B22: AMBIANCE | C22: AIGUILLE | D22: ALEATOIRE | E22: AGRICULTEU | F22: AEROBIC | G22: AEROPLANE | H22: AJONC | I22: AGRESSION | J22: ACTES | K22: ALLIANCE | L22: ADULAIRE | M22: ALLEMAGNE | N22: ADMINISTRE | O22: AGIO | P22: ADMINISTRA | Q22: AIR | R22: AMITIE | S22: ANARCHIQUE | T22: AEROPLANE
A23: AGILITE | B23: AMPLITUDE | C23: ALARME | D23: ALGEBRE | F23: AEROGRAPHE | G23: AEROSTAT | H23: ALBATROS | I23: AGUERRIR | J23: ACTION | K23: ALLIE | L23: AEGYRINE | M23: ALLIANCE | N23: ADNEE | O23: AGIOTAGE | P23: AFFAIRE | Q23: ALARMANT | R23: ANIMATION | S23: ANNEXION | T23: AEROSTAT
A24: AIKIDO | B24: AMURE | C24: ALEATOIRE | D24: ALGEBRIQUE | E24: AGROLOGIE | F24: AFFICHE | G24: AFFALER | H24: ALBINOS | I24: AIR | J24: ACTIVITE | K24: ALLOCATAIR | L24: AEROSOL | M24: ALOFI | N24: ADOUCIR | O24: AGNEL | P24: AFFERENT | Q24: ALEXANDRIN | R24: AOUTIEN | S24: APPARTEME | T24: AFFALER
A25: AILIER | B25: ANCIENNETE | C25: ALERTE | D25: ALGORITHME | E25: AGRONOME | F25: AGON | G25: AFFINER | H25: ALBUMINE | I25: ALLIANCE | J25: ACTUAIRE | K25: ALLOCATION | L25: AETITE | M25: AMBASSADE | N25: ADRENALINE | O25: AGREAGE | P25: AFFIDAVIT | Q25: ALLEGORIE | R25: ARCHIPEL | S25: AQUEDUC | T25: AFFINER
A26: ALEATOIRE | B26: ANEMOMETRE | C26: ALGEBRE | D26: ALIQUOTE | E26: AGRONOMIE | F26: AIKIDO | G26: AFFRETER | H26: ALEVINS | I26: ALLIE | J26: ADAPTEE | K26: AMI | L26: AFFINITE | M26: AMBASSADEU | N26: AFFECT | O26: AGREEUR | P26: AGNAT | Q26: ALLEGORIQ | R26: ARRET | S26: ARC | T26: AFFRETER
A27: ALLIANCE | B27: ANNEE | C27: ALGORITHME | D27: AMPERE | E27: AGRUME | F27: AIR | G27: AFFRETEUR | H27: ALGOIDE | I27: AMIRAL | J27: ADHESION | K27: AMICAL | L27: AGATE | M27: AMERIQUE | N27: AFFECTER | O27: AGRICOLE | P27: AGREMENT | R27: ARRIVE | S27: ARCADE | T27: AFFRETEUR
A28: ALLIE | B28: ANNUEL | C28: ALIGNEMENT | D28: AMPLITUDE | E28: AIGREUR | F28: AISANCE | G28: AGREEUR | H28: ALGUE | I28: AMIRAUTE | J28: ADJOINT | K28: AMIE | L28: AGILE | M28: AMMAN | N28: AFFECTION | O28: AGUICHE | P28: AIGAGE | Q28: AMPHITHEAT | R28: ARRIVEE | S28: ARCATURE | T28: AGREEUR
A29: ALPINISME | B29: ANTARCTIQU | C29: ALLOCATION | D29: ANALYSE | E29: AIL | F29: ALBUM | G29: AGRES | H29: ALIMENT | I29: AMORCE | J29: ADMINISTRA | K29: AMITIE | L29: AGILITE | M29: AMSTERDAM | N29: AGIR | O29: AIDE | P29: ALIBI | Q29: AMPOULE | R29: ARRIVER | S29: ARCEAU | T29: AGRES
A30: ALUETTE | B30: ANTECEDENT | C30: ALLUMAGE | D30: ANALYSTE | E30: AIMER | F30: ALCHIMIE | G30: AIGUILLEUR | H30: ALIMENTAIR | I30: ANCIEN | K30: AMOUR | L30: AGROALIMEN | M30: ANCIENNE | N30: AGREGE | O30: AISANCE | P30: ALINEA | Q30: ANALEPSE | R30: ART | S30: ARCHEVECH | T30: AIGUILLEUR
A31: AMATEUR | B31: ANTERIORIT | C31: ALLUMER | D31: ANALYTIQUE | E31: AIREE | F31: ALLEGORIE | G31: AIRE | H31: ALLEE | I31: ANIMOSITE | J31: ADMINISTRE | K31: AMOUREUX | L31: AIMANT | M31: ANDORRE | N31: AIDE | O31: ALENA | P31: ALLEGORIE | Q31: ANAPHORE | R31: ARTISANAT | S31: ARCHITECTE | T31: AIRE
A32: AMBIANCE | B32: ANTICYCLON | C32: ALPHA | D32: ANGLE | E32: ALEVINAGE | F32: ALLEGRO | G32: AJUT | H32: ALLIGATOR | I32: ANNEXION | J32: ADOPTION | K32: ANALOGIE | L32: AIR | M32: ANGLAIS | N32: AIDER | O32: ALLOCATION | P32: ALLEGUER | Q32: ANGELISME | R32: ATOUT | T32: AJUT
A33: AMICAL | B33: ANTIQUITE | C33: AMER | D33: ANNEAU | E33: ALFA | F33: ALTO | G33: ALBATROS | H33: ALPAGA | J33: ADRESSE | K33: ANCESTRAL | L33: AIRAIN | M33: ANGLETERRE | N33: AIGUILLE | O33: ALOI | P33: ALLOTER | Q33: ANONYME | R33: ATTIRE | S33: ARCOLOGIE | T33: ALBATROS
A34: AMORTI | B34: ARBRE | C34: AMERTUME | D34: ANSE | E34: ALFATIER | F34: AMATEUR | G34: ALERTE | H34: ALPIN | I34: ANTAGONIST | J34: AFFAIRE | K34: ANCETRE | L34: AIRE | M34: ANGOLA | N34: AILE | O34: ALTERATION | P34: AMENDE | Q34: ANTHOLOGIE | R34: ATTRACTIF | S34: AREA | T34: ALERTE
A35: AMPHITHEAT | B35: ARC | C35: AMITIE | D35: ANTECEDENT | E35: ALIMENT | F35: AMBITION | G35: ALGUES | H35: ALPINE | I35: ANTICHAR | J35: AGENCE | K35: ANTECEDENT | L35: ALABANDINE | M35: ANKARA | N35: AINE | O35: AMENDE | P35: AMIABLE | Q35: ANTITHESE | R35: ATTRACTION | S35: ART | T35: ALGUE
A36: AMUSANT | B36: ARCENCIEL | C36: AMNESIE | D36: ANTINOMIE | E36: ALPAGE | F36: ANDANTE | G36: ALLEE | H36: ALTRUISTE | I36: ANTIDROGUE | J36: AGENCEMENT | K36: ANTHROPOLO | L36: ALABANDITE | M36: ANNEXER | N36: AIR | O36: AMENDER | P36: AMISSION | Q36: APARTES | R36: ATTRAIT | S36: ARTERE | T36: ALGUES
A37: AMUSEMENT | B37: ARCTIQUE | C37: AMORCE | D37: APOTHEME | E37: AMELIORER | F37: ANIMATEUR | G37: ALLEGE | H37: AMERINDIEN | J37: AGENCER | K37: APPARENTE | L37: ALBATRE | M37: ANNEXION | N37: AISSELLE | O37: AMITIE | P37: ANNAL | Q37: APHORISME | R37: AUBERGE | S37: ARTIFICIAL | T37: ALLEE
A38: AMUSER | B38: ARIDE | C38: AMOVIBLE | D38: APPLICATIO | E38: AMENAGER | F38: ANTILABE | G38: ALLERVOILE | H38: AMIBE | I38: ANTITABAC | J38: AGENT | K38: APPARENTEM | L38: ALBEDO | M38: APIA | N38: AJUSTER | O38: AMORTIR | P38: ANNALE | Q38: APOLOGUE | R38: AUTOCAR | S38: ARTISTE | T38: ALLEGE
A39: ANALYSER | B39: ARIDITE | C39: AMPLIFIER | D39: APPLIQUER | E39: AMENDEMENT | F39: ANTIQUE | G39: ALLURE | H39: AMPHIBIE | I39: ANTITERROR | J39: AGORA | K39: APPARTEMEN | L39: ALBITE | M39: APPEL | N39: ALCALOIDE | O39: AMPLEUR | P39: ANNEXE | Q39: APOSTROPHE | R39: AUTORAIL | S39: ASPECT | T39: ALLERVOILE
A40: ANIMATEUR | B40: ARROSAGE | C40: AMULETTE | D40: APPROXIMER | E40: AMEUBLIR | F40: ANTIQUITE | G40: ALOSE | H40: ANATOMIE | I40: APOTRE | J40: AGREE | K40: APPARTENAN | L40: ALBUGINE | M40: ARABIE | N40: ALIENE | O40: ANALYSE | P40: ANNULATION | Q40: APPRETE | R40: AVENTURE | S40: ASPHALTE | T40: ALLURE
A41: ANIMER | B41: ASTRONOMIQ | C41: ANALOGIQUE | D41: APRETE | E41: AMIDON | F41: APARTE | G41: ALTIPORT | H41: ANE | I41: APPELE | J41: AGREMENT | K41: ARBRE | L41: ALBUGO | M41: ARBITRE | N41: ALIENISTE | O41: ANALYSTE | P41: ANNULER | Q41: ARABE | R41: AVENTURIE | S41: ASSAINISSE | T41: ALOSE
A42: ANNEAUX | B42: ATMOSPHER | C42: ANALYSE | D42: ARAGO | E42: ANANAS | F42: AQUARELLE | G42: AMARINER | H42: ANGUILLE | I42: APRESGUERR | J42: AGRICOLE | K42: ARGENT | L42: ALCALI | M42: ARBITRER | N42: ALLAITER | O42: ANNALITE | P42: ANNULITE | Q42: ARGUMENT | R42: AVENTURIER | S42: ASSIEGEE | T42: ALTIPORT
B43: ATMOSPHERE | C43: ANALYSER | D43: ARBRE | E43: ANCON | F43: ARABESQUE | G43: AMARRAGE | H43: ANIMAL | I43: ARBITRAGE | J43: AJUSTER | K43: ARISTOCRAT | L43: ALCALIN | M43: ARCHIVE | N43: ALLERGIE | O43: ANNONCE | P43: ANTECEDENT | Q43: ARIA | R43: BADAUD | S43: ATRIUM | T43: AMARINER
A44: ANTICIPER | B44: ATTENDANT | C44: ANALYSTE | D44: ARC | E44: ANDIN | F44: ARCHET | G44: AMARRE | H44: ANIMALERIE | I44: ARBITRE | J44: ALIGNER | K44: ARRIERE | L44: ALCALINITE | M44: ARGENTINE | N44: ALLOPATHE | O44: ANNUEL | P44: APOSTILLE | Q44: ARRANGE | R44: BAGAGE | S44: ATTIQUE | T44: AMARRAGE
A45: ANTIDOPAGE | B45: ATTENTE | C45: ANAMNESE | D45: ARCHIMEDE | E45: ANE | F45: ARIA | G45: AMARRER | H45: ANIMALIER | I45: ARCHER | J45: ALINEA | K45: ASCENDANCE | L45: ALCANE | M45: ARMEE | N45: ALLOPATHIE | O45: ANNUITE | P45: APPARAT | Q45: ART | R45: BAGAGES | T45: AMARRE
A46: APNEE | B46: AUBE | C46: ANCRE | D46: ARETE | E46: ANIMAL | F46: ARPEGE | G46: AMARRES | H46: ANIMALITE | I46: ARENE | J46: ALLEGRESSE | K46: ASCENDANT | L46: ALCANES | M46: ARMENIE | N46: ALVEOLE | O46: ANTIQUAIRE | P46: APPEL | Q46: ARTHURIEN | R46: BAIE | S46: AUTOBUS | T46: AMARRER
A47: APNEISTE | B47: AUPARAVANT | C47: ANDROID | D47: ARGUMENT | E47: ANIMER | F47: ART | G47: AME | H47: ANOURE | I47: ARGOULET | J47: ALLIANCE | K47: ASSEMBLEE | L47: ALCENE | M47: ARMENIEN | N47: ALZHEIMER | O47: APPEL | P47: APPRECIAT | Q47: ARTIFICIE | R47: BAIGNADE | S47: AUTOCAR | T47: AMARRES
A48: APPROCHE | B48: AURORE | C48: ANDROIDE | D48: ARITHMETIQ | E48: APICOLE | G48: AMER | H48: ANTHROPOPH | I48: ARME | J48: ALLOCATION | K48: ASSOCIATIO | L48: ALCHIMIE | M48: ARTIFICE | N48: AMADOUER | O48: APPOINT | P48: ARBITRAGE | Q48: ARTISTE | R48: BAIGNEUR | S48: AUTOMOBILE | T48: AMBRE
A49: APPROPRIE | B49: AUTAN | C49: ANECDOTE | D49: ARRONDI | E49: APICULTURE | F49: ARTIFICE | G49: AMERRIR | H49: ANTILOPE | I49: ARMEE | J49: ALLOUER | K49: ATELIER | L49: ALCHIMISTE | M49: ASIATIQUE | N49: AMBON | O49: APPORT | P49: ARBITRAIRE | Q49: ARTISTIQUE | R49: BAIN | S49: AUTOPONT | T49: AME
A50: AQUAGYM | B50: AUTOMNE | C50: ANECDOTES | D50: ARRONDIR | E50: APPRENDRE | F50: ARTISAN | G50: AMERS | H50: APPETIT | I50: ARMEMENT | J50: AMBASSADE | K50: ATTIRANCE | L50: ALCOOL | M50: ASIE | N50: AMBULANCE | O50: APPORTEUR | P50: ARBITRE | Q50: ASPECT | R50: BALADE | S50: AUTOROUTE | T50: AMER
A51: AQUAPLANE | B51: AVANCER | C51: ANNALES | D51: ART | E51: AQQUICOLE | F51: ARTISANAT | G51: AMIRAL | H51: APPRIVOIS | I51: ARMER | J51: AMENAGEMEN | K51: AUTORITEPA | L51: ALDEHYDE | M51: ASILE | N51: AMBULANCIE | O51: APPROVISIO | P51: ARCHEVEQUE | Q51: ASSONANCE | R51: BALLADE | S51: AUVENT | T51: AMERRIR
A52: ARBALETE | B52: AVENIR | C52: ANNEAU | D52: ARTS | E52: AQUACOLE | F52: ARTISTE | G52: AMIRAUTE | H52: APTITUDE | I52: ARMET | J52: AMIRAUTE | K52: BAPTEME | L52: ALDEHYDES | M52: ASMARA | O52: ARBITRAGE | P52: ARCHIDIOCE | Q52: ATTENTAT | R52: BALNEAIRE | S52: AVAL | T52: AMERS
A53: ARBITRAGE | B53: AVERSE | C53: ANNIVERSAI | D53: ASCETISME | E53: AQUEDUC | F53: ARTISTERIE | G53: AMMARE | H53: AQUARIUM | I53: ARMISTICE | J53: ANALYSE | K53: BEAU | L53: ALGEBRE | M53: ASSIMILAT | N53: AMELIORER | O53: ARGENT | P53: ARGUMENT | Q53: ATTRIBUER | R53: BANQUET | S53: AVENUE | T53: AMIRAL
A54: ARBITRAL | B54: AVERSES | C54: ANNOTE | D54: ASSIDUITE | E54: ARABLE | F54: ARTISTIQUE | G54: AMONT | H54: AQUATIQUE | I54: ARMURE | J54: ANARCHIE | K54: BEAUFRERE | L54: ALIMENTS | M54: ASTANA | N54: AMENAGEMEN | O54: ARGENTIER | P54: ARRESTATIO | Q54: AUBE | R54: BARBECUE | S54: BALCON | T54: AMIRAUTE
A55: ARBITRE | B55: AVOIR | C55: ANNULE | D55: ASSOCIATIF | E55: ARAIRE | F55: ARTMODERNE | G55: AMURE | H55: ARA | I55: ARRETS | J55: ANARCHISME | K55: BEAUPERE | L55: ALIZARINE | M55: ASTUCE | N55: AMINE | O55: ARMATEUR | P55: ARRET | Q55: AUTEUR | R55: BARQUE | S55: BALEARISAT | T55: AMMARE
A56: ARBITRER | B56: BANQUISE | C56: ANTISLASH | D56: ASTROIDE | E56: ARANT | G56: ANCHOIS | H56: ARAIGNEE | I56: ARSENAL | J56: ANATOMIQUE | K56: BEBE | L56: ALLANT | M56: ASTUCIEUX | N56: AMPHETAMIN | O56: ARPAILLEUR | P56: ARRETE | Q56: AUTEURE | R56: BATEAU | S56: BALNEAIRE | T56: AMONT
A57: ARCADE | B57: BAROMETRE | C57: ANTIVIRUS | D57: ASTROLOGIE | E57: ARBRE | F57: ASPECT | G57: ANCRAGE | H57: ARBRE | I57: ARTILLERIE | J57: ANIMATEUR | K57: BELLE | L57: ALLEGRE | M57: ASUNCION | N57: AMPHITHEAT | O57: ARRANGER | P57: ARRETER | Q57: AUTOBIOGRA | R57: BERLINE | S57: BALUSTRE | T57: AMURE
A58: ARCHER | B58: BASSIN | C58: APERCU | D58: ASTRONOMIE | E58: ARCON | F58: ASSYRIEN | G58: ANCRE | H58: ARCHETYPE | I58: ARTILLEUR | J58: ANIMER | K58: BELLEMERE | L58: ALLIAGE | M58: ATHENES | N58: AMPOULE | O58: ARRENTER | P58: ARRETISTE | Q58: AUTOFICTIO | R58: BILLET | S58: BANC | T58: ANCHOIS
A59: ARCHERIE | B59: BATTANTE | C59: APEX | D59: ASYMPTOTE | E59: ARCURE | F59: ATELIER | G59: ANCRER | H59: ARGILE | I59: ASKARI | J59: ANNONE | K59: BELLESOEUR | L59: ALLOPHANE | M59: ATTACHE | N59: AMPUTER | O59: ARRERAGES | P59: ARTICLE | Q59: AUTOGRAPHE | R59: BISTROT | S59: BANDITE | T59: ANCRAGE
A60: ARENE | B60: BIODIVERSI | C60: APPAREIL | D60: ATTRIBUT | E60: ARDU | F60: ATTRACTION | G60: ANGARIE | H60: ARIDE | I60: ASPIRANT | J60: ANNULER | K60: BENEFICIAI | L60: ALLOTROPIE | M60: ATTENTAT | N60: AMYGDALE | O60: ARRHER | P60: ARTICULE | Q60: AUTRICE | R60: BONDE | S60: BANLIEUE | T60: ANCRE
A61: ARGENT | B61: BISE | C61: ARBRE | D61: AUTOMATIQU | E61: ARE | F61: AUDITEUR | G61: ANGLE | H61: ARIDITE | I61: ASSAILLANT | J61: APPOSER | K61: BENEFICIER | L61: ALMANDIN | M61: AUDIENCE | N61: AMYLASE | O61: ARRHES | P61: ASILE | Q61: AVANTSCENE | R61: BORD | S61: BAR | T61: ANCRER
A62: ARMEE | B62: BLIZZARD | C62: ARCHIVE | D62: AUTORITE | E62: AREAGE | F62: AUDITION | G62: ANNEXE | H62: ARTHROPODE | I62: ASSAILLIR | J62: APPRETER | K62: BENJAMIN | L62: ALMANDINE | M62: AUSTRALIE | N62: ANAGLYPHE | O62: ARRIERE | P62: ASSASSINAT | Q62: AVENTURE | R62: BOURLINGUE | S62: BARDAGE | T62: ANGARIE
A63: ARRIERE | B63: BOUE | C63: ARCHIVER | D63: AXE | E63: ARIDITE | F63: AUTEUR | G63: ANORDIR | H63: ASSOUVIR | I63: ASSAUT | J63: APPROUVER | K63: BERCAIL | L63: ALMELEC | M63: AUTOCHTONE | N63: ANAL | O63: ARRIMAGE | P63: ASSEOIR | Q63: BAL | R63: BOUTIQUE | S63: BARRAGE | T63: ANGLE
A64: ARTISTE | B64: BOUEUX | C64: ARCHIVES | D64: AXIOME | E64: ARPENT | F64: BAL | G64: ANSE | H64: AUBIER | I64: ASSER | J64: ARBITRAIRE | K64: BERCEAU | L64: ALPAX | M64: AUTODETER | N64: ANALGESIQU | O64: ARTEL | P64: ASSESSEUR | Q64: BALLADE | R64: BRONZER | S64: BARRIERE | T64: ANNEXE
A65: ASSEMBLER | B65: BOUFFEE | C65: ARDOISE | D65: AZIMUT | E65: ARROSAGE | F65: BALADEUR | G65: ANSPECT | H65: AULNE | I65: ASSIEGER | K65: BERCER | L65: ALUMINE | M65: AUTONOMIE | N65: ANALYSE | O65: ARTISAN | P65: ASSIGNER | Q65: BALLE | R65: BROUILLARD | S65: BASSIN | T65: ANORDIR
A66: ASTUCE | B66: BOURRASQUE | C66: AROBASE | D66: BANDE | E66: ARTICHAUT | F66: BALAFON | G66: ANTENNE | H66: AUTOMATIQU | I66: ASTE | K66: BIEN | L66: ALUMINITE | M66: AUTORITAI | N66: ANATOMIE | O66: ARTISANAL | P66: ASSISES | Q66: BALLERINE | R66: BRUME | S66: BASTIDE | T66: ANSE
A67: ATEMI | B67: BRISE | C67: AROBE | D67: BAREME | E67: ARTISAN | F67: BALCON | G67: APIQUER | H67: AUTOUR | I67: ATHLETE | J67: ARCHIVE | K67: BIOLOGIQUE | L67: ALUMINIUM | M67: AUTORITE | N67: ANATOMIQUE | O67: ARTISANAT | P67: ASSUJETTI | Q67: BALLET | R67: BUFFET | S67: BASTION | T67: ANSPECT
A68: ATHLETE | B68: BRISEVENT | C68: ARROBASE | D68: BARRE | E68: ARTISANAT | F68: BALLERIN | G68: APOTRE | H68: AUTRUCHE | I68: ATTAQUE | J68: ARCHIVER | K68: BLASON | L68: ALUN | M68: AUTRICHE | N68: ANATOMISER | O68: ASSAINIR | P68: ASSURANCE | Q68: BARDE | R68: BUNGALOW | S68: BATI | T68: ANTENNE
A69: ATHLETIQUE | B69: BROUILLARD | C69: ARTICLE | D69: BASE | E69: ASPERGE | F69: BALLERINE | G69: APPARAUX | H69: AVIAIRE | I69: ATTAQUER | J69: ARCHIVES | K69: BONPERE | L69: ALUNITE | M69: AVISE | N69: ANATOMISTE | O69: ASSIETTE | P69: ASTREINTE | Q69: BATIMENT | R69: CABINE | S69: BATIERE | T69: APIQUER
A70: ATHLETISME | B70: BROUILLASS | C70: ASSIGNER | D70: BEZOUT | E70: ASPERGER | F70: BALLET | G70: APPAT | H70: AYE | I70: ATTENTAT | J70: ARMATURE | K70: BOURGEOISE | L70: AMALGAME | M70: BACHKIRIE | N70: ANEMIE | O70: ASSIGNAT | P70: ATTAQUER | Q70: BEAUXARTS | R70: CAFE | S70: BATIMENT | T70: APOTRE
A71: ATOUT | B71: BRUISSEME | C71: ASSISTANT | D71: BICARRE | E71: ASSOLEMENT | F71: BANDE | G71: AQUATIQUE | H71: BABOUIN | I71: AUTORITE | J71: ARMEE | K71: BRANCHES | L71: AMAZONITE | M71: BAGDAD | N71: ANESTHESIE | O71: ASSOCIE | P71: ATTEINTE | Q71: BIBLIOGRAP | R71: CALME | S71: BATISSE | T71: APPARAUX
A72: ATTAQUANT | B72: BRUIT | C72: ASTERISQUE | D72: BIEN | E72: ASSOLER | F72: BANDEDESSI | G72: ARCASSE | H72: BACTERIE | I72: AVANCER | J72: ARRANGER | K72: BRU | L72: AMBRE | M72: BAKOU | N72: ANESTHESIQ | O72: ASSOCIER | P72: ATTENTAT | Q72: BIOGRAPHE | R72: CAMPAGNE | S72: BAZAR | T72: APPAT
A73: ATTAQUE | B73: BRUME | C73: AUDIO | D73: BIJECTIF | E73: ATTACHER | F73: BAROQUE | G73: ARCHE | H73: BAIE | I73: AVIATEUR | J73: ARRET | K73: BUDGET | L73: AME | M73: BALKANS | N73: ANGINE | O73: ASSURANCE | P73: ATTESTER | Q73: BIOGRAPHIE | R73: CAMPER | S73: BEFFROI | T73: AQUATIQUE
A74: ATTELAGE | B74: BRUMEUX | C74: AUTOBIOGRA | D74: BIJECTION | E74: AUBERGINE | F74: BASSE | G74: ARCHIPEL | H74: BALEINE | I74: AVIATION | J74: ARRETE | K74: CADET | L74: AMERICIUM | M74: BALOURD | N74: ANGIOGRAPH | O74: ATELIER | P74: ATTRAIRE | Q74: BLASON | R74: CAMPEUR | S74: BERME | T74: ARCASSE
A75: ATTRAPE | B75: BULLETIN | C75: AUTOMATE | D75: BILINEAIRE | E75: AUNEAU | F75: BASSISTE | G75: ARCTIQUE | H75: BALOURD | I75: AVION | J75: ARRETS | K75: CADETTE | L75: AMETHYSTE | M75: BALTE | N75: ANIMAL | O75: ATTACHE | P75: AUDIENCE | Q75: BONSENS | R75: CAMPING | S75: BETON | T75: ARCHE
A76: ATTRAPER | B76: CADRAN | C76: AUTOMATION | D76: BILLION | E76: AUTHON | F76: BASSON | G76: ARCURE | H76: BALSA | I76: BAGAREUR | J76: ARTICLE | K76: CADRE | L76: AMIANTE | M76: BAMAKO | N76: ANIS | O76: ATTIRAIL | P76: AUDIT | Q76: BOUFFON | R76: CANOE | S76: BIDONVILLE | T76: ARCHIPEL
A77: AUTOMOBILE | B77: CALENDAIRE | C77: AVATAR | D77: BINAIRE | E77: AUXINE | F77: BATIMENT | G77: ARISER | H77: BANDICOOT | I77: BAGARRE | J77: ARTICULER | K77: CAPACITAT | L77: AMIDE | M77: BANGKOK | N77: ANNEAU | O77: ATTITRER | P77: AUTEUR | Q77: BOUFFONNER | R77: CANTINE | S77: BILLETTE | T77: ARCTIQUE
A78: AVENTURE | B78: CANICULE | C78: AVOIRENTET | D78: BINOME | E78: AVICULTURE | F78: BATTERIE | G78: ARMADA | H78: BARBARE | I78: BALISTIQUE | J78: ARTISANAT | K78: CARACTERE | L78: AMINE | M78: BANGLADESH | N78: ANNEXE | O78: ATTRITION | P78: AUTORISER | Q78: BOULEVARD | R78: CARAVANE | S78: BIOLOGIQUE | T78: ARCURE
... A87: BADMINTON | B87: CHRONO | C87: BETA | D87: BORNE | E87: BASILIC | F87: BEQUET | G87: ARTILLERIE | H87: BELUGA | I87: BATAILLEUR | J87: ATELIER | K87: CHAISE | L87: ANALYSE | M87: BENIN | N87: ANTIBIOTIQ | O87: AVIS | P87: BAILLI | Q87: CALLIGRAM | R87: CHAMANIQUE | S87: BORDURE | T87: ARRIMER
A88: BAL | C88: BIBELOT | D88: BORNEE | E88: BASSIN | F88: BERCEUSE | G88: ARTIMON | H88: BEOTIEN | I88: BATAILLON | J88: ATOME | K88: CHAMBRE | L88: ANALYTE | M88: BERLIN | N88: ANTICANCER | O88: AVOIR | P88: BAILLIAGE | Q88: CANTATE | R88: CHAMBRE | S88: BORNE | T88: ARSENAL
A89: BALANCOIRE | B89: CHRONOMETR | C89: BINAIRE | D89: BOUCLE | E89: BATTAGE | F89: BESTIAIRE | G89: ASPIRER | H89: BERGE | I89: BATION | J89: ATTACHE | K89: CHEFDEFAMI | L89: ANALYTIQUE | M89: BERNE | N89: ANTICOAGUL | O89: BADWILL | P89: BALANCE | Q89: CANTATRICE | R89: CHANGE | S89: BOULEVARD | T89: ARTILLERIE
A90: BALLE | B90: CHUTE | C90: BINETTE | D90: BOULE | E90: BECHE | F90: BIEN | G90: ASTROLABE | H90: BERNACLE | I90: BATTANT | J90: ATTRIBUTIO | K90: CHERIR | L90: ANATOMIE | M90: BERRY | N90: ANTICORPS | O90: BAIL | P90: BALANCER | Q90: CANZONE | R90: CHANGEMENT | S90: BOURG | T90: ARTIMON
A91: BALLON | B91: CIEL | C91: BIOGRAPHIE | D91: BOULIER | E91: BECHER | F91: BIGUINE | H91: BESOIN | I91: BATTRE | J91: AUDIENCE | K91: CHOYER | L91: ANDESINE | M91: BEYROUTH | N91: ANTIDEPRES | O91: BAISSE | P91: BANC | Q91: CAPTATIO | R91: CHANGER | S91: BOURGADE | T91: ASPIRER
A92: BANDE | B92: CINGLER | C92: BIOPUCE | D92: BOUT | E92: BERGER | F92: BIJOU | G92: ASTRONEF | H92: BESOINS | I92: BELLICISME | J92: AUDIT | K92: CIMETIERE | L92: ANDESITE | M92: BHOUTAN | N92: ANTIDOTE | O92: BALANCE | P92: BANQUEROUT | Q92: CARICATURE | R92: CHARMANT | S92: BOURGEOIS | T92: ASTROLABE
A93: BANQUE | B93: CIRCULATIO | C93: BIOS | D93: BRUTALITE | E93: BETAIL | F93: BISCUIT | G93: ASTRONOMIE | H93: BESTIAIRE | I93: BELLICISTE | J93: AUDITEUR | K93: CINEMA | L93: ANDROGYNE | M93: BICHKEK | N93: ANTIGENE | O93: BALANCIER | P93: BARRE | Q93: CASINO | R93: CHARTER | S93: BOURGMESTR
A94: BAQUET | B94: CIRRUS | C94: BIP | D94: BUDGETAIRE | E94: BETEL | F94: BISTRE | G94: ATLANTIQUE | H94: BESTIAL | I94: BELLIGERAN | J94: AUSTERITE | K94: CLAN | L94: ANGLE | M94: BILATERAL | N94: ANTIHISTAM | O94: BANCAIRE | P94: BARREAU | Q94: CELEBRE | R94: CHATEAU | S94: BOVIDUC | T94: ASTRONEF
A95: BARRE | B95: CISAILLEME | C95: BISTABLE | D95: CALCUL | E95: BETTERAVE | F95: BIWA | G95: ATTERRAGE | H95: BESTIALITE | I95: BELLIQUEUX | J95: AUTOCRATIE | K95: CLANIQUE | L95: ANHYDRIDE | M95: BIRMANIE | N95: ANTIPSYCHO | O95: BANCO | P95: BASOCHE | Q95: CELEBRITE | R95: CHEF | S95: BRANCHE | T95: ASTRONOMIE
A96: BASCULE | B96: CITERNE | C96: BIT | D96: CALCULER | E96: BIGAUT | F96: BLUES | G96: ATTERRIR | H96: BESTIOLE | I96: BERET | J96: AUTONOME | K96: COCON | L96: ANHYDRITE | M96: BISSAU | N96: ANTISEPTIQ | O96: BANQUE | P96: BATONNAT | Q96: CENACLE | R96: CHEMIN | S96: BRASSERIE | T96: ATLANTIQUE
A97: BASEBALL | B97: CLEMENT | C97: BLOC | D97: CALCULETTE | E97: BIGOT | F97: BOILEAU | G97: ATTERRISSA | H97: BETAIL | I97: BIDASSE | J97: AUTONOMIE | K97: COGNATION | L97: ANIMAL | M97: BLED | N97: ANTIVIRAL | O97: BANQUIER | P97: BAUX | Q97: CENSURE | R97: CHEMINEE | S97: BRECHE | T97: ATOLL
A98: BASKET | B98: CLEMENTE | C98: BLOCAGE | D98: CANONIQUE | E98: BINAGE | F98: BOIS | G98: ATTERRRIR | H98: BETE | I98: BIFLE | J98: AUTORISER | K98: COHESION | L98: ANIMALES | M98: BLOCUS | N98: ANTRE | O98: BARATTAGE | P98: BENEFICE | Q98: CENTON | R98: CHEQUE | S98: BRIQUE | T98: ATTERRAGE
A99: BASKETBALL | B99: CLEPSYDRE | C99: BLOG | D99: CANTOR | E99: BINAILLE | F99: BOLERO | G99: AUBE | H99: BICHE | I99: BIGOR | J99: AUTORITE | K99: COLLATERAL | L99: ANIMER | M99: BOGOTA | N99: ANUS | O99: BAREME | P99: BIEN | Q99: CESURE | R99: CHERCHEUR | S99: BRUIT | T99: ATTERRIR
A100: BASQUE | B100: CLIMAT | C100: BLOGUE | D100: CAPACITE | E100: BINE | F100: BOSSA | G100: AULNE | H100: BIODIVERSI | I100: BLESS | J100: AVENANT | K100: COMMUN | L100: ANION | M100: BOLIVIE | N100: ANXIETE | O100: BARON | P100: BIENFONDE | Q100: CHAMP | R100: CHIMERE | S100: CADASTRE | T100: ATTERRISSA
A101: BASTE | B101: CLIMATIQUE | C101: BLUETOOTH | D101: CARACTERIS | E101: BINER | F101: BOULEUR | G101: AURIQUE | H101: BIOLOGIE | I101: BLESSE | J101: AVIATION | K101: COMMUNAUTE | L101: ANNULAIRE | M101: BORD | N101: AORTE | O101: BAZAR | P101: BILLET | Q101: CHANSON | R101: CIEL | S101: CADRE | T101: ATTERRRIR
A102: BATAILLE | B102: CLIMATOLOG | C102: BOGUER | D102: CARDINAL | E102: BINETTE | F102: BOUM | G102: AUSSIERE | H102: BIOME | I102: BLESSER | J102: AVIS | K102: COMPARAISO | L102: ANTHRACITE | M102: BORDER | N102: APHASIE | O102: BCE | P102: BLAME | Q102: CHANT | R102: CIRCUIT | S102: CAFE | T102: AUBE
A103: BATIR | B103: COINCIDENC | C103: BOITE | D103: CARDIOIDE | E103: BINEUR | F103: BOURRES | G103: AVAL | H103: BIOSHERE | I103: BLEU | J103: AVOCAT | K103: COMPASSION | L103: ANTHROPOLO | M103: BORNAGE | N103: APONEVROSE | O103: BEAUTE | P103: BLANCHIR | Q103: CHAPITRE | R103: CITADELLE | S103: CALIDUC | T103: AULNE
A104: BATON | B104: COMPOSE | C104: BOITIER | D104: CARRE | E104: BIOCIDE | F104: BREAKCORE | G104: AVANT | H104: BIOSPHERE | I104: BLINDE | J104: BANCAIRE | K104: COMPOSE | L104: ANTIMOINE | M104: BOTSWANA | N104: APOPHYSE | O104: BENEFICE | P104: BON | Q104: CHEVALERES | R104: CLASSE | S104: CALME | T104: AURIQUE
A105: BATTANT | B105: COMPTEUR | C105: BOOSTER | D105: CARTESIEN | E105: BIOLOGIQUE | F105: BRIO | G105: AVARIE | H105: BIOTE | I105: BLOCUS | J105: BANQUE | K105: CONCORDANC | L105: APATITE | M105: BOURG | N105: APOTHICAIR | O105: BESANT | P105: BONTE | Q105: CHIASME | R105: CLIENTELE | S105: CAMARIN | T105: AUSSIERE
A106: BATTE | B106: CONCOMITAN | C106: BOOT | D106: CATEGORIE | E106: BIOMASSE | F106: BRONZE | G106: AVENTURE | H106: BIOTIQUE | I106: BOMBARDE | J106: BARREAU | K106: CONDOLEANC | L106: APLITE | M106: BOURGADE | N106: APPAREIL | O106: BESOIN | P106: BORDEREAU | Q106: CHIMERIQUE | R106: CLIMATIQUE | S106: CAMPANE | T106: AVAL
A107: BATTLE | C107: BORD | D107: CATENAIRE | E107: BIOTIQUE | F107: BRUIT | G107: AVIATEUR | H107: BIOTOPE | I107: BOMBARDEME | J107: BATI | K107: CONFIANCE | L107: APPARENCE | M107: BOURGEOIS | N107: APPELER | O107: BETAIL | P107: BOURREAU | Q107: CHOSE | R107: CLUB | S107: CAMPO | T107: AVANT
A108: BATTOIR | B108: CONDITION | C108: BORNE | D108: CAUCHY | E108: BIOTOPE | F108: BRUITISTE | G108: AVIATION | H108: BIPEDE | I108: BOMBARDER | J108: BATIR | K108: CONFLIT | L108: APPDIGEST | M108: BOYCOTT | N108: APPENDICE | O108: BIEN | P108: BREVET | Q108: CHRONIQUE | R108: COFFRE | S108: CAMPUS | T108: AVARIE
...

Sheet M4
A1: ALKAMO — M4
A2: N° | B2: THÈME | C2: MOTS
A3: 1 | B3: CONCEPT ET IDÉE | C3: =COUNTA(M4_mots!A3:A5000) -> 407
A4: 2 | B4: ÉMOTION | C4: =COUNTA(M4_mots!B3:B5000) -> 446
A5: 3 | B5: COULEUR | C5: =COUNTA(M4_mots!C3:C5000) -> 453
A6: 4 | B6: PHYSIQUE | C6: =COUNTA(M4_mots!D3:D5000) -> 671
A7: 5 | B7: CUISINE ET GASTRO | C7: =COUNTA(M4_mots!E3:E5000) -> 763
A8: 6 | B8: CORPS HUMAIN | C8: =COUNTA(M4_mots!F3:F5000) -> 929
A9: 7 | B9: CULTURE | C9: =COUNTA(M4_mots!G3:G5000) -> 297
A10: 8 | B10: ARCHÉOLOGIE | C10: =COUNTA(M4_mots!H3:H5000) -> 609
A11: 9 | B11: INSECTE ET REPTILE | C11: =COUNTA(M4_mots!I3:I5000) -> 547
A12: 10 | B12: HISTOIRE | C12: =COUNTA(M4_mots!J3:J5000) -> 456
A13: 11 | B13: LITTÉRATURE | C13: =COUNTA(M4_mots!K3:K5000) -> 649
A14: 12 | B14: CÉLÉBRITÉ | C14: =COUNTA(M4_mots!L3:L5000) -> 492
A15: 13 | B15: BRAVOURE | C15: =COUNTA(M4_mots!M3:M5000) -> 386
A16: 14 | B16: TECHNOLOGIE | C16: =COUNTA(M4_mots!N3:N5000) -> 1100
A17: 15 | B17: MÉTÉO ET CLIMAT | C17: =COUNTA(M4_mots!O3:O5000) -> 571
A18: 16 | B18: ARCHITECTURE | C18: =COUNTA(M4_mots!P3:P5000) -> 1512
A19: 17 | B19: DÉCORATION | C19: =COUNTA(M4_mots!Q3:Q5000) -> 585
A20: 18 | B20: MONTAGNE ET DÉSERT | C20: =COUNTA(M4_mots!R3:R5000) -> 503
A21: 19 | B21: POISSON ET MER | C21: =COUNTA(M4_mots!S3:S5000) -> 1266
A22: 20 | B22: MARKETING | C22: =COUNTA(M4_mots!T3:T5000) -> 205
A23: TOTAL | C23: =SUM(C3:C22) -> 12847

Sheet M4_mots
A1: CONCEPT ET IDÉE | B1: ÉMOTION | C1: COULEUR | D1: PHYSIQUE | E1: CUISINE ET GASTRO | F1: CORPS HUMAIN | G1: CULTURE | H1: ARCHÉOLOGIE | I1: INSECTE ET REPTILE | J1: HISTOIRE | K1: LITTÉRATURE | L1: CÉLÉBRITÉ | M1: BRAVOURE | N1: TECHNOLOGIE | O1: MÉTÉO ET CLIMAT | P1: ARCHITECTURE | Q1: DÉCORATION | R1: MONTAGNE ET DÉSERT | S1: POISSON ET MER | T1: MARKETING
A2: =COUNTA(A3:A5000) -> 407 | B2: =COUNTA(B3:B5000) -> 446 | C2: =COUNTA(C3:C5000) -> 453 | D2: =COUNTA(D3:D5000) -> 671 | E2: =COUNTA(E3:E5000) -> 763 | F2: =COUNTA(F3:F5000) -> 929 | G2: =COUNTA(G3:G5000) -> 297 | H2: =COUNTA(H3:H5000) -> 609 | ... T2: =COUNTA(T3:T5000) -> 205
A3: ABSTRAIT | B3: ABANDON | C3: ABONDANCE | D3: ABDOMEN | E3: ABAISSER | F3: ABCES | G3: ABBAYE | H3: ABAQUE | I3: ABDOMEN | J3: ABOLIR | K3: ABSTRACTIO | L3: ABONNES | M3: ABIME | N3: ABRASIF | O3: ABAT | P3: ABAQUE | Q3: ABATJOUR | R3: ABIME | S3: ABER | T3: ACCAPARER
A4: ABSTRAITE | B4: ABATTU | C4: ABRICOT | D4: ACOUSTIQUE | E4: ABATS | F4: ABDOMEN | G4: ABSTRAIT | H4: ABRI | I4: ABDOMINAL | J4: ABOLITION | K4: ABSTRAIT | L4: ACCLAMER | M4: ABNEGATION | N4: ABRASION | O4: ABIME | P4: ABAT | Q4: ACAJOU | R4: ABORDER | S4: ABIME | T4: ACCROCHE
A5: ACCEPTION | B5: ABSENCE | C5: ABSINTHE | D5: ACTIF | E5: ABONDANCE | F5: ABDOS | G5: ACADÉMIE | H5: ABSIDE | I5: ABEILLE | J5: ABREGE | K5: ACADEMICIE | L5: ACCOMPLI | M5: ACIER | N5: ABSORBEUR | O5: ABRI | P5: ABATTRE | Q5: ACCROCHE | R5: ABRI | S5: ABLE | T5: ACHAT
A6: ACCORD | B6: ABSURDE | C6: ACAJOU | D6: ACTION | E6: ABONDANT | F6: ABDUCT | G6: ACCORD | H6: ACANTHUS | I6: ABRAXAS | J6: ABROGATION | K6: ACADEMISME | L6: ACTEUR | M6: ACTIF | N6: ACCES | O6: ACCALMIE | P6: ABBAYE | Q6: ACCROCHER | R6: ABRITER | S6: ABLETTE | T6: ACHETEUR
A7: ACTE | B7: ACCABLÉ | C7: ACCORD | D7: ACTIVITE | E7: ABOUTI | F7: ABSORBER | G7: ADOPTION | H7: ACCES | I7: ACARIEN | J7: ACADEMIE | K7: ACCENT | L7: ACTIF | M7: ACTIVE | N7: ACCUMULER | O7: ACRE | P7: ABOUTIR | Q7: ACIER | R7: ABRUPT | S7: ABONDANCE | T7: ACQUÉRIR
A8: ACTUEL | B8: ACCEPTER | C8: ACIER | D8: ADROIT | E8: ABRICOT | F8: ACNE | G8: AFFINITÉ | H8: ACHEULIEN | I8: ACAROLOGIE | J8: ACCESSION | K8: ACCESSOIRE | L8: ACTRICE | M8: ADMIRABLE | N8: ACIDE | O8: ACTUEL | P8: ABREUVOIR | Q8: ADOUCIR | R8: ABYSSAL | S8: ABORD | T8: ACTIVITÉ
A9: ADAPTATION | B9: ADMIRER | C9: AGRESSIVE | D9: AFFINITE | E9: ABSINTHE | F9: ACUITE | G9: AGRUME | H9: ACIER | I9: ACRIDIEN | J9: ACIER | K9: ACROSTICHE | L9: ADHESION | M9: AFFRANCHIR | N9: ACIER | O9: AERIEN | P9: ABRI | Q9: AERIEN | R9: ACACIA | S9: ABORDAGE | T9: ADHÉRENT
A10: AFFIRMER | B10: ADORER | C10: AIGUE | D10: AGILE | E10: ACCOMPLI | F10: ADIPE | G10: AMBIANCE | H10: ACROPOLE | I10: ACROLOGIE | J10: ACROPOLE | K10: ACTE | L10: ADMIRABLE | M10: AFFRONTER | N10: ACTIF | O10: AGIR | P10: ABSIDE | Q10: AFFICHER | R10: ACACIAS | S10: ABORDER | T10: ADOPTION
A11: ALGEBRE | B11: AFFECT | C11: ALBATRE | D11: AGILITE | E11: ACCORD | F11: ADN | G11: APPORT | H11: ADOBE | I11: ACRONICTE | J11: ADHESION | K11: ACTEURS | L11: ADMIRATEUR | M11: AGILE | N11: ACTIVER | O11: AGITE | P11: ABSTRAIT | Q11: AGENCER | R11: ACCLIVE | S11: ABYME | T11: AFFAIRE
A12: ALLEGORIE | B12: AFFECTER | C12: ALERTE | D12: AIR | E12: ACCUEIL | F12: ADOLESCENT | G12: ARABLE | H12: AFFINAGE | I12: ADALIA | J12: AGORA | K12: ACTION | L12: ADMIRATION | M12: AGIR | N12: ADAPTATEUR | O12: AGREABLE | P12: ACAJOU | Q12: AGREMENTER | R12: ACIER | S12: ABYSSAL | T12: AFFICHAGE
A13: AMBITION | B13: AFFECTIF | C13: ALEZAN | D13: AIRE | E13: ACCUEILLI | F13: ADRENALINE | G13: ARCHIVES | H13: AFFOUILLER | I13: ADULTE | J13: AGREGATION | K13: ACTUALISME | L13: ADMIRER | M13: AGUERRI | N13: ADHERENCE | O13: AIR | P13: ACANTHUS | Q13: AJOURE | R13: ACRE | S13: ABYSSE | T13: AFFICHE
A14: ANALOGIE | B14: AFFLICTION | C14: AMARANTE | D14: ALBEDO | E14: ACETO | F14: ADRESSE | G14: ART | H14: AGGLOMERE | I14: AESHNE | J14: AGRESSION | K14: ACTUALITE | L14: ADORER | M14: AIDER | N14: AFFAIBLIR | O14: ALBEDO | P14: ACCES | Q14: AJUSTER | R14: ADDAX | S14: ACANTHURE | T14: AGENCE
... A26: ARGUMENTER | B26: AMERTUME | C26: ARDENT | D26: ANDROGYNE | E26: AIGRE | F26: ALCOOL | G26: BILDUNG | H26: AMMONITE | I26: AIGLE | J26: ANGE | K26: ALLEGORIQ | L26: ALIAS | M26: ARDEUR | N26: ALESAGE | O26: ANNEE | P26: ACTUEL | Q26: ANTIQUE | R26: ALPIN | S26: ACTIF | T26: ATTRACTIF
A27: ART | B27: AMITIÉ | C27: ARDEUR | D27: ANGLE | E27: AIGUILLAT | F27: ALERTE | G27: BLUES | H27: AMPHORE | I27: AIGUILLON | J27: ANIMATION | L27: ALLEGRESSE | M27: ARME | N27: ALESOIR | O27: ANTRE | P27: ADAMANTIN | Q27: APPLIQUE | R27: ALPINISME | S27: ACTINIE | T27: BAISSER
A28: ASPECT | B28: AMOUR | C28: ARDOISE | D28: ANIMAL | E28: AIL | F28: ALGIE | G28: BLÉ | H28: AMULETTE | I28: AILE | J28: ANNALE | K28: AMPHITHEAT | L28: ALLURE | M28: ARMEE | N28: ALGEBRE | O28: APEX | P28: ADAPTER | Q28: ARABESQUE | R28: ALPINISTE | S28: ACTIVE | T28: BONIMENT
A29: ASPIRER | B29: AMOUREUX | C29: ARGENT | D29: ANIMALES | E29: AILE | F29: ALITER | G29: BRÛLIS | H29: ANALYSER | I29: AIR | J29: ANNALES | K29: AMPOULE | L29: AMBITIEUX | M29: ARMURE | N29: ALGORITHME | O29: APRE | P29: ADENT | Q29: ARCADE | R29: ALTIPLANO | S29: ACUL | T29: BOUTIQUE
A30: ASSIMILE | B30: AMYGDALE | C30: ARGENTE | D30: ANIMER | E30: AIOLI | F30: ALLERGIE | G30: BÉTAIL | H30: ANCRAGE | I30: ALGUE | J30: ANNEXION | K30: ANALEPSE | L30: AMBITION | M30: ARTILLERIE | N30: ALIGNEMENT | O30: AQUA | P30: ADEQUATION | Q30: ARDOISE | R30: ALTITUDE | S30: ADENT | T30: BRANCHE
A31: ATYPIQUE | B31: AMÉNITÉ | C31: ARGENTER | D31: ANNULAIRE | E31: AIR | F31: ALLURE | G31: CABARET | H31: ANNEAU | I31: ALLIGATOR | J31: ANTIQUE | K31: ANAPHORE | L31: AMI | M31: ASSAUT | N31: ALIGNER | O31: AQUEUX | P31: ADOBE | Q31: ARETE | R31: AMAS | S31: ADHERENCE | T31: BROCHURE
A32: AXIOME | B32: ANGOISSE | C32: ARGENTIN | E32: AIRELLE | F32: ALVEOLE | G32: CAFÉIER | H32: ANTIQUE | I32: ALLOPHES | J32: ANTIQUITE | K32: ANGELISME | L32: AMOUR | M32: ASSURANCE | N32: ALIMENTER | O32: ARBRE | P32: ADOSSEMENT | Q32: ARGENT | R32: ANCRE | S32: ADJOINT | T32: BRUT
A33: BASE | B33: ANTIPATHIE | C33: ART | D33: APPARENCE | E33: AJOUTER | F33: AMAIGRIRE | G33: CAMPAGNE | H33: ANTIQUITE | I33: ALVEOLE | J33: APOCRYPHE | K33: ANONYME | L33: ANIMATEUR | M33: ATTAQUE | N33: ALLIAGE | O33: ARC | P33: ADRESSE | Q33: ARGILE | R33: ANGLE | S33: ADOS | T33: BULLETIN
A34: BEAU | B34: ANXIEUX | C34: ARTIFICIEL | D34: APPDIGEST | E34: ALGUE | F34: AMBITION | G34: CAPITAL | H34: AQUEDUC | I34: ALYTE | J34: ARBITRAGE | K34: ANTHOLOGIE | L34: ANIMATION | M34: AUBE | N34: ALLOCATION | O34: ARCEN | P34: AFFLEUR | Q34: ARMATURE | R34: ARBRE | S34: ADRET | T34: CADEAU
A35: BIAIS | B35: ANXIÉTÉ | C35: ARTISTE | D35: APPOINT | E35: ALLIAGE | F35: AME | G35: CARNAVAL | H35: ARASE | I35: AMPEDUS | J35: ARC | K35: ANTITHESE | L35: ANNONCE | M35: AUDACE | N35: ALLONGE | O35: ARCHIPEL | P35: AFFLEURER | Q35: ARMOIRE | R35: ARCHE | S35: AFALE | T35: CAMPAGNE
A36: BIEN | B36: APAISER | C36: ASSORTIR | D36: APTE | E36: ALLIE | F36: AMYGDALE | G36: CENSURE | H36: ARASER | I36: AMPHIBIEN | J36: ARCHAISME | K36: APARTES | L36: ANONYMAT | M36: AUDACIEUX | N36: ALLUMER | O36: ARCTIQUE | P36: AGATE | Q36: ASSEMBLER | R36: ARDEUR | S36: AFFALER | T36: CASSER
A37: BIOLOGIE | B37: APAISÉ | C37: AUBERGINE | D37: APTITUDE | E37: ALOSE | F37: ANALYSE | G37: CERCLE | H37: ARCADE | I37: AMPHIBOL | J37: ARCHIVE | K37: APHORISME | L37: APOGEE | M37: AVANCEE | N37: AMORCER | O37: ARENE | P37: AGENCEMENT | Q37: ASSISE | R37: ARDOISE | S37: AFFE | T37: CATALOGUE
A38: BIOLOGIQUE | B38: APATHIE | C38: AUDACE | E38: AMANDE | F38: ANEMIE | G38: CHAMP | H38: ARCHE | I38: ANACONDA | J38: ARCHIVER | K38: APOLOGUE | L38: APPARAT | M38: AVANCER | N38: AMPLIFIER | O38: ARGENT | P38: AGENCER | Q38: ASSORTIR | R38: ARENE | S38: AFFET | T38: CHAMPION
A39: BLAME | B39: APEURÉ | C39: AURORE | D39: ARISTOTE | E39: AMER | F39: ANGINE | G39: CHANSON | H39: ARCHIVE | I39: ANAX | J39: ARCHIVES | K39: APOSTROPHE | L39: APPARENCE | M39: BADGE | N39: AMPOULE | O39: ARGILE | P39: AGENT | Q39: ATRIUM | R39: ARETE | S39: AFFIN | T39: CHOQUANT
A40: BONHEUR | B40: APITOYER | C40: AVIVER | D40: ASPECT | E40: AMPLEUR | F40: ANGOISSE | G40: CHANVRE | H40: ARCHIVER | I40: ANDRENE | J40: ARGENT | K40: APPRETE | L40: APPLAUDI | M40: BAIONNETTE | N40: ANALOGIQUE | O40: ARIDE | P40: AGGLOMERE | Q40: ATTIRER | R40: ARGILE | S40: AFFOURCHER | T40: CIBLAGE
A41: BUT | B41: APPÉTIT | C41: AZUR | D41: ASTHENIE | E41: AMUSE | F41: ANOSMIE | G41: CHEF | H41: ARDOISE | I41: ANGUIS | J41: ARMEE | K41: ARABE | L41: APPLAUDIR | M41: BASTION | N41: ANALYSE | O41: ARIDITE | P41: AGGLOMERER | Q41: ATTRAIT | R41: ARIDE | S41: AFFRET | T41: CIBLE
A42: CADRE | B42: ARDENT | C42: AZURE | E42: ANCHOIS | F42: ANUS | G42: CHÂTEAU | H42: ARENE | I42: ANIMAL | J42: ARMISTICE | K42: ARGUMENT | L42: APPRECIER | M42: BATAILLE | N42: ANALYSER | O42: ARME | P42: AGILE | Q42: AUVENT | R42: AROLE | S42: AFFRETEUR | T42: CIBLER
A43: CAS | B43: ARDEUR | C43: AZUREE | D43: ATHLETE | E43: ANDOUILLE | F43: AORTE | G43: CINÉMA | H43: ARGENT | I43: ANISOPLIE | J43: ART | K43: ARIA | L43: APPUI | M43: BATAILLON | N43: ANCRAGE | O43: ARRET | P43: AGORA | Q43: AZUR | R43: ASPERITE | S43: AFFUT | T43: CLIENT
A44: CATEGORIE | B44: ARTISTE | C44: BASALTE | D44: ATOME | E44: ANETH | F44: APEX | G44: CIRQUE | H44: ARGILE | I44: ANNEAU | J44: ARTICLE | K44: ARRANGE | L44: APPUYER | M44: BIVOUAC | N44: ANCRER | O44: ARROSER | P44: AGRAFAGE | Q44: BADIGEON | R44: ASPRE | S44: AGENCE | T44: CLIENTÈLE
A45: CAUSALITE | B45: ASPIRER | C45: BEIGE | D45: ATOMIQUE | E45: ANGULE | F45: APHASIE | G45: CIVILISÉ | H45: ARKOSE | I45: ANOPHELE | J45: ARTISTIQUE | K45: ART | L45: ARDEUR | M45: BOMBE | N45: ANGLE | O45: ASPRE | P45: AGRAFE | Q45: BAGUETTE | R45: ATTEINDRE | S45: AGENT | T45: CLIGNOTER
A46: CAUSE | B46: ATARAXIE | C46: BICOLORE | D46: ATOMISME | E46: ANIS | F46: APNEE | G46: CIVISME | H46: ARME | I46: ANTENNE | J46: ASCENSION | K46: ARTHURIEN | L46: ARGENT | M46: BONTE | N46: ANGULAIRE | O46: ASTRE | P46: AGRAFFAGE | Q46: BAHUT | R46: AVALANCHE | S46: AGITE | T46: CLIP
A47: CERNER | B47: ATTITUDE | C47: BICROMATE | E47: APERITIF | F47: APPENDICE | G47: CLEF | H47: ARMER | I47: AOUTAT | J47: ASSASSINAT | K47: ARTIFICIE | L47: ARROGANCE | M47: BOUCLIER | N47: ANNOTATION | O47: ATMOSPHERE | P47: AGRANDIR | Q47: BALCON | R47: AVANCER | S47: AGITEE | T47: COMMERCE
A48: CERTITUDE | B48: ATTRISTÉ | C48: BISTRE | D48: AUTORITE | E48: APOGEE | F48: ARCEAU | G48: CLIMAT | H48: ARSENIC | I48: APAMEE | J48: ASSEMBLEE | K48: ARTISTE | L48: ARTICLE | M48: BRASIER | N48: ANNULER | O48: AUBE | P48: AGREE | Q48: BALDAQUIN | R48: AVENTURE | S48: AGREMENT | T48: COMMERCER
A49: CHAMP | B49: AVARICE | C49: BITUME | D49: BACON | E49: APPETIT | F49: ARCHE | G49: CODE | H49: ARTEFACT | I49: APATURA | J49: AURELE | K49: ARTISTIQUE | L49: ARTISTE | M49: BRAVADE | N49: ANODE | O49: AURORE | P49: AIGUILLE | Q49: BAMBOU | R49: BARCANE | S49: AGRES | T49: COÛT
A50: CHIMIE | B50: AVERSION | C50: BLANC | D50: BALEZE | E50: APPRECIER | F50: ARCHET | G50: COHÉSION | H50: ARTISAN | I50: APHELIE | J50: AUTEUR | K50: ASPECT | L50: ASCENSION | M50: BRAVE | N50: ANTENNE | O50: AUSTRAL | P50: AILE | Q50: BANDE | R50: BARRE | S50: AGUER | T50: CRÉATIF
A51: CHOIX | B51: AVIDITÉ | C51: BLANCHIR | D51: BARAQUE | E51: ARACHIDE | F51: ARDEUR | G51: COLON | H51: ASSEMBLAGE | I51: APHODIUS | J51: AUTORITE | K51: ASSONANCE | L51: ATOUT | M51: BRAVER | N51: ANTIVIRUS | O51: AUTOMNE | P51: AILERON | Q51: BANDEAU | R51: BASALTE | S51: AHURI | T51: CRÉER
A52: CHOSE | B52: BIEN | C52: BLEU | D52: BARYCENTRE | E52: ARACK | F52: AREOLE | G52: COLONIE | H52: ASSEMBLER | I52: APHROPHOR | J52: AVENTURE | K52: ATTENTAT | L52: ATTAQUE | M52: BRAVOURE | N52: APERCU | O52: AVAL | P52: AIR | Q52: BANDEAUX | R52: BEAU | S52: AHURT | T52: CRÉNEAU
A53: CLAIR | B53: BIENÊTRE | C53: BLEUET | D53: BARYON | E53: ARMAGNAC | F53: ARN | G53: COMÉDIE | H53: ATELIER | I53: APODERUS | J53: AZTEQUE | K53: ATTRIBUER | L53: ATTIRER | M53: BUT | N53: APPAREIL | O53: AVALANCHE | P53: AIRE | Q53: BANQUETTE | R53: BEDOUIN | S53: AIGLEFIN | T53: DESIGN
A54: CLARTE | B54: BLASER | C54: BLEUIR | D54: BAVARD | E54: AROMATES | F54: ARTERE | G54: CONCEPT | H54: ATTACHE | I54: APTERE | J54: AZTEQUES | K54: AUBE | L54: ATTRACTION | M54: CALME | N54: APPEL | O54: AVERSE | P54: AJOUR | Q54: BARIOLE | R54: BERGE | S54: AIGUE | T54: DESIGNER
A55: CLASSE | B55: BLESSANT | C55: BLEUIT | D55: BEAU | E55: AROME | F55: ASPECT | G55: CONCERTO | H55: AUTEL | I55: AQUATIQUE | J55: BANNIR | K55: AUTEUR | L55: ATTRAIT | M55: CAMP | N55: APPELER | O55: AVERSES | P55: AJOURAGE | Q55: BARIOLER | R55: BERME | S55: AIGUILLAT | T55: DEVISE
A56: CLOS | B56: BLESSÉ | C56: BONHEUR | D56: BICEPS | E56: ARTICHAUT | F56: ASTHME | G56: CONTE | H56: BAGUE | I56: ARACHNIDE | J56: BARBARES | K56: AUTEURE | L56: AUDACE | M56: CANON | N56: APPLIQUER | O56: AVERSEUX | P56: AJOURE | Q56: BAROQUE | R56: BISE | S56: AILE | T56: DIPLÔME
A57: CODE | B57: BONHEUR | C57: BORDEAUX | E57: ARTISANAL | F57: ATAXIE | G57: CORTÈGE | H57: BAGUETTE | I57: ARAIGNEE | J57: BATAILLE | K57: AUTOBIOGRA | L57: AUDIENCE | M57: CAPITAINE | N57: APPUYER | O57: AZIMUT | P57: AJOURER | Q57: BASALTE | R57: BIVOUAC | S57: AILERON | T57: DISCOURS
A58: COGNITION | B58: BONTÉ | C58: BRILLANCE | D58: BIOLOGIE | E58: ASPERGE | F58: ATONIE | G58: COSTUME | H58: BANDE | I58: ARBRE | J58: BATIMENT | K58: AUTOFICTIO | L58: AUDITEUR | M58: CASERNE | N58: ARBRE | O58: AZUR | P58: AJUSTER | Q58: BASE | R58: BIVOUAQUER | S58: AILIER | T58: DONNÉE
A59: COMMUN | B59: BOUGON | C59: BRILLANT | D59: BIOLOGIQUE | E59: ASPIC | F59: ATROPH | G59: COUTUME | H59: BARRAGE | I59: ARGILE | J59: BIBLE | K59: AUTOGRAPHE | L59: AURA | M59: CASQUE | N59: ARCHIVE | O59: BAIE | P59: ALABASTRE | Q59: BATIR | R59: BLIZZARD | S59: AIMANT | T59: DÉBOUCHÉ
A60: COMPLEMENT | B60: BOULEVERSÉ | C60: BRILLER | E60: ASSEMBLEE | F60: ATROPHIE | G60: CRISE | H60: BARREAUX | I60: ARGIOPE | J60: BIBLIQUE | K60: AUTRICE | L60: AUTEUR | M60: CAUSE | N60: ARCHIVER | O60: BAIN | P60: ALAISE | Q60: BATISTE | R60: BLOC | S60: AINEE | T60: DÉCIDER
A61: COMPRENDRE | B61: BRISER | C61: BRIQUE | D61: BITUME | E61: ASSEMBLER | F61: ATTELLE | G61: CRITIQUE | H61: BASALTE | I61: ARGUS | J61: BIFACE | K61: AVANTSCENE | L61: AUTOGRAPHE | M61: CAVALERIE | N61: ARGENT | O61: BAISSER | P61: ALANDIER | Q61: BEAU | R61: BOIRE | S61: AIRE | T61: DÉCISION
A62: CONCEPT | B62: BROUILLE | C62: BRONZE | D62: BOHR | E62: ASSIETTE | F62: ATTENTION | G62: CROQUIS | H62: BASILIQUE | I62: ARGYRIS | J62: BIOGRAPHIE | K62: AVENTURE | L62: AVATAR | M62: CERTITUDE | N62: ARGUMENT | O62: BALLON | P62: ALBATRE | Q62: BEIGE | R62: BOISE | S62: AITE | T62: DÉFAUT
A63: CONCEPTION | B63: BRÛLANT | C63: BRUN | D63: BOSON | E63: ATTIRER | F63: ATTITUDE | G63: CROYANCE | H63: BASSIN | I63: AROMIE | J63: BLOCUS | K63: BAL | L63: BADGE | M63: CHALLENGE | N63: ARMATURE | O63: BANC | P63: ALCAZAR | Q63: BETON | R63: BONDIR | S63: AJOUR | T63: DÉPENSER
A64: CONCEPTUEL | B64: BRÛLER | C64: BRUNIR | D64: BOUCHE | E64: ATTRAIT | F64: ATTRAPER | G64: CRÉATION | H64: BASTIDE | I64: ARTHROPODE | J64: BOIS | K64: BALLADE | L64: BANDE | M64: CHAMP | N64: ARRACHAGE | O64: BANQUISE | P64: ALCOVE | Q64: BIBELOT | R64: BORD | S64: AJURE | T64: DÉPLIANT
A65: CONCEVOIR | B65: BÉAT | C65: BRUYERE | D65: BRAS | E65: AUBERGINE | F65: AUDACE | G65: CUBISME | H65: BASTION | I65: ASILE | J65: BOUCLIER | K65: BALLE | L65: BAROMETRE | M65: CHAMPION | N65: ARRET | O65: BAROMETRE | P65: ALDOSE | Q65: BISEAU | R65: BOSSE | S65: AJUT | T65: EMBALLER
A66: CONCRET | B66: BÉGUIN | C66: CACAO | D66: BRILLER | E66: AVOCAT | F66: AVALER | G66: CUISINE | H66: BECHE | I66: ASPIC | J66: BOUDDHISME | K66: BALLERINE | L66: BEAU | M66: CHARGE | N66: ARRETER | O66: BARQUE | P66: ALEE | Q66: BLANCHIR | R66: BOUEUX | S66: AKENE | T66: EMBLÈME
A67: CONCRETE | B67: CAFARD | C67: CAFE | D67: BRUIT | E67: BABA | F67: AVANT | G67: CULTIVER | H67: BEFFROI | I67: ASPILATE | J67: BREVET | K67: BALLET | L67: BEAUTE | M67: CHARGER | N67: ASCENDANT | O67: BASSE | P67: ALESE | Q67: BOIS | R67: BOUQUETIN | S67: ALBACORE | T67: EMPLETTE
A68: CONNAITRE | B68: CALME | C68: CALME | D68: BRUTAL | E68: BADIANE | F68: AVANTBRAS | G68: CULTIVÉ | H68: BERME | I68: ATLAS | J68: BRIBE | K68: BARDE | L68: BIJOU | M68: CHATEAU | N68: ASPECT | O68: BASSIN | P68: ALGEBRE | Q68: BORDEAUX | R68: BRECHE | S68: ALBATROS | T68: ENCART
A69: CONNEXION | B69: CALMER | C69: CANARI | D69: BUSTE | E69: BAGUETTE | F69: AXONE | G69: CULTUEL | H69: BIFACE | I69: ATTAQUE | J69: BRIQUE | K69: BATIMENT | L69: BILAN | M69: CHEVALIER | N69: ASPIRATION | O69: BATON | P69: ALGUE | Q69: BORDURE | R69: BRILLER | S69: ALBER | T69: ENQUÊTE
A70: CONSCIENCE | B70: CAPRICE | C70: CANDEUR | D70: CADAVRE | E70: BAKLAVA | F70: BACTERIE | G70: CULTURE | H70: BIJOU | I70: ATTELABUS | J70: BRONZE | K70: BEAUXARTS | L70: BIOGRAPHIE | M70: CIBLE | N70: ASSEMBLAGE | O70: BAUGE | P70: ALIGNE | Q70: BOSSE | R70: BROUILLARD | S70: ALBURNE | T70: ENSEIGNE
A71: CONSENSUS | B71: CAPTIVER | C71: CANNELLE | D71: CALME | E71: BALLOTINE | F71: BAISER | G71: CULTUREL | H71: BIJOUTIER | I71: ATTIS | J71: BULLE | K71: BIBLIOGRAP | L71: BLOGGER | M71: CIME | N71: ASSEMBLER | O71: BERGE | P71: ALIGNEMENT | Q71: BOUGEOIR | R71: BRULANT | S71: ALCEE | T71: ENTREPÔT
A72: CONTENU | B72: CERVEAU | C72: CARAMEL | D72: CAPABLE | E72: BALSAMIQUE | F72: BANDAGE | G72: CÉRÉALE | H72: BISEAU | I72: ATYCHIE | J72: CAFE | K72: BIOGRAPHE | L72: BON | M72: CITADELLE | N72: ASSURER | O72: BETON | P72: ALIGNER | Q72: BOUGIE | R72: BRULER | S72: ALCYON | T72: EXPOSER
... A110: DOCTRINE | B110: DRAME | C110: CONTRASTE | D110: CONCRET | E110: BUFFET | F110: CABINET | G110: FRUIT | H110: CERAMIQUE | I110: CANAL | J110: COMMANDE | K110: CINEASTE | L110: CLASH | M110: DEFI | N110: BRIDES | O110: CELESTE | P110: ANTIQUE | Q110: CERISIER | R110: CONTEMPLER | S110: ALOUR | T110: MARCHAND
A111: DOGME | B111: DÉCHAÎNÉ | C111: CONTRASTER | E111: BUTTERNUT | F111: CALCIUM | G111: FUMIER | H111: CERCLAGE | I111: CANOPEE | J111: COMMERCE | K111: CITATION | L111: CLASSE | M111: DEFIER | N111: BROCHE | O111: CHALEUR | P111: ANTIS | Q111: CHAISE | R111: CONTOUR | S111: ALPAX | T111: MARCHANDER
A112: DOMAINE | B112: DÉDAIN | C112: CORAIL | D112: CONDITION | E112: CABARET | F112: CALLUS | G112: FÊTE | H112: CHAPELLE | I112: CAPRICORNE | J112: COMMUNE | L112: CLASSIQUE | M112: DELIVRER | N112: BROYEUR | O112: CHAMP | P112: APERCU | Q112: CHALEUR | R112: CONTOURNER | S112: ALPIN | T112: MARCHÉ
A113: DONNE | B113: DÉGOÛT | C113: CORAL | D113: CONSISTANC | E113: CABILLAUD | F113: CALME | G113: GALERIE | H113: CHARBON | I113: CARABE | J113: COMPARER | L113: CLICHE | M113: DEPASSER | N113: BRUIT | O113: CHANGEANT | P113: APERTURE | Q113: CHANDELIER | R113: CORDE | S113: ALQUER | T113: MARCHÉAGE
A114: DONNEE | B114: DÉLICE | C114: COURAGE | D114: CONSISTANT | E114: CACAHUETE | F114: CAMBRURE | G114: GAMME | H114: CHATEAU | I114: CARAPACE | J114: COMPLOT | K114: CLASSIQUE | L114: CLUB | M114: DEROBADE | N114: BRULER | O114: CHANGEMENT | P114: APLANIR | Q114: CHANDELLE | R114: CORDEE | S114: ALSE | T114: MARKETING
A115: DOUTE | B115: DÉLIRE | C115: CRAIE | D115: CONTINU | E115: CACAO | F115: CANCER | G115: GLOBAL | H115: CHAUX | I115: CARNIVORE | J115: CONCORDAT | K115: CLERIHEW | L115: COACH | M115: DETERMINE | N115: BUREAU | O115: CHANGER | P115: APLAT | Q115: CHANGER | R115: CORNE | S115: ALTER | T115: MARQUAGE
A116: DROIT | B116: DÉPRESSION | C116: CRAMOISI | D116: CORPOREL | E116: CADEAU | F116: CAPILLAIRE | G116: GOTHIQUE | H116: CHEVET | I116: CASCADE | J116: CONFLIT | K116: CLIMAX | L116: COCKTAIL | M116: DEVOIR | N116: BUS | O116: CHAOS | P116: APLATI | Q116: CHARME | R116: CORNICE | S116: ALTITUDE | T116: MARQUE
A117: DUALITE | B117: DÉPRIME | C117: CRAYON | D117: CORPS | E117: CAILLE | F117: CAPSULE | G117: GOUACHE | H117: CHUTTE | I117: CELLULE | J117: CONQUERIR | K117: CODA | L117: CODE | M117: DEVOUE | N117: BUTEE | O117: CHARME | P117: APLOMB | Q117: CHARPENTE | R117: CORNICHE | S117: AMAGO | T117: MERCATIQUE
A118: DUREE | B118: DÉRANGER | C118: CREATIF | D118: CORPULENT | E118: CALER | F118: CARACTERE | G118: GOÛT | H118: CIMENTER | I118: CERAMBYX | J118: CONQUETE | K118: COLLABORAT | L118: COIFFURE | M118: DEVOUEMENT | N118: CABLE | O118: CHAUD | P118: APOPHYSE | Q118: CHAUX | R118: COTEAU | S118: AMANT | T118: MESSAGE
A119: EBAUCHE | B119: DÉSARROI | C119: CREATIVE | D119: COSMOLOGIE | E119: CALMAR | F119: CARBONE | G119: GRAVURE | H119: CIMETIERE | I119: CERQUE | J119: CONSULAT | K119: COMEDIE | L119: COLLECTIF | M119: DIAMANT | N119: CABLER | O119: CHAUFFER | P119: APPENTIS | Q119: CHENE | R119: COUDE | S119: AMARINER | T119: MODE
A120: ECART | B120: DÉSEMPARÉ | C120: CREATIVITE | D120: COSTAUD | E120: CALVADOS | F120: CARESSE | G120: HARICOT | H120: CIPPE | I120: CETOINE | J120: CONTE | K120: COMEDIEN | L120: COMEDIE | M120: DIGNITE | N120: CACHE | O120: CHENE | P120: APPLIQUE | Q120: CHENEAU | R120: COULOIR | S120: AMARRAGE | T120: MONOPOLE
A121: ECHANGE | B121: DÉSESPOIR | C121: CREME | D121: COU | E121: CANAPE | F121: CAROTIDE | G121: HARMONIE | H121: CIRE | I121: CHALEUR | J121: CONTER | K121: COMEDIENNE | L121: COMEDIEN | M121: DIRIGER | N121: CALCUL | O121: CHINOOOK | P121: APPOINTER | Q121: CHENILLE | R121: COURAGE | S121: AMARRE | T121: MONTRER
A122: ECONOMIE | B122: DÉSESPÉRÉ | C122: CRIARD | D122: COUCHE | E122: CANARD | F122: CARPE | G122: HECTARE | H122: CIRQUE | I122: CHAMPIGNON | J122: CONTEUR | K122: COMIQUE | L122: COMPETENCE | M122: DISCIPLINE | N122: CALCULER | O122: CIEL | P122: APPRETER | Q122: CHEVET | R122: COURIR | S122: AMARRER | T122: NOTORIÉTÉ
A123: ECONOMIQUE | B123: DÉSIR | C123: CUIR | D123: COUDE | E123: CANELE | F123: CARRURE | G123: HISTOIRE | H123: CISEAU | I123: CHARANCON | J123: CONTEXTE | K123: COMMENTAIR | L123: CONCERT | M123: DONJON | N123: CALIBRAGE | O123: CIME | P123: APPUI | Q123: CHEVILLE | R123: COURSE | S123: AMAURE | T123: NOVATEUR
A124: ECRITURE | B124: DÉSIRER | C124: CUIVRE | D124: COULEUR | E124: CANNELER | F124: CARTILAGE | G124: HORIZON | H124: CISTE | I124: CHASSE | J124: CONTRE | K124: COMMENTATE | L124: CONFIANCE | M124: DONNER | N124: CALIBRER | O124: CIRRUS | P124: APPUIS | Q124: CHOISIR | R124: COUVERT | S124: AMBAS | T124: NÉGOCIANT
A125: EFFET | B125: DÉSOLÉ | C125: CYAN | D125: COUP | E125: CANNELLE | F125: CATARR | G125: HUMAIN | H125: CITADELLE | I125: CHASSER | J125: CORVEE | K125: COMPAGNIE | L125: CONFIRM | M125: DROIT | N125: CALORIE | O125: CLAIR | P125: APPUYER | Q125: CHROME | R125: CRAMPON | S125: AMBLE | T125: NÉGOCIER
... A177: GUIDE | B177: FÉLICITÉ | C177: FAUVE | D177: DRILLE | E177: COMBLE | F177: CONTUSION | G177: MÉMOIRES | H177: DECAPAGE | I177: CROTALE | J177: EFFRAYANT | K177: DRAMATURGE | L177: DYNAMIQUE | M177: FORT | N177: COMPTEUR | O177: DETROIT | P177: ARQUEE | Q177: CUBE | R177: ETAPE | S177: ANGOR | T177: SLOGAN
A178: HISTOIRE | B178: GAIETÉ | C178: FERTILITE | D178: DRU | E178: COMBLER | F178: CONVAL | G178: MÛRIER | H178: DECAPER | I178: CRUSTACE | J178: EGYPTE | L178: ECLAT | M178: FORTERESSE | N178: CONCEVOIR | O178: DIOXYDE | P178: ARQUER | Q178: CUIR | R178: ETENDUE | S178: ANGUILLE | T178: SOLDER
A179: HUMAIN | B179: GLACIAL | C179: FERVEUR | D179: DUALISME | E179: COMMANDE | F179: CORDON | G179: MŒURS | H179: DECAPITER | I179: CUIRASSE | J179: EMOUVANTE | K179: DRAME | L179: ECRAN | M179: FOUGUE | N179: CONDUCTEUR | O179: DIVERSITE | P179: ARRASEMENT | Q179: CUIVRE | R179: ETOILE | S179: ANGULAS | T179: SONDER
A180: HYPOTHESE | B180: GORGE | C180: FEUILLE | D180: DUNETTE | E180: COMPOTE | F180: CORNEE | G180: NATION | H180: DECLASSER | I180: CULEX | J180: EMPIRE | K180: DYSTOPIE | L180: ECRIRE | M180: FRANCHIR | N180: CONDUITE | O180: DOME | P180: ARRET | Q180: CUVE | R180: ETROIT | S180: ANIBE | T180: SPONSOR
A181: IDEAL | B181: GRATITUDE | C181: FIDELITE | D181: DUR | E181: COMPOTEE | F181: CORPS | G181: NATURE | H181: DECOUVERTE | I181: CURCULION | J181: ENCRE | K181: EAU | L181: ECRIVAIN | M181: FRATERNITE | N181: CONE | O181: DONNEE | P181: ARRETE | Q181: CYLINDRE | R181: EUPHORBE | S181: ANIMAL | T181: SPOT
A182: IDEALISME | B182: GRAVITÉ | C182: FILE | D182: DUREE | E182: COMTE | F182: CORTEX | G182: NORME | H182: DECOUVRIR | I182: CUTICULE | J182: ENDURER | K182: ECOLE | L182: EFFACEMENT | M182: FROID | N182: CONNECTER | O182: DOSE | P182: ARRONDI | Q182: DALLAGE | R182: EXPLORER | S182: ANIME | T182: STAND
A183: IDEE | B183: GRISERIE | C183: FLAMANT | D183: DYNAMIQUE | E183: CONCASSER | F183: COTE | G183: NOTE | H183: DECRIRE | I183: DALLE | J183: ENTENDUES | K183: ECRIRE | L183: EFFORT | M183: FRONT | N183: CONNEXION | O183: DOUCE | P183: ARRONDIR | Q183: DALLE | R183: EXPOSE | S183: ANIMELLE | T183: STRATÉGIE
A184: IDEEL | B184: GROGNON | C184: FLAMBER | D184: EAU | E184: CONDIMENT | F184: COTON | G184: NOUVELLE | H184: DEFUNT | I184: DAMIER | J184: EPIQUE | K184: ECRIT | L184: EGERIE | M184: FUSIL | N184: CONSOLE | O184: DOUCEUR | P184: ARSENAUX | Q184: DAMAS | R184: FAILLE | S184: ANION | T184: STYLE
A185: IDENTITE | B185: GRÂCE | C185: FLUO | D185: ECART | E185: CONFIRE | F185: COTYLO | G185: OCTAVE | H185: DEGAGER | I185: DANGER | J185: EPISODE | K185: ECRITE | L185: ELECTORAT | M185: GAGEURE | N185: CONTACT | O185: DOUX | P185: ART | Q185: DAMIER | R185: FAITE | S185: ANISE | T185: SUCCÈS
A186: IDEOLOGIE | B186: GUÉRIR | C186: FONCE | D186: ECHANTILLO | E186: CONFISERIE | F186: COU | G186: OPÉRA | H186: DENUDER | I186: DARD | J186: EPITOME | K186: ECRITS | L186: ELEGANCE | M186: GALVANISER | N186: CONTROLEUR | O186: DRACHE | P186: ARTICULER | Q186: DECOR | R186: FALAISE | S186: ANISETTE | T186: SYMBOLE
A187: IMAGE | B187: GUÉRISON | C187: FONCER | D187: ECHELLE | E187: CONFIT | F187: COUDE | G187: ORAL | H187: DEPOSER | I187: DECTIQUE | J187: EPOPEE | K187: ECRITURE | L187: ELOGE | M187: GARDIEN | N187: CONVERTIR | O187: DRAGE | P187: ARTISAN | Q187: DECORATION | R187: FANAGE | S187: ANITE | T187: SYNERGIE
A188: IMAGINAIRE | B188: GÉNÉROSITÉ | C188: FOND | D188: ECHINE | E188: CONSERVER | F188: COUPURE | G188: ORALITÉ | H188: DEPOT | I188: DEFENSE | J188: EPOQUE | K188: ECRIVAIN | L188: EMERGENCE | M188: GARNISON | N188: CONVOYEUR | O188: DRAIN | P188: ARTISANAT | Q188: DECORER | R188: FENNEC | S188: ANKH | T188: TARIF
A189: IMAGINE | B189: GÉRER | C189: FONDRE | D189: ECLAIR | E189: CONSOMME | F189: COURBATURE | G189: ORGE | H189: DEPOUILLER | I189: DENT | J189: ERE | K189: ECRIVAINE | L189: EMERGER | M189: GENERAL | N189: COPEAUX | O189: DRAP | P189: ASPECT | Q189: DENTELLE | R189: FERME | S189: ANNAL | T189: TECHNIQUE
A190: IMAGINER | B190: GÊNE | C190: FORCE | D190: ECLAT | E190: CONTENT | F190: COURIR | G190: ORIGAMI | H190: DESSIN | I190: DERMAPTERE | J190: ERUDIT | K190: EDITEUR | L190: EMINENT | M190: GENEROSITE | N190: COPIE | O190: DUNE | P190: ASPECTER | Q190: DESSIN | R190: FEU | S190: ANNEE | T190: TENDANCE
... A207: INNOVE | B207: IMPÉTUEUX | C207: GOUACHE | D207: EMOTIONNEL | E207: COUVERT | F207: DEBUT | G207: POÉSIE | H207: DRESSER | I207: ECAILLE | J207: FABLE | K207: ENSEIGNER | L207: EVENEMENT | M207: HEROIQUE | N207: CRAN | O207: EMBRUN | P207: ATTEINDRE | Q207: EBENISTE | R207: FRACTURE | S207: APOGON | T207: ÉTUDE
A208: INNOVER | B208: INDICIBLE | C208: GRANDEUR | D208: ENDURANCE | E208: CRAQUANT | F208: DECLIN | G208: PRAIRIE | H208: EBAUCHE | I208: ECLOSION | J208: FABULEUSE | K208: ENTITE | L208: EVOLUTION | M208: HEROISME | N208: CREER | O208: EMBRUNS | P208: ATTERRIR | Q208: ECLAIRAGE | R208: FRANC | S208: APPAS
A209: INSTANCE | B209: INDIGNÉ | C209: GRENAT | D209: ENERGIE | E209: CREATIF | F209: DEFENSE | G209: PRATIQUE | H209: EBAUCHER | I209: ECORCE | J209: FACON | K209: ENTRACTE | L209: EXEMPLE | M209: HEROS | N209: CREUSER | O209: ENCLAVE | P209: ATTIQUE | Q209: ECLAIRE | R209: FRANCHIR | S209: APPAT
A210: INTELLECT | B210: INDOLENCE | C210: GRIS | D210: ENERGIQUE | E210: CREME | F210: DEFLORE | G210: PRIEURÉ | H210: ECAILLE | I210: ELEVAGE | J210: FAIT | K210: ENVOI | L210: EXPLOIT | M210: HOMMAGE | N210: CREUSET | O210: ENGOUFFRER | P210: AUBER | Q210: ECLAIRER | R210: FRIMAS | S210: APPES
A211: INTENTION | B211: INDÉFINI | C211: GRISATRE | D211: ENORME | E211: CREMEUX | F211: DELTOIDE | G211: PRIMEUR | H211: ECART | I211: ELYTRE | J211: FAITS | K211: EPIC | L211: EXPOSITION | M211: HONNEUR | N211: CRIBLE | O211: ENNEIGE | P211: AUBERON | Q211: ECLAT | R211: FROID | S211: APPON
A212: INTRODUIT | B212: INDÉFINIE | C212: GROSEILLE | D212: ENSEMBLE | E212: CREPIERE | F212: DEMARCHE | G212: PRIÈRE | H212: ECLAT | I212: EMBUSCADE | J212: FAMILLE | K212: EPIGRAMME | L212: EXPRIMER | M212: IDEAL | N212: CRISTAL | O212: ENSOLEILLE | P212: AUDACIEUX | Q212: ECLATANT | R212: FRONT | S212: APPONT
A213: INTUITIF | B213: INHIBÉ | C213: HALO | D213: ENTRETIEN | E213: CREVETTE | F213: DENT | G213: PÂTURAGE | H213: ECLATER | I213: EMYDE | J213: FEODAL | K213: EPILOGUE | L213: FABLE | M213: IMPASSIBLE | N213: CRITERE | O213: ENTOURAGE | P213: AUREOLE | Q213: ECRAN | R213: GALET | S213: APPROCHE
A214: INTUITION | B214: INSTINCT | C214: HARMONIE | D214: ENTROPIE | E214: CROQUANT | F214: DENTISTE | G214: PÔLE | H214: ECOFACT | I214: ENROULER | J214: FEODALE | K214: EPIPHORE | L214: FACE | M214: IMPETUS | N214: CROCHET | O214: EOLIEN | P214: AUVENT | Q214: ECRIN | R214: GAZELLE | S214: APPUI
A215: INUTILE | B215: INTENSE | C215: HARMONISER | D215: EPAIS | E215: CROQUER | F215: DENTS | G215: QUATUOR | H215: ECORCER | I215: EPEIRE | J215: FEODALITE | K215: EPIQUE | L215: FAMEUSE | M215: IMPULSION | N215: CRYPTAGE | O215: EPAIS | P215: AVALOIRE | Q215: ECRU | R215: GEISER | S215: APRES
...

Sheet M5
A1: ALKAMO — M5
A2: N° | B2: THÈME | C2: MOTS
A3: 1 | B3: ARCHITECTURE | C3: =COUNTA(M5_mots!A3:A5000) -> 1512
A4: 2 | B4: ART | C4: =COUNTA(M5_mots!B3:B5000) -> 971
A5: 3 | B5: HISTOIRE | C5: =COUNTA(M5_mots!C3:C5000) -> 456
A6: 4 | B6: ASTRONOMIE | C6: =COUNTA(M5_mots!D3:D5000) -> 601
A7: 5 | B7: MÉDECINE | C7: =COUNTA(M5_mots!E3:E5000) -> 809
A8: 6 | B8: COMMUNICATION | C8: =COUNTA(M5_mots!F3:F5000) -> 551
A9: 7 | B9: THÉÂTRE | C9: =COUNTA(M5_mots!G3:G5000) -> 405
A10: 8 | B10: ÉCONOMIE | C10: =COUNTA(M5_mots!H3:H5000) -> 638
A11: 9 | B11: DROIT | C11: =COUNTA(M5_mots!I3:I5000) -> 706
A12: 10 | B12: RELIGION | C12: =COUNTA(M5_mots!J3:J5000) -> 632
A13: 11 | B13: CONCEPT ET IDÉE | C13: =COUNTA(M5_mots!K3:K5000) -> 407
A14: 12 | B14: INDUSTRIE | C14: =COUNTA(M5_mots!L3:L5000) -> 659
A15: 13 | B15: HUMANITÉ | C15: =COUNTA(M5_mots!M3:M5000) -> 715
A16: 14 | B16: TOURISME | C16: =COUNTA(M5_mots!N3:N5000) -> 367
A17: 15 | B17: CULINAIRE | C17: =COUNTA(M5_mots!O3:O5000) -> 839
A18: 16 | B18: NAVIGATION | C18: =COUNTA(M5_mots!P3:P5000) -> 1093
A19: 17 | B19: LITTÉRATURE | C19: =COUNTA(M5_mots!Q3:Q5000) -> 649
A20: 18 | B20: COMMERCE | C20: =COUNTA(M5_mots!R3:R5000) -> 1019
A21: 19 | B21: SPORT | C21: =COUNTA(M5_mots!S3:S5000) -> 579
A22: 20 | B22: URBANISME | C22: =COUNTA(M5_mots!T3:T5000) -> 628
A23: 21 | B23: MILITAIRE | C23: =COUNTA(M5_mots!U3:U5000) -> 774
A24: 22 | B24: ÉNERGIE | C24: =COUNTA(M5_mots!V3:V5000) -> 754
A25: 23 | B25: AGRONOMIE | C25: =COUNTA(M5_mots!W3:W5000) -> 848
A26: 24 | B26: TEXTILE | C26: =COUNTA(M5_mots!X3:X5000) -> 1458
A27: 25 | B27: DIPLOMATIE | C27: =COUNTA(M5_mots!Y3:Y5000) -> 904
A28: TOTAL | C28: =SUM(C3:C27) -> 18974

Sheet M5_mots
A1: ARCHITECTURE | B1: ART | C1: HISTOIRE | D1: ASTRONOMIE | E1: MÉDECINE | F1: COMMUNICATION | G1: THÉÂTRE | H1: ÉCONOMIE | I1: DROIT | J1: RELIGION | K1: CONCEPT ET IDÉE | L1: INDUSTRIE | M1: HUMANITÉ | N1: TOURISME | O1: CULINAIRE | P1: NAVIGATION | Q1: LITTÉRATURE | R1: COMMERCE | S1: SPORT | T1: URBANISME | U1: MILITAIRE | V1: ÉNERGIE | W1: AGRONOMIE | X1: TEXTILE | Y1: DIPLOMATIE
A2: =COUNTA(A3:A5000) -> 1512 | B2: =COUNTA(B3:B5000) -> 971 | C2: =COUNTA(C3:C5000) -> 456 | D2: =COUNTA(D3:D5000) -> 601 | E2: =COUNTA(E3:E5000) -> 809 | F2: =COUNTA(F3:F5000) -> 551 | G2: =COUNTA(G3:G5000) -> 405 | H2: =COUNTA(H3:H5000) -> 638 | ... Y2: =COUNTA(Y3:Y5000) -> 904
A3: ABAQUE | B3: ABSTRAIT | C3: ABOLIR | D3: ABSIDE | E3: ABCES | F3: ABONNÉ | G3: ABSURDE | H3: ACCUMULER | I3: ABANDON | J3: ABBAYE | K3: ABSTRAIT | L3: ABATTOIR | M3: ABNEGATION | N3: ABRI | O3: ABAISSER | P3: ABATEE | Q3: ABSTRACTIO | R3: ABATAGE | S3: ACROBATIE | T3: ABRI | U3: ABRI | V3: ABATTAGE | W3: ABATTOIR | X3: ABACA | Y3: ABDIQUER
A4: ABAT | B4: ACADEMISME | C4: ABOLITION | D4: ACCOMPLIR | E4: ABDOMEN | F4: ACCENT | G4: ACCESSOIRE | H4: ACHAT | I4: ABATTEMENT | J4: ABBE | K4: ABSTRAITE | L4: ABRASION | M4: ABOUTIR | N4: ACCUEIL | O4: ABATS | P4: ABER | Q4: ABSTRAIT | R4: ACCORD | S4: ACROSPORT | T4: ABRIBUS | U4: ACADEMIE | V4: ABSORPTION | W4: ABATTRE | X4: ABEILLE | Y4: ABITRER
A5: ABATTRE | B5: ACCORD | C5: ABREGE | D5: ACCRETION | E5: ABOLIR | F5: ACCEPTER | G5: ACCLAMER | H5: ACQUISE | I5: ABDIQUER | J5: ABBESSE | K5: ACCEPTION | L5: ACHAT | M5: ABRI | N5: AEROPORT | O5: ABONDANCE | P5: ABORD | Q5: ACADEMICIE | R5: ACCORDER | S5: ACTIF | T5: ABSIDE | U5: ACCORD | V5: ACCELERATE | W5: ABEILLE | X5: ABLATION | Y5: ABOLIR
A6: ABBAYE | B6: ACCORDAGE | C6: ABROGATION | D6: ACRAB | E6: ABSORPTION | F6: ACCLAMER | G6: ACCORD | H6: ACQUIT | I6: ABOLIR | J6: ABJURER | K6: ACCORD | L6: ACIDE | M6: ABRITER | N6: AFFLUENT | O6: ABONDANT | P6: ABORDAGE | Q6: ACADEMISME | R6: ACCUMULER | S6: ACTION | T6: ACCROISSEM | U6: ACHARNE | W6: ABREUVER | X6: ACADEMIE | Y6: ABOLITION
A7: ABOUTIR | B7: ACCORDEON | C7: ACADEMIE | D7: ACTEUR | E7: ACADEMIE | F7: ACCORD | G7: ACCUEIL | H7: ACTIF | I7: ABROGER | J7: ABLUTION | K7: ACTE | L7: ACIER | M7: ABSOUDRE | N7: AFFLUX | O7: ABOUTI | P7: ABORDER | Q7: ACCENT | R7: ACHAT | S7: ACTIVITE | T7: ACCROTERE | U7: ACHARNEMEN | V7: ACCUMULATE | W7: ABREUVOIR | X7: ACCESSOIRE | Y7: ABORDER
A8: ABREUVOIR | B8: ACCORDEUR | C8: ACCESSION | D8: ACTIVITE | E8: ACCOUCHEUR | F8: ACCÈS | G8: ACROBATE | H8: ACTION | I8: ABSOLUTION | J8: ABSIDE | K8: ACTUEL | L8: ACIERIE | M8: ACCEPTER | N8: AGENCE | O8: ABRICOT | P8: ABRI | Q8: ACCESSOIRE | R8: ACHETER | S8: ADVERSAIRE | T8: ACIER | U8: ACHEEN | V8: ACHAT | W8: ABRICOT | X8: ACCLAME | Y8: ABOUTIR
A9: ABRI | B9: ACCROCHE | C9: ACIER | D9: AERODYNE | E9: ACCUEIL | F9: ACRONYME | G9: ACTE | H9: AFFAIRE | I9: ABSOUDRE | J9: ABSOLUTION | K9: ADAPTATION | L9: ACRYLIQUE | M9: ACCOMPLIR | N9: AGREMENT | O9: ABSINTHE | P9: ABYSSAL | Q9: ACROSTICHE | R9: ACHETEUR | S9: AEROBIC | T9: ACROPOLE | U9: ACIER | V9: ACHETER | W9: ABSINTHE | X9: ACCOUCHEME | Y9: ABSENCE
A10: ABSIDE | B10: ACHROME | C10: ACROPOLE | D10: AEROLITE | E10: ACCUEILLIR | F10: ACTE | G10: ACTEUR | H10: AGENCE | I10: ABUS | J10: ABSOUDRE | K10: AFFIRMER | L10: ACTIF | M10: ACCORD | N10: AGRICULTUR | O10: ACCOMPLI | P10: ACCALMIE | Q10: ACTE | R10: ACOMPTE | S10: AIKIDO | T10: AEROPORT | U10: ACTION | V10: ACRETE | W10: ACACIA | X10: ACCROC | Y10: ABSOUDRE
A11: ABSTRAIT | B11: ACORDE | C11: ADHESION | D11: AGIR | E11: ACNE | F11: ADRESSE | G11: ACTION | H11: AGENT | I11: ABUSER | J11: ABSOUTE | K11: ALGEBRE | L11: ACTIVITE | M11: ACCORDER | N11: AGROTOURIS | O11: ACCORD | P11: ACCONAGE | Q11: ACTEURS | R11: ACQUET | S11: AILIER | T11: AGENCEMENT | U11: ACTIVISTE | V11: ACTINIDE | W11: ACAJOU | X11: ACCROCHE | Y11: ABSTENIR
A12: ACAJOU | B12: ACTE | C12: AGORA | D12: AGO | E12: ACOUSIE | F12: ADRESSER | G12: ACTRICE | H12: AGIO | I12: ACCEDER | J12: ABSTENIR | K12: ALLEGORIE | L12: ADAPTATION | M12: ACCUEIL | N12: AIR | O12: ACCUEIL | P12: ACCORE | Q12: ACTION | R12: ACQUISE | S12: ALPINISME | T12: AGGLOMERAT | U12: ADJUDANT | V12: ACTION | W12: ACARIEN | X12: ACETATE | Y12: ACADEMIE
A13: ACANTHUS | B13: ACTEUR | C13: AGREGATION | D13: AIR | E13: ACUPUNCTUR | F13: AFFICHAGE | G13: ADAGIO | H13: AGIOTAGE | I13: ACCESSION | J13: ABSTINENCE | K13: AMBITION | L13: ADDITIF | M13: ACE | N13: ALBUM | O13: ACCUEILLI | P13: ACCOSTAGE | Q13: ACTUALISME | R13: ACQUIT | S13: AMATEUR | T13: AGGLOMERE | U13: ADVERSAIRE | V13: ACTIONNEUR | W13: ACHENE | X13: ACHAT | Y13: ACCEDER
A14: ACCES | B14: ACTIVITES | C14: AGRESSION | D14: AKARNAR | E14: ADMINISTRE | F14: AFFICHE | G14: ADRESSE | H14: AGNEL | I14: ACCORD | J14: ACEDIE | K14: ANALOGIE | L14: ADJUVANT | M14: ACHAT | N14: ALLER | O14: ACETO | P14: ACCOSTER | Q14: ACTUALITE | R14: ACTIF | S14: AMICAL | T14: AGORA | U14: AERIEN | V14: ACTIVITE | W14: ACIDITE | X14: ACRYLIQUE | Y14: ACCEPTER
A15: ACCOLADE | B15: ACTRICE | C15: ALCHIMISTE | D15: ALBEDO | E15: ADOUCIR | F15: AGENCE | G15: AFFICHE | H15: AGRICOLE | I15: ACCUEILLIR | J15: ACHOURA | K15: ANALYSE | L15: ADROIT | M15: ACQUERIR | N15: ALPINISME | O15: ACIDE | P15: ACONIER | Q15: ADAPTATIO | R15: ACTION | S15: AMORTI | T15: AGRANDISSE | U15: AERODROME | V15: ADDITION | W15: ACRE | X15: ADMIRATION | Y15: ACCLAMER
A16: ACCOLURE | B16: ACTUALITE | C16: ALLEGORIE | D16: ALBENE | E16: AFFECT | F16: AGENDA | G16: AGORA | H16: AIDE | I16: ACCUSE | J16: ADEPTE | K16: ANALYSER | L16: AFFAIRE | M16: ACTE | N16: AMBULANT | O16: ACIDULE | P16: ACTUAIRE | Q16: ADMIRATEU | R16: ACTIVITE | S16: AMUSEMENT | T16: AIR | U16: AERONEF | V16: ADYNAMIE | W16: ACTIVITE | X16: AGAVE | Y16: ACCOMPLI
A17: ACCORD | B17: ADAGIO | C17: ALLIANCE | D17: ALCOR | E17: AFFECTER | F17: AGORA | G17: ALLEGORIE | H17: AISANCE | I17: ACCUSER | J17: ADHAN | K17: ANALYTIQUE | L17: AFFINAGE | M17: ACTES | N17: AMENAGEMEN | O17: ACRAS | P17: AERIEN | Q17: AFFECTE | R17: AERIEN | S17: ANNEAUX | T17: ALEM | U17: AFFAIRE | V17: AGENCE | W17: ADVENTICE | X17: AGLET | Y17: ACCORD
A18: ACCOTEMENT | B18: ADMIRATEU | C18: ALMANACH | D18: ALGOL | E18: AFFECTION | F18: ALARME | G18: ALLEGRO | H18: ALENA | I18: ACQUERIR | J18: ADHESION | K18: ANCRER | L18: AGENCEMENT | M18: ACTEUR | N18: ANIMATION | O18: ACRE | P18: AEROBUS | Q18: AFFECTIF | R18: AFFAIRE | S18: ANTIDOPAGE | T18: ALFIZ | U18: AFFRONTEME | V18: AGILITE | W18: ADVENTIF | X18: AGNEAU | Y18: ACCORDER
... A22: ACOLYTE | B22: AEROBIC | C22: ANALYSER | D22: ALPHA | E22: AIDER | F22: AMBIGUÏTÉ | G22: AMBULANT | H22: AMENDE | I22: ACQUITTER | J22: ADULATION | K22: APPROCHE | L22: AIGUISER | M22: ADAPTION | N22: ARRIVE | O22: AGAR | P22: AEROPLANE | Q22: AIR | R22: AGIO | S22: AQUAGYM | T22: ANARCHIQUE | U22: AGRESSIF | V22: ALIMENT | W22: AFFOURER | X22: AIGU | Y22: ACHAT
A23: ACORE | B23: AEROGRAPHE | C23: ANALYSES | D23: ALTAZIMUTH | E23: AIGUILLE | F23: ANIMATEUR | G23: AMPHI | H23: AMENDER | I23: ACTE | J23: AFFECTION | K23: APPUI | L23: AIR | M23: ADHERER | N23: ARRIVEE | O23: AGAVE | P23: AEROSTAT | Q23: ALARMANT | R23: AGIOTAGE | S23: AQUAPLANE | T23: ANNEXION | U23: AGRESSION | W23: AGAME | X23: AIGUILLE | Y23: ACQUERIR
A24: ACQUIT | B24: AFFICHE | C24: ANCIEN | D24: ALTIMETRE | E24: AIR | F24: ANIMER | G24: ANIMATEUR | H24: AMORTIR | I24: ACTES | J24: AGAPE | K24: ARCHETYPE | L24: ALARME | M24: ADHESION | N24: ARRIVER | O24: AGNEAU | P24: AFFALER | Q24: ALEXANDRIN | R24: AGNEL | S24: ARBALETE | T24: APPARTEME | U24: AGUERRIR | V24: ALIMENTER | W24: AGAVE | X24: AIGUILLEE | Y24: ACTE
A25: ACROTERE | B25: AGON | C25: ANECDOTE | D25: ALTITUDE | E25: AJUSTER | F25: ANNALE | G25: APART | H25: AMPLEUR | I25: ACTIF | J25: AGNOSTIQUE | K25: ARGUMENT | L25: ALCOOL | M25: ADMETTRE | N25: ARTISANAT | O25: AGNELET | P25: AFFINER | Q25: ALLEGORIE | R25: AGREAGE | S25: ARBITRAL | T25: AQUEDUC | U25: AIR | V25: ALLANT | W25: AGNEAU | X25: AISANCE | Y25: ACTES
A26: ACTUEL | B26: AIKIDO | C26: ANGE | D26: ALUNIR | E26: ALCALOIDE | F26: ANNONCE | G26: APARTE | H26: ANALYSE | I26: ACTION | J26: AMBON | K26: ARGUMENTER | L26: ALESAGE | M26: ADMIRER | N26: ASCENSION | O26: AGREMENTER | P26: AFFRETER | Q26: ALLEGORIQ | R26: AGREEUR | S26: ARBITRE | T26: ARC | U26: ALLIANCE | V26: ALLEGRESSE | W26: AGNELAGE | X26: AISE | Y26: ACTEUR
A27: ADAMANTIN | B27: AIR | C27: ANIMATION | D27: ALYCONE | E27: ALIENE | F27: ANNONCER | G27: APLOMB | H27: ANALYSTE | I27: ACTIONNER | J27: AME | K27: ART | L27: ALESOIR | M27: ADN | N27: ASTRONAUT | O27: AGRUME | P27: AFFRETEUR | R27: AGRICOLE | S27: ARCHER | T27: ARCADE | U27: ALLIE | V27: ALLUMAGE | W27: AGNELER | X27: AJOURE | Y27: ACTEURS
A28: ADAPTER | B28: AISANCE | C28: ANNALE | D28: AMAS | E28: ALIENISTE | F28: ANNONCEUR | G28: APPLAUDIR | H28: ANNALITE | I28: ADHERER | J28: AMEN | K28: ASPECT | L28: ALFA | M28: ADOPTER | N28: ATOUT | O28: AIGRE | P28: AGREEUR | Q28: AMPHITHEAT | R28: AGUICHE | S28: ARCHERIE | T28: ARCATURE | U28: AMIRAL | V28: ALTERNATEU | W28: AGRAIRE | X28: AJOUREE | Y28: ACTIF
A29: ADENT | B29: ALBUM | C29: ANNALES | D29: AMATEUR | E29: ALLAITER | F29: ANONYMAT | G29: ARCHET | H29: ANNUEL | I29: ADJOINT | J29: AMIDA | K29: ASPIRER | L29: ALIMENT | M29: ADORER | N29: ATTIRE | O29: AIGUILLAT | P29: AGRES | Q29: AMPOULE | R29: AIDE | S29: ARENE | T29: ARCEAU | U29: AMIRAUTE | V29: AME | W29: AGRICOLE | X29: AJOURER | Y29: ACTION
A30: ADEQUATION | B30: ALCHIMIE | C30: ANNEXION | E30: ALLERGIE | F30: ANTENNE | G30: ARENE | H30: ANNUITE | I30: ADJUGER | J30: AMISH | K30: ASSIMILE | L30: ALIMENTER | M30: ADULTE | N30: ATTRACTIF | O30: AIL | P30: AIGUILLEUR | Q30: ANALEPSE | R30: AISANCE | S30: ARRIERE | T30: ARCHEVECH | U30: AMORCE | V30: AMORTISSEM | W30: AGROCHIMIE | X30: AJUSTE | Y30: ADAPTER
A31: ADOBE | B31: ALLEGORIE | C31: ANTIQUE | D31: ANALEMME | E31: ALLOPATHE | F31: APPEL | G31: ARIA | H31: APPOINT | I31: ADMETTRE | J31: AMOUR | K31: ATYPIQUE | L31: ALLIAGE | M31: AFFABLE | N31: ATTRACTION | O31: AILE | P31: AIRE | Q31: ANAPHORE | R31: ALENA | S31: ARTISTE | T31: ARCHITECTE | U31: ANCIEN | V31: AMPACITE | W31: AGROLOGIE | X31: AJUSTER | Y31: ADHERENT
A32: ADOSSEMENT | B32: ALLEGRO | C32: ANTIQUITE | D32: ANGLE | E32: ALLOPATHIE | F32: APPELER | G32: ARIETTE | H32: APPORT | I32: ADOPTER | J32: ANAGOGIE | K32: AXIOME | L32: ALLUMETTE | M32: AFFECTION | O32: AILERON | P32: AJUT | Q32: ANGELISME | R32: ALLOCATION | S32: ATEMI | U32: ANIMOSITE | V32: AMPERAGE | W32: AGRONOME | X32: ALAISE | Y32: ADHERER
A33: ADRESSE | B33: ALTO | C33: APOCRYPHE | D33: ANNEAU | E33: ALVEOLE | F33: APPROUVER | G33: ARLEQUIN | H33: APPORTEUR | I33: ADOPTION | J33: ANCETRE | K33: BASE | L33: ALUMINIUM | M33: AFFINITE | N33: ATTRAIT | O33: AIOLI | P33: ALBATROS | Q33: ANONYME | R33: ALOI | S33: ATHLETE | T33: ARCOLOGIE | U33: ANNEXER | V33: AMPERE | W33: AGRONOMIE | X33: ALESE | Y33: ADHESION
A34: AFFLEUR | B34: AMATEUR | C34: ARBITRAGE | D34: ANNEE | E34: ALZHEIMER | F34: ARBITRAGE | G34: ART | H34: ARGENT | I34: ADRESSE | J34: ANGE | K34: BEAU | L34: ALUNERIE | M34: AFFIRMER | N34: AUBERGE | O34: AIR | P34: ALERTE | Q34: ANTHOLOGIE | R34: ALTERATION | S34: ATHLETIQUE | T34: AREA | U34: ANNEXION | V34: ANIMATION | W34: AGRUME | X34: ALLURE | Y34: ADJOINT
A35: AFFLEURER | B35: AMBITION | C35: ARC | D35: ANTARES | E35: AMADOUER | F35: ARCHIVE | G35: AUBADE | H35: ARGENTIER | I35: ADULTERE | J35: ANGELOT | K35: BIAIS | L35: AMBRE | M35: AFFLICTION | N35: AUTOCAR | O35: AIRELLE | P35: ALGUES | Q35: ANTITHESE | R35: AMENDE | S35: ATHLETISME | T35: ART | V35: ANION | W35: AGRUMES | X35: ALPAGA | Y35: ADMIRER
A36: AGATE | B36: ANDANTE | C36: ARCHAISME | D36: ANTENNE | E36: AMBULANCE | F36: ARGOT | G36: AUDACE | H36: ARPAILLEUR | I36: AFFAIRE | J36: ANGLICAN | K36: BIEN | L36: AMIDON | M36: AGE | N36: AUTORAIL | O36: AJOUTER | P36: ALLEE | Q36: APARTES | R36: AMENDER | S36: ATTAQUANT | T36: ARTERE | U36: ANTAGONIST | V36: ANODE | W36: AIL | X36: AMADIS | Y36: ADOPTER
A37: AGENCEMENT | B37: ANIMATEUR | C37: ARCHIVE | D37: APEX | E37: AMBULANCIE | F37: ARGUEMENT | G37: AUDITION | H37: ARRERAGES | I37: AFFIDAVIT | J37: ANIMISME | K37: BIOLOGIE | L37: AMORCE | M37: AGENT | N37: AVENTURE | O37: ALGUE | P37: ALLEGE | Q37: APHORISME | R37: AMITIE | S37: ATTELAGE | T37: ARTIFICIAL | U37: ANTICHAR | V37: APATHIE | W37: AILE | X37: AMBULATOIR | Y37: ADOPTION
A38: AGENCER | B38: ANTILABE | C38: ARCHIVER | D38: APHELIE | F38: ARGUMENT | G38: AUDITORIUM | H38: ARRIERE | I38: AFFIRMER | J38: ANIMISTE | K38: BIOLOGIQUE | L38: AMORTIR | M38: AGIR | N38: AVENTURIE | O38: ALIMENT | P38: ALLERVOILE | Q38: APOLOGUE | R38: AMORTIR | S38: AUTOMOBILE | T38: ARTISTE | U38: ANTIDROGUE | V38: APATHIQUE | W38: AILLER | X38: AMIANTE | Y38: ADORER
A39: AGENT | B39: ANTIQUE | C39: ARCHIVES | D39: APHELION | E39: AMELIORER | F39: ARTICLE | G39: AUTEUR | H39: ARRIMAGE | I39: AGIR | J39: ANNATE | K39: BLAME | L39: AMPHORE | M39: AGREER | N39: AVENTURIER | O39: ALLIAGE | P39: ALLURE | Q39: APOSTROPHE | R39: AMPLEUR | S39: AVIATION | T39: ASPECT | V39: APLOMB | W39: AIRE | X39: AMIDONNER | Y39: ADRESSE
A40: AGGLOMERE | B40: ANTIQUITE | C40: ARGENT | D40: APOASTRE | E40: AMINE | F40: ASSEMBLER | G40: AVANT | H40: ASSAINIR | I40: AGREER | J40: APOCALYPSE | K40: BONHEUR | L40: AMPOULE | M40: AIDE | N40: BADAUD | O40: ALLIE | P40: ALOSE | Q40: APPRETE | R40: ANALYSE | S40: AVIRON | T40: ASPHALTE | U40: ANTITABAC | V40: APPROVISIO | W40: AIRELLE | X40: AMORCE | Y40: ADROIT
A41: AGGLOMERER | B41: APARTE | C41: ARMEE | D41: APOGEE | E41: AMPHETAMIN | F41: ATTENTE | G41: BAL | H41: ASSIETTE | I41: AGREMENT | J41: APOSTAT | K41: BUT | L41: ANALYSE | M41: AIDER | N41: BAGAGE | O41: ALOSE | P41: ALTIPORT | Q41: ARABE | R41: ANALYSTE | S41: BALLE | T41: ASSAINISSE | U41: ANTITERROR | V41: APRETE | W41: AJONC | X41: AMPLE | Y41: AFFAIRE
A42: AGILE | B42: AQUARELLE | C42: ARMISTICE | D42: APOLLO | E42: AMPOULE | F42: ATTESTER | G42: BALCON | H42: ASSIGNAT | I42: AGRESSION | J42: APOSTATE | K42: CADRE | L42: APTE | M42: AIGUILLER | N42: BAGUENAUDE | O42: AMANDE | P42: AMARINER | Q42: ARGUMENT | R42: ANNALITE | S42: BALLON | T42: ASSIEGEE | U42: APOTRE | V42: APTE | W42: ALIMENT | X42: AMPUTATION | Y42: AFFAIRES
A43: AGORA | B43: ARABESQUE | C43: ART | D43: APOLUNE | E43: ANALGESIQU | F43: AUDIENCE | G43: BALLADE | H43: ASSOCIE | I43: ALERTER | J43: APOTRE | K43: CAS | L43: ARGENT | M43: AIMANT | N43: BAIGNEUR | O43: AMER | P43: AMARRAGE | Q43: ARIA | R43: ANNONCE | S43: BAQUET | T43: ATRIUM | U43: APPELE | V43: APTITUDE | W43: ALISE | X43: AMURE | Y43: AFFIRMER
A44: AGRAFAGE | B44: ARCHET | C44: ARTICLE | D44: APPARENTE | E44: ANALYSE | F44: AUDIO | G44: BALLERINE | H44: ASSURANCE | I44: ALIBI | J44: ARCHE | K44: CATEGORIE | L44: ARGILE | M44: AINE | N44: BAIN | O44: AMIDON | P44: AMARRE | Q44: ARRANGE | R44: ANNUEL | S44: BARRE | T44: ATTIQUE | U44: APRESGUERR | V44: ARDENT | W44: ALLEE | X44: ANATOMIE | Y44: AGENCE
A45: AGRAFE | B45: ARIA | C45: ARTISTIQUE | D45: APSIDE | E45: ANATOMIE | F45: AUDITOIRE | G45: BALLET | H45: ATELIER | I45: ALIMENTS | J45: ARDEUR | K45: CAUSALITE | L45: ARME | M45: AINES | N45: BALADE | O45: AMPLEUR | P45: AMARRER | Q45: ART | R45: ANNUITE | S45: BASEBALL | U45: ARBITRAGE | V45: ARDEUR | W45: ALOES | X45: ANATOMISTE | Y45: AGENCER
A46: AGRAFFAGE | B46: ARPEGE | C46: ASCENSION | D46: ARAIGNEE | E46: ANATOMIQUE | F46: AUTORISER | G46: BANC | H46: AUMONE | I46: ALINEA | J46: ASCETISME | K46: CAUSE | L46: ARMEMENT | M46: AIR | N46: BALNEAIRE | O46: AMUSE | P46: AMARRES | Q46: ARTHURIEN | R46: ANTIQUAIRE | S46: BASKET | T46: AUTOBUS | U46: ARBITRE | V46: ARGON | W46: ALPAGE | X46: ANCIEN | Y46: AGENDA
A47: AGRANDIR | B47: ART | C47: ASSASSINAT | D47: ARCHE | E47: ANEMIE | F47: AVENANT | G47: BARBE | H47: AUREUS | I47: ALLEGUER | J47: ASPIRATION | K47: CERNER | L47: ART | M47: AISANCE | N47: BALNEARE | O47: ANANAS | P47: AME | Q47: ARTIFICIE | R47: APPEL | S47: BASKETBALL | T47: AUTOCAR | U47: ARCHER | V47: ARME | W47: AMANDIER | X47: ANESTHESIE | Y47: AGENT
A48: AGREE | C48: ASSEMBLEE | D48: ARIEL | E48: ANESTHESIE | F48: AVERTIR | G48: BAROQUE | H48: AUSTERITE | I48: ALLIER | J48: ATHEE | K48: CERTITUDE | L48: ARTICULER | M48: AJUSTER | N48: BATEAU | O48: ANCHOIS | P48: AMER | Q48: ARTISTE | R48: APPOINT | S48: BATON | T48: AUTOMOBILE | U48: ARENE | V48: ARMEE | W48: AMENDEMENT | X48: ANGLAISE | Y48: AGILE
A49: AIGUILLE | B49: ARTIFICE | C49: AURELE | D49: ARTISTE | E49: ANESTHESIQ | F49: AVIS | G49: BARYTON | H49: AVARE | I49: ALLONGE | J49: ATHEISME | K49: CHAMP | L49: ARTIFICE | M49: ALERTER | N49: BEDOUIN | O49: ANDOUILLE | P49: AMERRIR | Q49: ARTISTIQUE | R49: APPORT | S49: BATTANT | T49: AUTOPONT | U49: ARGOULET | V49: ARRACHER | W49: AMENDER | X49: ANGORA | Y49: AGIR
A50: AILE | B50: ARTISAN | C50: AUTEUR | E50: ANIS | F50: AXER | G50: BATIMENT | H50: AVARICE | I50: ALLOUER | J50: ATMA | K50: CHIMIE | L50: ARTIFICIEU | M50: ALLIANCE | N50: BERLINE | O50: ANETH | P50: AMERS | Q50: ASPECT | R50: APPORTEUR | S50: BATTE | T50: AUTOROUTE | U50: ARME | V50: ASTATIQUE | W50: AMIDON | X50: ANORAK | Y50: AGREER
A51: AILERON | B51: ARTISANAT | C51: AUTORITE | D51: ASPECT | E51: ANNEXE | F51: BABILLER | G51: BATTEMENT | H51: AVERS | I51: AMBASSADE | J51: ATTENTE | K51: CHOIX | L51: ARTISAN | M51: ALLIE | N51: BILLET | O51: ANGULE | P51: AMIRAL | Q51: ASSONANCE | R51: APPROVISIO | S51: BATTRE | T51: AUVENT | U51: ARMEE | V51: ASTRE | W51: ANALYSE | X51: ANTIMITE | Y51: AGREMENT
A52: AIR | B52: ARTISTE | C52: AVENTURE | D52: ASSOLIR | E52: ANSE | F52: BALBUTIER | G52: BEAUTE | H52: AVOIR | I52: AMENDE | J52: AUMONE | K52: CHOSE | L52: ARTISANAL | M52: ALLIER | N52: BILLETTIQ | O52: ANIS | P52: AMIRAUTE | Q52: ATTENTAT | R52: ARBITRAGE | S52: BIATHLON | T52: AVAL | U52: ARMEMENT | V52: ATOME | W52: ANANAS | X52: APEX | Y52: AIDE
A53: AIRE | B53: ARTISTERIE | C53: AZTEQUE | D53: ASTERISME | E53: ANTALGIE | F53: BALISE | G53: BEMOL | H53: BADWILL | I53: AMENDER | J53: AUTEL | K53: CLAIR | L53: ARTISANAT | M53: ALTERITE | N53: BOHEMIEN | O53: APERITIF | P53: AMMARE | Q53: ATTRIBUER | R53: ARGENT | S53: BICROSS | T53: AVENUE | U53: ARMER | V53: ATOMIQUE | W53: ANDAIN | X53: APIECEUR | Y53: AIDER
A54: AJOUR | B54: ARTISTIQUE | C54: AZTEQUES | D54: ASTEROIDE | E54: ANTIBIOTIQ | F54: BANDEROLE | G54: BILLET | H54: BAIL | I54: AMIABLE | J54: AVATAR | K54: CLARTE | L54: ASSEMBLAGE | M54: ALTRUISME | N54: BONDE | O54: APOGEE | P54: AMONT | Q54: AUBE | R54: ARGENTIER | S54: BILLARD | T54: BALCON | U54: ARMET | V54: ATONIE | W54: ANE | X54: APLAT | Y54: AIGUILLER
A55: AJOURAGE | B55: ARTMODERNE | C55: BANNIR | D55: ASTRAL | E55: ANTICANCER | F55: BAVARD | G55: BIS | H55: BAISSE | I55: AMNISTIE | J55: AVE | K55: CLASSE | L55: ASSEMBLEE | M55: AMABILITE | N55: BORD | O55: APPETER | P55: AMURE | Q55: AUTEUR | R55: ARMATEUR | S55: BIRDIE | T55: BALEARISAT | U55: ARMISTICE | V55: ATTOVOLT | W55: ANET | X55: APPARAT | Y55: AIMABLE
A56: AJOURE | C56: BARBARES | D56: ASTRE | E56: ANTICOAGUL | F56: BAVARDAGE | G56: BOUFFES | H56: BALANCE | I56: AMNISTIER | J56: AVIS | K56: CLOS | L56: ASSEMBLER | M56: AME | N56: BOURLINGUE | O56: APPETIT | P56: ANCHOIS | Q56: AUTEURE | R56: ARPAILLEUR | S56: BLOC | T56: BALNEAIRE | U56: ARMURE | W56: ANETH | X56: APPARENCE | Y56: AINE
A57: AJOURER | B57: ASPECT | C57: BATAILLE | D57: ASTROLABE | E57: ANTICORPS | F57: BAVARDER | G57: BOUFFON | H57: BALANCIER | I57: ANI | J57: BAHAI | K57: CODE | L57: ASTUCIEUX | M57: AMELIORER | N57: BOUTIQUE | O57: APPRECIER | P57: ANCRAGE | Q57: AUTOBIOGRA | R57: ARRANGER | S57: BOBSLEIGH | T57: BALUSTRE | U57: ARRETS | V57: AUDACE | W57: ANIER | X57: APPLIQUE | Y57: AISANCE
A58: AJUSTER | B58: ASSYRIEN | C58: BATIMENT | D58: ASTROLOGIE | E58: ANTIDEPRES | F58: BILAN | G58: BOUGIE | H58: BANCAIRE | I58: ANIMER | J58: BAPTEME | K58: COGNITION | L58: ATELIER | M58: AMENER | N58: BRONZER | O58: ARACHIDE | P58: ANCRE | Q58: AUTOFICTIO | R58: ARRENTER | S58: BOCCIA | T58: BANC | U58: ARSENAL | V58: AUGMENTER | W58: ANIL | X58: APPRET | Y58: AJUSTER
A59: ALABASTRE | B59: ATELIER | C59: BIBLE | D59: ASTRONAUTE | E59: ANTIDOTE | F59: BILATÉRAL | G59: BRAVO | H59: BANCO | I59: ANNEXE | J59: BAPTISER | K59: COMMUN | L59: AUBAINE | M59: AMI | N59: BROUILLARD | O59: ARACK | P59: ANCRER | Q59: AUTOGRAPHE | R59: ARRERAGES | S59: BOIS | T59: BANDITE | U59: ARTILLERIE | V59: AUTONOME | W59: ANIMALE | X59: ARAMIDE | Y59: ALERTE
A60: ALAISE | B60: ATTRACTION | C60: BIBLIQUE | D60: ASTRONEF | E60: ANTIGENE | F60: BILLET | G60: BROADWAY | H60: BANQUE | I60: ANNULER | J60: BAPTISTE | K60: COMPLEMENT | L60: AUDACE | M60: AMICAL | N60: BRUME | O60: ARMAGNAC | P60: ANGARIE | Q60: AUTRICE | R60: ARRHER | S60: BORNE | T60: BANLIEUE | U60: ARTILLEUR | V60: AUTORITE | W60: ANIMAUX | X60: ARCHAL | Y60: ALERTER
A61: ALANDIER | B61: AUDITEUR | C61: BIFACE | D61: ASTRONOME | E61: ANTIHISTAM | F61: BLOCUS | G61: BRUIT | H61: BANQUIER | I61: ANTECEDENT | J61: BASILIEN | K61: COMPRENDRE | L61: AUTOMATE | M61: AMIS | N61: BUFFET | O61: ARMOIRE | P61: ANGLE | Q61: AVANTSCENE | R61: ARRHES | S61: BOTTE | T61: BAR | U61: ASKARI | V61: AVARE | W61: ANIS | X61: ARMATURE | Y61: ALLIANCE
A62: ALBATRE | B62: AUDITION | C62: BIOGRAPHIE | D62: ASTRONOMIE | E62: ANTIPSYCHO | F62: BLOG | G62: BUNRAKU | H62: BARATTAGE | I62: APAISER | J62: BASILIQUE | K62: CONCEPT | L62: AUTOMATION | M62: AMITIE | N62: BUNGALOW | O62: AROMATE | P62: ANNEXE | Q62: AVENTURE | R62: ARRIERE | S62: BOULE | T62: BARDAGE | U62: ASPIRANT | V62: BAISSER | W62: ANON | X62: ARMELINE | Y62: ALLIE
A63: ALCAZAR | B63: AUTEUR | C63: BLOCUS | D63: ASTUCIEUX | E63: ANTISEPTIQ | F63: BORNE | G63: BURLESQUE | H63: BAREME | I63: APOSTILLE | J63: BEATIFIER | K63: CONCEPTION | L63: AUTOMOBILE | M63: AMNISTIE | N63: CABINE | O63: AROMATES | P63: ANORDIR | Q63: BAL | R63: ARRIMAGE | S63: BOULISME | T63: BARRAGE | U63: ASSAILLANT | V63: BANQUER | W63: APEX | X63: ARMET | Y63: ALLIER
A64: ALCOVE | B64: BAL | C64: BOIS | D64: ATENUATION | E64: ANTIVIRAL | F64: BOUCHE | G64: BUT | H64: BARON | I64: APPEL | J64: BENIR | K64: CONCEPTUEL | L64: AVANCE | M64: AMNISTIER | N64: CAMPAGNE | O64: AROMATIQUE | P64: ANSE | Q64: BALLADE | R64: ARTEL | S64: BOWLING | T64: BARRIERE | U64: ASSAILLIR | V64: BANQUEROUT | W64: APICULTURE | X64: ARMOIRE | Y64: ALLIES
A65: ALDOSE | B65: BALADEUR | C65: BOUCLIER | D65: ATLAS | E65: ANXIETE | F65: BOYAU | G65: BUTO | H65: BCE | I65: APPELER | J65: BENIT | K65: CONCEVOIR | L65: AXLE | M65: AMOUR | N65: CAMPER | O65: AROME | P65: ANSPECT | Q65: BALLE | R65: ARTISAN | S65: BOXE | T65: BASSIN | U65: ASSAUT | V65: BARRAGE | W65: APPORT | X65: ARMURE | Y65: ALTERITE
A66: ALEE | B66: BALAFON | C66: BOUDDHISME | D66: ATMOSPHERE | E66: AORTE | F66: BOÎTE | G66: CABARET | H66: BEAUTE | I66: APPELS | J66: BENITIER | K66: CONCRET | L66: BALOURDISE | M66: ANALYSE | N66: CAMPEUR | O66: AROMES | P66: ANTENNE | Q66: BALLERINE | R66: ARTISANAL | S66: BOYCOTT | T66: BASTIDE | U66: ASSER | V66: BATTERIE | W66: ARABLE | X66: ARRET | Y66: AMBASSADE
A67: ALESE | B67: BALCON | C67: BREVET | D67: ATOME | E67: APHASIE | F67: BRANCHER | G67: CABOTIN | H67: BENEFICE | I67: APPOINTER | J67: BIBLE | K67: CONCRETE | L67: BANCAIRE | M67: ANCETRE | N67: CAMPING | O67: ARROSER | P67: APIQUER | Q67: BALLET | R67: ARTISANAT | S67: BRASSE | T67: BASTION | U67: ASSIEGER | V67: BESOIN | W67: ARACHIDE | X67: ARRONDI | Y67: AMELIORER
A68: ALGEBRE | B68: BALLERIN | C68: BRIBE | D68: ATTENDRE | E68: APOTHICAIR | F68: BRIEFING | G68: CADRE | H68: BESANT | I68: APPORT | J68: BIBLIQUE | K68: CONNAITRE | L68: BANQUE | M68: ANCETRES | N68: CANTINE | O68: ARTICHAUT | P68: APOTRE | Q68: BARDE | R68: ASSAINIR | S68: BRIDGE | T68: BATI | U68: ASTE | V68: BIOENERGET | W68: ARBRE | X68: ARTISANAL | Y68: AMENER
... A90: AMPHIPRO | B90: BIEN | C90: CHEVALIER | D90: BLEUE | E90: ATTELLE | F90: CHAÎNE | G90: CHOEUR | H90: BRIQUE | I90: ATTEINTE | J90: CATENE | K90: DECISION | L90: BREVETER | M90: ARTS | N90: COMMUNE | O90: BANQUET | P90: ASTROLABE | Q90: CANZONE | R90: BAIL | S90: CENDREE | T90: BOURG | U90: BATAILLE | V90: CALORIFIQU | W90: AVOCAT | X90: BALEINAGE | Y90: ARCHIVE
A91: AMPHORE | B91: BIGUINE | C91: CHRONIQUE | D91: BLUFF | E91: ATTENDRIR | F91: CHEMIN | G91: CHORAL | H91: BRONZE | I91: ATTENTAT | J91: CATHARISME | K91: DEDUCTION | L91: BRICOLEUR | M91: ASPIRER | N91: COMPAGNIE | O91: BARBECUE | Q91: CAPTATIO | R91: BAISSE | S91: CENTRAL | T91: BOURGADE | U91: BATAILLEUR | V91: CALORIQUE | W91: AVOINE | X91: BALEINE | Y91: ARDENT
A92: AMPLEUR | B92: BIJOU | C92: CINEMA | D92: BOITE | E92: ATTENTIF | F92: CHUCHOTER | G92: CHORALE | H92: BRUT | I92: ATTESTER | J92: CATHEDRALE | K92: DEFINI | L92: BRILLANT | M92: ASSENTIR | N92: COMPAGNON | O92: BARDE | P92: ASTRONEF | Q92: CARICATURE | R92: BALANCE | S92: CENTRE | T92: BOURGEOIS | U92: BATAILLON | V92: CANALISER | W92: AZOTE | X92: BALLE | Y92: ARDEUR
A93: ANCIEN | B93: BISCUIT | C93: CITADELLE | D93: BOLIDE | E93: AUDITION | F93: CIBLE | G93: CHORISTE | H93: BUDGET | I93: AUDIENCE | J93: CATHOLIQUE | K93: DEFINIR | L93: BROYEUR | M93: ASSIDU | N93: CONDUCTEUR | O93: BASILIC | P93: ASTRONOMIE | Q93: CASINO | R93: BALANCIER | S93: CERCEAU | T93: BOURGMESTR | U93: BATION | V93: CAPACITE | W93: BACHE | X93: BALLET | Y93: ARME
A94: ANCLEMENT | B94: BISTRE | C94: CITE | D94: BOREAL | E94: AURIFIER | F94: CIRCUIT | G94: CHUTE | H94: BUDGETAIRE | I94: AUDIT | J94: CELEBRER | K94: DEFINITION | L94: BRUIT | M94: ASSISTER | N94: CONFORT | O94: BASSIN | P94: ATLANTIQUE | Q94: CELEBRE | R94: BANCAIRE | S94: CEREBRAL | T94: BOVIDUC | U94: BATTANT | V94: CAPTATION | W94: BAIE | X94: BAMBOU | Y94: ARMEE
A95: ANCRAGE | B95: BIWA | C95: CITOYEN | D95: BOREALE | E95: AUTOMEDICA | F95: CLAIR | G95: CHŒUR | H95: BURSAL | I95: AUDITER | J95: CELESTE | K95: DEGRE | L95: BUTANE | M95: ASSOCIER | O95: BASSINE | P95: ATTERRAGE | Q95: CELEBRITE | R95: BANCO | S95: CESTE | T95: BRANCHE | U95: BATTRE | V95: CAPTEUR | W95: BAIES | X95: BANANE | Y95: ARMISTICE
A96: ANCRE | B96: BLUES | C96: CLASSE | D96: BOUCLE | E96: AUTOPSIE | F96: CLAMEUR | G96: CINEMA | H96: BUTIN | I96: AUTEUR | J96: CELESTIN | K96: DELIMITER | L96: CABLAGE | M96: ASSUMER | N96: CONVOI | O96: BATTERIE | P96: ATTERRIR | Q96: CENACLE | R96: BANQUE | S96: CHALLENGE | T96: BRASSERIE | U96: BAZOOKA | V96: CARACTERE | W96: BALE | X96: BANDANA | Y96: ARTICLE
A97: ANCRER | B97: BOILEAU | C97: CLERC | D97: BRANCHES | E97: AVENANT | F97: CLARIFIER | G97: CINTRE | H97: CADRE | I97: AUTORISER | J97: CELLE | K97: DEMARCHE | L97: CACAO | M97: ATOUT | N97: CORRESPON | O97: BATTRE | P97: ATTERRISSA | Q97: CENSURE | R97: BANQUIER | S97: CHALLENGER | T97: BRECHE | U97: BELLICISME | V97: CARBONE | W97: BALIVEAU | X97: BANDE | Y97: ARTIFICE
A98: ANDAIN | B98: BOIS | C98: CLERGE | D98: BRAS | E98: AVIS | F98: CLARTÉ | G98: CINTRES | H98: CAGNOTTE | I98: AUTORITE | J98: CENACLE | K98: DEMONTRER | L98: CADENCE | M98: ATTACHE | N98: COTE | O98: BECASSE | P98: ATTERRRIR | Q98: CENTON | R98: BARATTAGE | S98: CHAMPION | T98: BRIQUE | U98: BELLICISTE | V98: CARBURANT | W98: BALLOT | X98: BANDEAU | Y98: ASILE
A99: ANDOUILLER | B99: BOLERO | C99: COALITION | D99: BRENNER | E99: AVULSION | F99: CLAVIER | G99: CIRQUE | H99: CAISSE | I99: AVENANT | J99: CENE | K99: DESACCORD | L99: CAFE | M99: ATTACHER | N99: CROISIERE | O99: BECHAMEL | P99: AUBE | Q99: CESURE | R99: BAREME | S99: CHASSE | T99: BRUIT | U99: BELLIGERAN | V99: CARBURE | W99: BAMBOU | X99: BANNETTE | Y99: ASPECT
A100: ANGLE | B100: BOSSA | C100: CODEX | D100: BRILLANCE | E100: BACHELIER | F100: CLIC | G100: CLAQUE | H100: CAISSIER | I100: AVEU | J100: CERTITUDE | K100: DESIGN | L100: CALIBRE | M100: ATTENDRE | N100: CULTURE | O100: BEIGNET | P100: AULNE | Q100: CHAMP | R100: BARON | S100: CHAUSSURE | T100: CADASTRE | U100: BELLIQUEUX | V100: CARBUROL | W100: BANANIER | X100: BAPTISTE | Y100: ASSEMBLEE
A101: ANNEAU | B101: BOULEUR | C101: COEXISTER | D101: BRUME | E101: BACILLE | F101: CLIENT | G101: CLASSIQUE | H101: CALCUL | I101: AVIS | J101: CHABBAT | K101: DESIR | L101: CAMIONNAGE | M101: ATTENTIF | N101: CULTUREL | O101: BERGAMOTE | P101: AURIQUE | Q101: CHANSON | R101: BAZAR | S101: CHELEM | T101: CADRE | U101: BERET | V101: CASQUER | W101: BARBOTER | X101: BAREGE | Y101: ASSEMBLER
A102: ANNEAUX | B102: BOUM | C102: COINCIDER | D102: BULBE | E102: BACTERIE | F102: CLIQUE | G102: CLAVECIN | H102: CAPITAL | I102: AVOCAT | J102: CHAHADA | K102: DESSIN | L102: CANAL | M102: ATTENTION | N102: CURIEUX | O102: BETTERAVE | P102: AUSSIERE | Q102: CHANT | R102: BCE | S102: CHEVAL | T102: CAFE | U102: BIDASSE | V102: CATHODE | W102: BARRAGE | X102: BAROQUE | Y102: ASSISES
A103: ANNELURE | B103: BOURRES | C103: COLLECTION | D103: BUT | E103: BAIN | F103: CODE | G103: CLIMAX | H103: CARTEL | I103: AVOCATE | J103: CHAIRE | K103: DIALOGUE | L103: CAOUTCHOUC | M103: ATTITUDE | N103: CURISTE | O103: BEURRE | P103: AVAL | Q103: CHAPITRE | R103: BEAUTE | S103: CHRONO | T103: CALIDUC | U103: BIFLE | V103: CATION | W103: BASILIC | X103: BARRE | Y103: ASSISTER
A104: ANNEXE | B104: BREAKCORE | C104: COLONIAL | D104: CABOTIN | E104: BANDER | F104: CODEC | G104: CLOWN | H104: CASH | I104: AVOCATS | J104: CHAMAN | K104: DIFFERENCE | L104: CAPABLE | M104: ATTRIBUT | O104: BEURREE | P104: AVANT | Q104: CHEVALERES | R104: BENEFICE | S104: CIRCUIT | T104: CALME | U104: BIGOR | V104: CENTIVOLT | W104: BASSE | X104: BARRETTE | Y104: ASSUMER
A105: ANSE | B105: BRIO | C105: COLONIALE | D105: CADRAN | E105: BARBITURIQ | F105: COHÉRENCE | G105: COMEDIE | H105: CAURIS | I105: AVORTEMENT | J105: CHAMANISME | K105: DIFFUSION | L105: CAPACITE | M105: AUMONE | N105: DEAMBULER | O105: BISCUIT | P105: AVARIE | Q105: CHIASME | R105: BESANT | S105: CLUB | T105: CAMARIN | U105: BIVOUAC | V105: CENTIWATT | W105: BASSIN | X105: BAS | Y105: ASSURE
A106: ANTEF | B106: BRONZE | C106: COLONIE | D106: CALCUL | E106: BASSIN | F106: COLIS | G106: COMEDIEN | H106: CAUTION | I106: AVOUER | J106: CHANOINE | K106: DISCOURS | L106: CAPITAL | M106: AUTEUR | N106: DEBARQUER | O106: BISON | P106: AVENTURE | Q106: CHIMERIQUE | R106: BESOIN | S106: COACH | T106: CAMPANE | U106: BLESS | V106: CENTRALE | W106: BASSINE | X106: BASANE | Y106: ASSURER
A107: ANTENNE | B107: BRUIT | C107: COLONS | D107: CALDERA | E107: BATTRE | F107: COLLOQUE | G107: COMEDIENNE | H107: CAVALERIE | I107: BAIL | J107: CHANTRE | K107: DISCUSSION | L107: CAPTEUR | M107: AUTONOME | N107: DECOUVERTE | O107: BISQUE | P107: AVIATEUR | Q107: CHOSE | R107: BETAIL | S107: COLLECTIF | T107: CAMPO | U107: BLESSE | V107: CENTRIFUGE | W107: BASSINER | X107: BASIN | Y107: ASTUCE
A108: ANTES | B108: BRUITISTE | C108: COMBATTRE | D108: CALENDRIER | E108: BAUME | F108: COLONNE | G108: COMIQUE | H108: CENS | I108: BAN | J108: CHAPELLE | K108: DIVERGENCE | L108: CARBURANT | M108: AUTRUI | N108: DECOUVRIR | O108: BISTROT | P108: AVIATION | Q108: CHRONIQUE | R108: BIEN | S108: COMBAT | T108: CAMPUS | U108: BLESSER | V108: CENTROIDE | W108: BATTAGE | X108: BASKET | Y108: ATOUT
A109: ANTHO | B109: BUDO | C109: COMEDIE | D109: CAMERA | E109: BELLADONE | F109: COMMANDER | G109: COMMUNION | H109: CENTIME | I109: BANC | J109: CHAPITRE | K109: DIVERS | L109: CARBURE | M109: AVANCER | N109: DEFRAYER | O109: BLANCHIR | P109: AVION | Q109: CHRONIQUEU | R109: BIENFAIT | S109: COMBATIF | T109: CANAL | U109: BLEU | V109: CHALEUR | W109: BATTEUSE | X109: BASQUE | Y109: ATTACHE
A110: ANTIQUE | B110: BUNRAKU | C110: COMMANDE | D110: CANCER | E110: BERCER | F110: COMMENTER | G110: COMPAGNIE | H110: CENTRALE | I110: BARRE | J110: CHARIA | K110: DOCTRINE | L110: CARTEL | M110: AVENIR | N110: DEGUSTER | O110: BLANQUETTE | P110: AVIONIQUE | Q110: CINEASTE | R110: BIENS | S110: COMITE | T110: CANISAC | U110: BLINDAGE | V110: CHAMP | W110: BAUGE | X110: BASSINET | Y110: ATTENDRE
A111: ANTIS | B111: BUSTE | C111: COMMERCE | D111: CANICULE | E111: BESOIN | F111: COMMERCE | G111: COMPOSER | H111: CHANGE | I111: BARREAU | J111: CHARITE | K111: DOGME | L111: CARTON | M111: AVERTIR | N111: DEPART | O111: BLETTE | P111: AVIRON | Q111: CITATION | R111: BIFFAGE | S111: CONCOURIR | T111: CANIVEAU | U111: BLINDE | V111: CHARBON | W111: BECHE | X111: BASTE | Y111: ATTENTAT
A112: APERCU | B112: BUTO | C112: COMMUNE | D112: CAPSULE | E112: BICHONNER | F112: COMMUNION | G112: COMPTINE | H112: CHANGER | I112: BAUX | J112: CHARTREUX | K112: DOMAINE | L112: CARTONNAGE | M112: AVEU | N112: DEPARTEMEN | O112: BOCAL | P112: AVISO | R112: BIFFETON | S112: CONTRE | T112: CANTON | U112: BLOCUS | V112: CHARGE | W112: BERGERIE | X112: BATAVIA | Y112: ATTENTIF
A113: APERTURE | B113: BYZANTIN | C113: COMPARER | D113: CAPTEUR | E113: BIENETRE | F113: COMPTE | G113: COMPTOIR | H113: CHANGEUR | I113: BENEFICE | J113: CHASTE | K113: DONNE | L113: CARTOUCHE | M113: AVIS | N113: DEPLACEME | O113: BOCAUX | P113: AZIMUT | R113: BIGAILLE | S113: CORDE | T113: CAPITOLE | U113: BOMBARDE | V113: CHAUD | W113: BETAIL | X113: BATI | Y113: ATTITUDE
A114: APLANIR | B114: CABOT | C114: COMPLOT | D114: CARDANER | E114: BILE | F114: CONCERTER | G114: CONCERT | H114: CHARGE | I114: BIEN | J114: CHASUBLE | K114: DONNEE | L114: CASQUE | M114: AVISER | N114: DESTINATIO | O114: BOEUF | P114: AZUR | Q114: CLASSIQUE | R114: BIJOUTERIE | S114: CORNER | T114: CAROLE | U114: BOMBARDEME | V114: CHAUDIERE | W114: BETTE | X114: BATIE | Y114: AUDIENCE
A115: APLAT | B115: CABOTIN | C115: CONCORDAT | D115: CARME | E115: BILLARD | F115: CONCISION | G115: CONTES | H115: CHEQUE | I115: BIENFAIT | J115: CHIISME | K115: DOUTE | L115: CELLULOSE | M115: AVOCAT | N115: DEVELOPPEM | O115: BOIRE | P115: BABORD | Q115: CLERIHEW | R115: BIJOUX | S115: COULOIR | T115: CARREFOUR | U115: BOMBARDER | V115: CHAUFFAGE | W115: BETTERAVE | X115: BATIK | Y115: AUDIENCES
A116: APLATI | B116: CADENCE | C116: CONFLIT | D116: CARREFOUR | E116: BIOCHIMIE | F116: CONFIRMER | G116: CONTEUR | H116: CHEQUIER | I116: BIENS | J116: CHISME | K116: DROIT | L116: CENTRALE | M116: AXE | N116: DEVELOPPER | O116: BOL | P116: BAC | Q116: CLIMAX | R116: BILAN | S116: COUP | T116: CASBAH | U116: BOMBARDIER | V116: CHIMIE | W116: BIEF | X116: BATIR | Y116: AUTORISER
A117: APLOMB | B117: CALLIGRAPH | C117: CONQUERIR | D117: CARTE | F117: CONNECTER | G117: COR | H117: CHER | I117: BILAN | J117: CHORAL | K117: DUALITE | L117: CERAMIQUE | M117: AXIOME | N117: DILIGENCE | O117: BONHEUR | P117: BAGNOLE | Q117: CODA | R117: BILLET | S117: COUPE | T117: CASERNE | U117: BOMBE | V117: CHIMIQUE | W117: BINAGE | X117: BATISTE | Y117: AUTORITE
A118: APOPHYSE | B118: CALYPSO | C118: CONQUETE | D118: CARTES | E118: BIOLOGIE | F118: CONNEXION | G118: CORBEILLE | H118: CHERTE | I118: BILLET | J118: CHRETIEN | K118: DUREE | L118: CEREALE | M118: AXIOMES | N118: DIVERSIFIC | O118: BORDELAISE | P118: BAIE | Q118: COLLABORAT | R118: BILLON | S118: COURAGEUX | T118: CASINO | U118: BONNET | V118: CHLOROPLAS | W118: BINER | X118: BAVETTE | Y118: AVANCE
A119: APPENTIS | B119: CAMAIEU | C119: CONSULAT | D119: CEINTURE | E119: BIOMEDICAL | F119: CONSENSUS | G119: CORDAGE | H119: CHOMAGE | I119: BLAMER | J119: CHRETIENTE | K119: EBAUCHE | L119: CERTIFIER | M119: BAR | N119: DOUANE | O119: BORTSCH | P119: BAIGNADE | Q119: COMEDIE | R119: BITCOIN | S119: COUREUR | T119: CASTEL | U119: BORDEE | V119: CHOC | W119: BINETTE | X119: BAVOIR | Y119: AVANCER
A120: APPLIQUE | B120: CAMEE | C120: CONTE | D120: CELESTE | E120: BIOPSIE | F120: CONSOLE | G120: CORDE | H120: CHUTE | I120: BLANCHIR | J120: CIEL | K120: ECART | L120: CHAINE | M120: BARBARE | N120: EAU | O120: BOUCHE | P120: BAIGNER | Q120: COMEDIEN | R120: BLANC | S120: COURIR | T120: CENTRALE | U120: BOUCHERIE | V120: CINETIQUE | W120: BIOLOGIE | X120: BEAUTE | Y120: AVANCES
A121: APPOINTER | B121: CAMERA | C121: CONTER | D121: CENTAURE | E121: BISTOURI | F121: CONSULTER | G121: CORPS | H121: CIRCUIT | I121: BORDEREAU | J121: CIERGE | K121: ECHANGE | L121: CHALEUR | M121: BAS | N121: ECONOMIE | O121: BOUDIN | P121: BAILLE | Q121: COMEDIENNE | R121: BLASON | S121: COURSE | T121: CENTRALISE | U121: BOUCLIER | V121: CIRCUIT | W121: BIOLOGIQUE | X121: BECQUET | Y121: AVENIR
A122: APPRETER | B122: CANCAN | C122: CONTEUR | D122: CERES | E122: BLESSE | F122: CONTACT | G122: COSTUMES | H122: CIRCULANT | I122: BREVET | J122: CLARISSES | K122: ECONOMIE | L122: CHAMOTTE | M122: BASE | N122: ECONOMIQUE | O122: BOUFFE | P122: BALADE | Q122: COMIQUE | R122: BLATIER | S122: COURT | T122: CENTRE | U122: BOULET | V122: CLAQUER | W122: BIQUE | X122: BEGUIN | Y122: AVENIRS
A123: APPUI | B123: CANEVAS | C123: CONTEXTE | D123: CHALDEEN | E123: BLESSER | F123: CONTACTER | G123: COSTUMIER | H123: CLAUSE | I123: BULLETIN | J123: CLEMENCE | K123: ECONOMIQUE | L123: CHANTIER | M123: BENEVOLAT | O123: BOUILLI | P123: BALANCIER | Q123: COMMENTAIR | R123: BLE | S123: CRAMPON | T123: CENTRES | U123: BOURGEOISI | V123: COEUR | W123: BLE | X123: BEIGE | Y123: AVERTIR
A124: APPUIS | B124: CANON | C124: CONTRE | D124: CHALEUR | E124: BLESSURE | F124: CONTAGION | G124: COULISSE | H124: CLIENT | I124: CADASTRE | J124: CLERC | K124: ECRITURE | L124: CHANVRE | M124: BIBLE | N124: EGARE | O124: BOUILLON | P124: BALEINE | Q124: COMMENTATE | R124: BLOCKCHAIN | S124: CRAWL | T124: CENTREVILL | U124: BOXE | V124: COHESION | W124: BLUET | X124: BEQUET | Y124: AVEU
...

Sheet RÉCAP GLOBAL
A1: MAQUETTE | B1: TOTAL MOTS
A2: M1 | B2: =SUM(M1!C3:C22) -> 14082
A3: M2 | B3: =SUM(M2!C3:C22) -> 15174
A4: M3 | B4: =SUM(M3!C3:C22) -> 18389
A5: M4 | B5: =SUM(M4!C3:C22) -> 12847
A6: M5 | B6: =SUM(M5!C3:C27) -> 18974
A7: TOTAL GÉNÉRAL | B7: =SUM(B2:B6) -> 79466
